Workbook
Name OLE_LINK7: 元康盛景30号!$N$14

Sheet 申购数据-每日更新-0515
B1: 元康盛景17号 | C1: 元康盛景9号 | D1: 元康盛景20号 | E1: 元康盛景1号 | F1: 元康衡景1号私募证券投资基金B | G1: 元康盛景31号私募证券投资基金A | H1: 元康盛景28号A | I1: 元康盛景22号 | J1: 元康瑞景2号基础设施策略B | K1: 元康盛景29号私募证券投资基金 | L1: 元康全景1号私募证券投资基金B | M1: 元康盛景26号 | N1: 元康星辰量化4号
A2: 2026/05/15 | D2: 申购:雪球:16,300,000元,美市:1,035,000元 | F2: 申购:美市:1,000,000元 | G2: 申购:美市:14,000,000元 | H2: 申购:美市:3,250,000元 | M2: 申购:美市:4,500,000元 | N2: 赎回:美市:1,400,000份
A3: 2026/05/18 | G3: 申购:美市:1,500,000元 | H3: 赎回:美市:1,410,000份
A4: 2026/05/19 | C4: 赎回:联储:3,831,969份 | G4: 申购:美市:5,000,000元 | J4: 申购:美市:1,000,000元 | K4: 申购:美市:200,000元; 赎回:美市:700,000份 | L4: 申购:美市:100,000元
A5: 2026/05/20 | E5: 申购:美市:8,600,000元; 赎回:美市:2,722,460份
A6: 2026/05/21 | I6: 赎回:美市:6,889,278份
A7: 2026/05/25 | H7: 赎回:美市:1,240,000份
A8: 2026/05/26 | C8: 赎回:联储:5,899,357份 | D8: 赎回:雪球:1,102,424份,美市:1,324,389份 | I8: 赎回:美市:150,000份
A9: 2026/05/27 | H9: 赎回:美市:23,115,175份
A10: 2026/06/01 | H10: 赎回:美市:2,070,000份
A11: 2026/06/02 | K11: 赎回:美市:900,000份
A12: 2026/06/03 | B12: 赎回:雪球:681,199份 | E12: 赎回:美市:1,072,246份
A13: 2026/06/08 | H13: 赎回:美市:5,950,000份
A14: 2026/06/09 | I14: 赎回:美市:803,235份 | K14: 赎回:美市:290,000份
A15: 2026/06/10 | B15: 赎回:雪球:181,620份 | E15: 赎回:美市:107,225份
A16: 2026/06/16 | K16: 赎回:美市:1,000,000份
A17: 2026/06/22 | H17: 赎回:美市:28,430,000份
A18: 2026/06/24 | E18: 赎回:美市:59,785,584份 | L18: 申购:美市:100,000元 | N18: 申购:美市:100,000元
A19: 2026/06/25 | D19: 赎回:美市:2,403,376份 | I19: 赎回:美市:1,617,338份
A20: 2026/06/29 | H20: 赎回:美市:3,490,000份
A22: （内容由AI生成，仅供参考）

Sheet 汇总
A1: 日期 | B1: 元康盛景20号 | C1: 元康盛景26号 | D1: 元康盛景28号 | E1: 外贸信托_元康盛景1号 | F1: 苏信优先级Z2501 | G1: 苏信次级Z2502 | H1: 元康1号 | I1: 元康9号 | J1: 元康12号 | K1: 元康17号 | L1: 朗瑞1_5 | M1: 朗瑞1_8 | N1: 元康盛景29号 | O1: 元康盛景30号 | P1: 鹏雅119 | Q1: 鹏雅120 | R1: 中建投_臻泉2号 | S1: 慧聚领航1号 | T1: 苏信混合Z2603
A2: 46023 | B2: {=INDEX(_xlfn._xlws.FILTER(INDIRECT(B1&"!$E1:$E10000"),INDIRECT(B1&"!$a1:$a10000")=汇总!$A2),COUNTIF(INDIRECT(B1&"!$a1:$a10000"),汇总!$A2))} -> 619 | C2: {=INDEX(_xlfn._xlws.FILTER(INDIRECT(C1&"!$E1:$E10000"),INDIRECT(C1&"!$a1:$a10000")=汇总!$A2),COUNTIF(INDIRECT(C1&"!$a1:$a10000"),汇总!$A2))} -> 4182 | D2: {=INDEX(_xlfn._xlws.FILTER(INDIRECT(D1&"!$E1:$E10000"),INDIRECT(D1&"!$a1:$a10000")=汇总!$A2),COUNTIF(INDIRECT(D1&"!$a1:$a10000"),汇总!$A2))} -> 97 | E2: {=INDEX(_xlfn._xlws.FILTER(INDIRECT(E1&"!$E1:$E10000"),INDIRECT(E1&"!$a1:$a10000")=汇总!$A2),COUNTIF(INDIRECT(E1&"!$a1:$a10000"),汇总!$A2))} -> #VALUE! | F2: {=INDEX(_xlfn._xlws.FILTER(INDIRECT(F1&"!$E1:$E10000"),INDIRECT(F1&"!$a1:$a10000")=汇总!$A2),COUNTIF(INDIRECT(F1&"!$a1:$a10000"),汇总!$A2))} -> 192 | G2: {=INDEX(_xlfn._xlws.FILTER(INDIRECT(G1&"!$E1:$E10000"),INDIRECT(G1&"!$a1:$a10000")=汇总!$A2),COUNTIF(INDIRECT(G1&"!$a1:$a10000"),汇总!$A2))} -> 202 | H2: {=INDEX(_xlfn._xlws.FILTER(INDIRECT(H1&"!$E1:$E10000"),INDIRECT(H1&"!$a1:$a10000")=汇总!$A2),COUNTIF(INDIRECT(H1&"!$a1:$a10000"),汇总!$A2))} -> 151 | I2: {=INDEX(_xlfn._xlws.FILTER(INDIRECT(I1&"!$E1:$E10000"),INDIRECT(I1&"!$a1:$a10000")=汇总!$A2),COUNTIF(INDIRECT(I1&"!$a1:$a10000"),汇总!$A2))} -> 11 | ... S2: {=INDEX(_xlfn._xlws.FILTER(INDIRECT(S1&"!$E1:$E10000"),INDIRECT(S1&"!$a1:$a10000")=汇总!$A2),COUNTIF(INDIRECT(S1&"!$a1:$a10000"),汇总!$A2))} -> #VALUE!
A3: =+A2+1 -> 46024 | B3: {=IFERROR(INDEX(_xlfn._xlws.FILTER(INDIRECT(B$1&"!$E1:$E10000"),INDIRECT(B$1&"!$a1:$a10000")=汇总!$A3),COUNTIF(INDIRECT(B$1&"!$a1:$a10000"),汇总!$A3)),B2)} -> 619 | C3: {=IFERROR(INDEX(_xlfn._xlws.FILTER(INDIRECT(C$1&"!$E1:$E10000"),INDIRECT(C$1&"!$a1:$a10000")=汇总!$A3),COUNTIF(INDIRECT(C$1&"!$a1:$a10000"),汇总!$A3)),C2)} -> 4182 | D3: {=IFERROR(INDEX(_xlfn._xlws.FILTER(INDIRECT(D$1&"!$E1:$E10000"),INDIRECT(D$1&"!$a1:$a10000")=汇总!$A3),COUNTIF(INDIRECT(D$1&"!$a1:$a10000"),汇总!$A3)),D2)} -> 97 | E3: {=IFERROR(INDEX(_xlfn._xlws.FILTER(INDIRECT(E$1&"!$E1:$E10000"),INDIRECT(E$1&"!$a1:$a10000")=汇总!$A3),COUNTIF(INDIRECT(E$1&"!$a1:$a10000"),汇总!$A3)),E2)} -> #VALUE! | F3: {=IFERROR(INDEX(_xlfn._xlws.FILTER(INDIRECT(F$1&"!$E1:$E10000"),INDIRECT(F$1&"!$a1:$a10000")=汇总!$A3),COUNTIF(INDIRECT(F$1&"!$a1:$a10000"),汇总!$A3)),F2)} -> 192 | G3: {=IFERROR(INDEX(_xlfn._xlws.FILTER(INDIRECT(G$1&"!$E1:$E10000"),INDIRECT(G$1&"!$a1:$a10000")=汇总!$A3),COUNTIF(INDIRECT(G$1&"!$a1:$a10000"),汇总!$A3)),G2)} -> 202 | H3: {=IFERROR(INDEX(_xlfn._xlws.FILTER(INDIRECT(H$1&"!$E1:$E10000"),INDIRECT(H$1&"!$a1:$a10000")=汇总!$A3),COUNTIF(INDIRECT(H$1&"!$a1:$a10000"),汇总!$A3)),H2)} -> 151 | I3: {=IFERROR(INDEX(_xlfn._xlws.FILTER(INDIRECT(I$1&"!$E1:$E10000"),INDIRECT(I$1&"!$a1:$a10000")=汇总!$A3),COUNTIF(INDIRECT(I$1&"!$a1:$a10000"),汇总!$A3)),I2)} -> 11 | ... S3: {=IFERROR(INDEX(_xlfn._xlws.FILTER(INDIRECT(S$1&"!$E1:$E10000"),INDIRECT(S$1&"!$a1:$a10000")=汇总!$A3),COUNTIF(INDIRECT(S$1&"!$a1:$a10000"),汇总!$A3)),S2)} -> #VALUE!
A4: =+A3+1 -> 46025 | B4: {=IFERROR(INDEX(_xlfn._xlws.FILTER(INDIRECT(B$1&"!$E1:$E10000"),INDIRECT(B$1&"!$a1:$a10000")=汇总!$A4),COUNTIF(INDIRECT(B$1&"!$a1:$a10000"),汇总!$A4)),B3)} -> 619 | C4: {=IFERROR(INDEX(_xlfn._xlws.FILTER(INDIRECT(C$1&"!$E1:$E10000"),INDIRECT(C$1&"!$a1:$a10000")=汇总!$A4),COUNTIF(INDIRECT(C$1&"!$a1:$a10000"),汇总!$A4)),C3)} -> 4182 | D4: {=IFERROR(INDEX(_xlfn._xlws.FILTER(INDIRECT(D$1&"!$E1:$E10000"),INDIRECT(D$1&"!$a1:$a10000")=汇总!$A4),COUNTIF(INDIRECT(D$1&"!$a1:$a10000"),汇总!$A4)),D3)} -> 97 | E4: {=IFERROR(INDEX(_xlfn._xlws.FILTER(INDIRECT(E$1&"!$E1:$E10000"),INDIRECT(E$1&"!$a1:$a10000")=汇总!$A4),COUNTIF(INDIRECT(E$1&"!$a1:$a10000"),汇总!$A4)),E3)} -> #VALUE! | F4: {=IFERROR(INDEX(_xlfn._xlws.FILTER(INDIRECT(F$1&"!$E1:$E10000"),INDIRECT(F$1&"!$a1:$a10000")=汇总!$A4),COUNTIF(INDIRECT(F$1&"!$a1:$a10000"),汇总!$A4)),F3)} -> 192 | G4: {=IFERROR(INDEX(_xlfn._xlws.FILTER(INDIRECT(G$1&"!$E1:$E10000"),INDIRECT(G$1&"!$a1:$a10000")=汇总!$A4),COUNTIF(INDIRECT(G$1&"!$a1:$a10000"),汇总!$A4)),G3)} -> 202 | H4: {=IFERROR(INDEX(_xlfn._xlws.FILTER(INDIRECT(H$1&"!$E1:$E10000"),INDIRECT(H$1&"!$a1:$a10000")=汇总!$A4),COUNTIF(INDIRECT(H$1&"!$a1:$a10000"),汇总!$A4)),H3)} -> 151 | I4: {=IFERROR(INDEX(_xlfn._xlws.FILTER(INDIRECT(I$1&"!$E1:$E10000"),INDIRECT(I$1&"!$a1:$a10000")=汇总!$A4),COUNTIF(INDIRECT(I$1&"!$a1:$a10000"),汇总!$A4)),I3)} -> 11 | ... S4: {=IFERROR(INDEX(_xlfn._xlws.FILTER(INDIRECT(S$1&"!$E1:$E10000"),INDIRECT(S$1&"!$a1:$a10000")=汇总!$A4),COUNTIF(INDIRECT(S$1&"!$a1:$a10000"),汇总!$A4)),S3)} -> #VALUE!
A5: =+A4+1 -> 46026 | B5: {=IFERROR(INDEX(_xlfn._xlws.FILTER(INDIRECT(B$1&"!$E1:$E10000"),INDIRECT(B$1&"!$a1:$a10000")=汇总!$A5),COUNTIF(INDIRECT(B$1&"!$a1:$a10000"),汇总!$A5)),B4)} -> 619 | C5: {=IFERROR(INDEX(_xlfn._xlws.FILTER(INDIRECT(C$1&"!$E1:$E10000"),INDIRECT(C$1&"!$a1:$a10000")=汇总!$A5),COUNTIF(INDIRECT(C$1&"!$a1:$a10000"),汇总!$A5)),C4)} -> 4182 | D5: {=IFERROR(INDEX(_xlfn._xlws.FILTER(INDIRECT(D$1&"!$E1:$E10000"),INDIRECT(D$1&"!$a1:$a10000")=汇总!$A5),COUNTIF(INDIRECT(D$1&"!$a1:$a10000"),汇总!$A5)),D4)} -> 97 | E5: {=IFERROR(INDEX(_xlfn._xlws.FILTER(INDIRECT(E$1&"!$E1:$E10000"),INDIRECT(E$1&"!$a1:$a10000")=汇总!$A5),COUNTIF(INDIRECT(E$1&"!$a1:$a10000"),汇总!$A5)),E4)} -> #VALUE! | F5: {=IFERROR(INDEX(_xlfn._xlws.FILTER(INDIRECT(F$1&"!$E1:$E10000"),INDIRECT(F$1&"!$a1:$a10000")=汇总!$A5),COUNTIF(INDIRECT(F$1&"!$a1:$a10000"),汇总!$A5)),F4)} -> 192 | G5: {=IFERROR(INDEX(_xlfn._xlws.FILTER(INDIRECT(G$1&"!$E1:$E10000"),INDIRECT(G$1&"!$a1:$a10000")=汇总!$A5),COUNTIF(INDIRECT(G$1&"!$a1:$a10000"),汇总!$A5)),G4)} -> 202 | H5: {=IFERROR(INDEX(_xlfn._xlws.FILTER(INDIRECT(H$1&"!$E1:$E10000"),INDIRECT(H$1&"!$a1:$a10000")=汇总!$A5),COUNTIF(INDIRECT(H$1&"!$a1:$a10000"),汇总!$A5)),H4)} -> 151 | I5: {=IFERROR(INDEX(_xlfn._xlws.FILTER(INDIRECT(I$1&"!$E1:$E10000"),INDIRECT(I$1&"!$a1:$a10000")=汇总!$A5),COUNTIF(INDIRECT(I$1&"!$a1:$a10000"),汇总!$A5)),I4)} -> 11 | ... S5: {=IFERROR(INDEX(_xlfn._xlws.FILTER(INDIRECT(S$1&"!$E1:$E10000"),INDIRECT(S$1&"!$a1:$a10000")=汇总!$A5),COUNTIF(INDIRECT(S$1&"!$a1:$a10000"),汇总!$A5)),S4)} -> #VALUE!
A6: =+A5+1 -> 46027 | B6: {=IFERROR(INDEX(_xlfn._xlws.FILTER(INDIRECT(B$1&"!$E1:$E10000"),INDIRECT(B$1&"!$a1:$a10000")=汇总!$A6),COUNTIF(INDIRECT(B$1&"!$a1:$a10000"),汇总!$A6)),B5)} -> 619 | C6: {=IFERROR(INDEX(_xlfn._xlws.FILTER(INDIRECT(C$1&"!$E1:$E10000"),INDIRECT(C$1&"!$a1:$a10000")=汇总!$A6),COUNTIF(INDIRECT(C$1&"!$a1:$a10000"),汇总!$A6)),C5)} -> 2377 | D6: {=IFERROR(INDEX(_xlfn._xlws.FILTER(INDIRECT(D$1&"!$E1:$E10000"),INDIRECT(D$1&"!$a1:$a10000")=汇总!$A6),COUNTIF(INDIRECT(D$1&"!$a1:$a10000"),汇总!$A6)),D5)} -> 97 | E6: {=IFERROR(INDEX(_xlfn._xlws.FILTER(INDIRECT(E$1&"!$E1:$E10000"),INDIRECT(E$1&"!$a1:$a10000")=汇总!$A6),COUNTIF(INDIRECT(E$1&"!$a1:$a10000"),汇总!$A6)),E5)} -> #VALUE! | F6: {=IFERROR(INDEX(_xlfn._xlws.FILTER(INDIRECT(F$1&"!$E1:$E10000"),INDIRECT(F$1&"!$a1:$a10000")=汇总!$A6),COUNTIF(INDIRECT(F$1&"!$a1:$a10000"),汇总!$A6)),F5)} -> 192 | G6: {=IFERROR(INDEX(_xlfn._xlws.FILTER(INDIRECT(G$1&"!$E1:$E10000"),INDIRECT(G$1&"!$a1:$a10000")=汇总!$A6),COUNTIF(INDIRECT(G$1&"!$a1:$a10000"),汇总!$A6)),G5)} -> 202 | H6: {=IFERROR(INDEX(_xlfn._xlws.FILTER(INDIRECT(H$1&"!$E1:$E10000"),INDIRECT(H$1&"!$a1:$a10000")=汇总!$A6),COUNTIF(INDIRECT(H$1&"!$a1:$a10000"),汇总!$A6)),H5)} -> 151 | I6: {=IFERROR(INDEX(_xlfn._xlws.FILTER(INDIRECT(I$1&"!$E1:$E10000"),INDIRECT(I$1&"!$a1:$a10000")=汇总!$A6),COUNTIF(INDIRECT(I$1&"!$a1:$a10000"),汇总!$A6)),I5)} -> 11 | ... S6: {=IFERROR(INDEX(_xlfn._xlws.FILTER(INDIRECT(S$1&"!$E1:$E10000"),INDIRECT(S$1&"!$a1:$a10000")=汇总!$A6),COUNTIF(INDIRECT(S$1&"!$a1:$a10000"),汇总!$A6)),S5)} -> #VALUE!
A7: =+A6+1 -> 46028 | B7: {=IFERROR(INDEX(_xlfn._xlws.FILTER(INDIRECT(B$1&"!$E1:$E10000"),INDIRECT(B$1&"!$a1:$a10000")=汇总!$A7),COUNTIF(INDIRECT(B$1&"!$a1:$a10000"),汇总!$A7)),B6)} -> 619 | C7: {=IFERROR(INDEX(_xlfn._xlws.FILTER(INDIRECT(C$1&"!$E1:$E10000"),INDIRECT(C$1&"!$a1:$a10000")=汇总!$A7),COUNTIF(INDIRECT(C$1&"!$a1:$a10000"),汇总!$A7)),C6)} -> 2377 | D7: {=IFERROR(INDEX(_xlfn._xlws.FILTER(INDIRECT(D$1&"!$E1:$E10000"),INDIRECT(D$1&"!$a1:$a10000")=汇总!$A7),COUNTIF(INDIRECT(D$1&"!$a1:$a10000"),汇总!$A7)),D6)} -> 97 | E7: {=IFERROR(INDEX(_xlfn._xlws.FILTER(INDIRECT(E$1&"!$E1:$E10000"),INDIRECT(E$1&"!$a1:$a10000")=汇总!$A7),COUNTIF(INDIRECT(E$1&"!$a1:$a10000"),汇总!$A7)),E6)} -> 295.8 | F7: {=IFERROR(INDEX(_xlfn._xlws.FILTER(INDIRECT(F$1&"!$E1:$E10000"),INDIRECT(F$1&"!$a1:$a10000")=汇总!$A7),COUNTIF(INDIRECT(F$1&"!$a1:$a10000"),汇总!$A7)),F6)} -> 192 | G7: {=IFERROR(INDEX(_xlfn._xlws.FILTER(INDIRECT(G$1&"!$E1:$E10000"),INDIRECT(G$1&"!$a1:$a10000")=汇总!$A7),COUNTIF(INDIRECT(G$1&"!$a1:$a10000"),汇总!$A7)),G6)} -> 202 | H7: {=IFERROR(INDEX(_xlfn._xlws.FILTER(INDIRECT(H$1&"!$E1:$E10000"),INDIRECT(H$1&"!$a1:$a10000")=汇总!$A7),COUNTIF(INDIRECT(H$1&"!$a1:$a10000"),汇总!$A7)),H6)} -> 601 | I7: {=IFERROR(INDEX(_xlfn._xlws.FILTER(INDIRECT(I$1&"!$E1:$E10000"),INDIRECT(I$1&"!$a1:$a10000")=汇总!$A7),COUNTIF(INDIRECT(I$1&"!$a1:$a10000"),汇总!$A7)),I6)} -> 11 | ... S7: {=IFERROR(INDEX(_xlfn._xlws.FILTER(INDIRECT(S$1&"!$E1:$E10000"),INDIRECT(S$1&"!$a1:$a10000")=汇总!$A7),COUNTIF(INDIRECT(S$1&"!$a1:$a10000"),汇总!$A7)),S6)} -> #VALUE!
A8: =+A7+1 -> 46029 | B8: {=IFERROR(INDEX(_xlfn._xlws.FILTER(INDIRECT(B$1&"!$E1:$E10000"),INDIRECT(B$1&"!$a1:$a10000")=汇总!$A8),COUNTIF(INDIRECT(B$1&"!$a1:$a10000"),汇总!$A8)),B7)} -> 164 | C8: {=IFERROR(INDEX(_xlfn._xlws.FILTER(INDIRECT(C$1&"!$E1:$E10000"),INDIRECT(C$1&"!$a1:$a10000")=汇总!$A8),COUNTIF(INDIRECT(C$1&"!$a1:$a10000"),汇总!$A8)),C7)} -> 253 | D8: {=IFERROR(INDEX(_xlfn._xlws.FILTER(INDIRECT(D$1&"!$E1:$E10000"),INDIRECT(D$1&"!$a1:$a10000")=汇总!$A8),COUNTIF(INDIRECT(D$1&"!$a1:$a10000"),汇总!$A8)),D7)} -> 97 | E8: {=IFERROR(INDEX(_xlfn._xlws.FILTER(INDIRECT(E$1&"!$E1:$E10000"),INDIRECT(E$1&"!$a1:$a10000")=汇总!$A8),COUNTIF(INDIRECT(E$1&"!$a1:$a10000"),汇总!$A8)),E7)} -> 4613.7975 | F8: {=IFERROR(INDEX(_xlfn._xlws.FILTER(INDIRECT(F$1&"!$E1:$E10000"),INDIRECT(F$1&"!$a1:$a10000")=汇总!$A8),COUNTIF(INDIRECT(F$1&"!$a1:$a10000"),汇总!$A8)),F7)} -> 192 | G8: {=IFERROR(INDEX(_xlfn._xlws.FILTER(INDIRECT(G$1&"!$E1:$E10000"),INDIRECT(G$1&"!$a1:$a10000")=汇总!$A8),COUNTIF(INDIRECT(G$1&"!$a1:$a10000"),汇总!$A8)),G7)} -> 202 | H8: {=IFERROR(INDEX(_xlfn._xlws.FILTER(INDIRECT(H$1&"!$E1:$E10000"),INDIRECT(H$1&"!$a1:$a10000")=汇总!$A8),COUNTIF(INDIRECT(H$1&"!$a1:$a10000"),汇总!$A8)),H7)} -> 601 | I8: {=IFERROR(INDEX(_xlfn._xlws.FILTER(INDIRECT(I$1&"!$E1:$E10000"),INDIRECT(I$1&"!$a1:$a10000")=汇总!$A8),COUNTIF(INDIRECT(I$1&"!$a1:$a10000"),汇总!$A8)),I7)} -> 11 | ... S8: {=IFERROR(INDEX(_xlfn._xlws.FILTER(INDIRECT(S$1&"!$E1:$E10000"),INDIRECT(S$1&"!$a1:$a10000")=汇总!$A8),COUNTIF(INDIRECT(S$1&"!$a1:$a10000"),汇总!$A8)),S7)} -> #VALUE!
A9: =+A8+1 -> 46030 | B9: {=IFERROR(INDEX(_xlfn._xlws.FILTER(INDIRECT(B$1&"!$E1:$E10000"),INDIRECT(B$1&"!$a1:$a10000")=汇总!$A9),COUNTIF(INDIRECT(B$1&"!$a1:$a10000"),汇总!$A9)),B8)} -> 164 | C9: {=IFERROR(INDEX(_xlfn._xlws.FILTER(INDIRECT(C$1&"!$E1:$E10000"),INDIRECT(C$1&"!$a1:$a10000")=汇总!$A9),COUNTIF(INDIRECT(C$1&"!$a1:$a10000"),汇总!$A9)),C8)} -> 2486 | D9: {=IFERROR(INDEX(_xlfn._xlws.FILTER(INDIRECT(D$1&"!$E1:$E10000"),INDIRECT(D$1&"!$a1:$a10000")=汇总!$A9),COUNTIF(INDIRECT(D$1&"!$a1:$a10000"),汇总!$A9)),D8)} -> 97 | E9: {=IFERROR(INDEX(_xlfn._xlws.FILTER(INDIRECT(E$1&"!$E1:$E10000"),INDIRECT(E$1&"!$a1:$a10000")=汇总!$A9),COUNTIF(INDIRECT(E$1&"!$a1:$a10000"),汇总!$A9)),E8)} -> 1100.2633 | F9: {=IFERROR(INDEX(_xlfn._xlws.FILTER(INDIRECT(F$1&"!$E1:$E10000"),INDIRECT(F$1&"!$a1:$a10000")=汇总!$A9),COUNTIF(INDIRECT(F$1&"!$a1:$a10000"),汇总!$A9)),F8)} -> 199.56 | G9: {=IFERROR(INDEX(_xlfn._xlws.FILTER(INDIRECT(G$1&"!$E1:$E10000"),INDIRECT(G$1&"!$a1:$a10000")=汇总!$A9),COUNTIF(INDIRECT(G$1&"!$a1:$a10000"),汇总!$A9)),G8)} -> 202 | H9: {=IFERROR(INDEX(_xlfn._xlws.FILTER(INDIRECT(H$1&"!$E1:$E10000"),INDIRECT(H$1&"!$a1:$a10000")=汇总!$A9),COUNTIF(INDIRECT(H$1&"!$a1:$a10000"),汇总!$A9)),H8)} -> 601 | I9: {=IFERROR(INDEX(_xlfn._xlws.FILTER(INDIRECT(I$1&"!$E1:$E10000"),INDIRECT(I$1&"!$a1:$a10000")=汇总!$A9),COUNTIF(INDIRECT(I$1&"!$a1:$a10000"),汇总!$A9)),I8)} -> 11 | ... S9: {=IFERROR(INDEX(_xlfn._xlws.FILTER(INDIRECT(S$1&"!$E1:$E10000"),INDIRECT(S$1&"!$a1:$a10000")=汇总!$A9),COUNTIF(INDIRECT(S$1&"!$a1:$a10000"),汇总!$A9)),S8)} -> #VALUE!
A10: =+A9+1 -> 46031 | B10: {=IFERROR(INDEX(_xlfn._xlws.FILTER(INDIRECT(B$1&"!$E1:$E10000"),INDIRECT(B$1&"!$a1:$a10000")=汇总!$A10),COUNTIF(INDIRECT(B$1&"!$a1:$a10000"),汇总!$A10)),B9)} -> 466 | C10: {=IFERROR(INDEX(_xlfn._xlws.FILTER(INDIRECT(C$1&"!$E1:$E10000"),INDIRECT(C$1&"!$a1:$a10000")=汇总!$A10),COUNTIF(INDIRECT(C$1&"!$a1:$a10000"),汇总!$A10)),C9)} -> 2486 | D10: {=IFERROR(INDEX(_xlfn._xlws.FILTER(INDIRECT(D$1&"!$E1:$E10000"),INDIRECT(D$1&"!$a1:$a10000")=汇总!$A10),COUNTIF(INDIRECT(D$1&"!$a1:$a10000"),汇总!$A10)),D9)} -> 597 | E10: {=IFERROR(INDEX(_xlfn._xlws.FILTER(INDIRECT(E$1&"!$E1:$E10000"),INDIRECT(E$1&"!$a1:$a10000")=汇总!$A10),COUNTIF(INDIRECT(E$1&"!$a1:$a10000"),汇总!$A10)),E9)} -> 1100.2633 | F10: {=IFERROR(INDEX(_xlfn._xlws.FILTER(INDIRECT(F$1&"!$E1:$E10000"),INDIRECT(F$1&"!$a1:$a10000")=汇总!$A10),COUNTIF(INDIRECT(F$1&"!$a1:$a10000"),汇总!$A10)),F9)} -> 199.56 | G10: {=IFERROR(INDEX(_xlfn._xlws.FILTER(INDIRECT(G$1&"!$E1:$E10000"),INDIRECT(G$1&"!$a1:$a10000")=汇总!$A10),COUNTIF(INDIRECT(G$1&"!$a1:$a10000"),汇总!$A10)),G9)} -> 93.352 | H10: {=IFERROR(INDEX(_xlfn._xlws.FILTER(INDIRECT(H$1&"!$E1:$E10000"),INDIRECT(H$1&"!$a1:$a10000")=汇总!$A10),COUNTIF(INDIRECT(H$1&"!$a1:$a10000"),汇总!$A10)),H9)} -> 48.7 | I10: {=IFERROR(INDEX(_xlfn._xlws.FILTER(INDIRECT(I$1&"!$E1:$E10000"),INDIRECT(I$1&"!$a1:$a10000")=汇总!$A10),COUNTIF(INDIRECT(I$1&"!$a1:$a10000"),汇总!$A10)),I9)} -> 11 | ... S10: {=IFERROR(INDEX(_xlfn._xlws.FILTER(INDIRECT(S$1&"!$E1:$E10000"),INDIRECT(S$1&"!$a1:$a10000")=汇总!$A10),COUNTIF(INDIRECT(S$1&"!$a1:$a10000"),汇总!$A10)),S9)} -> #VALUE!
A11: =+A10+1 -> 46032 | B11: {=IFERROR(INDEX(_xlfn._xlws.FILTER(INDIRECT(B$1&"!$E1:$E10000"),INDIRECT(B$1&"!$a1:$a10000")=汇总!$A11),COUNTIF(INDIRECT(B$1&"!$a1:$a10000"),汇总!$A11)),B10)} -> 466 | C11: {=IFERROR(INDEX(_xlfn._xlws.FILTER(INDIRECT(C$1&"!$E1:$E10000"),INDIRECT(C$1&"!$a1:$a10000")=汇总!$A11),COUNTIF(INDIRECT(C$1&"!$a1:$a10000"),汇总!$A11)),C10)} -> 2486 | D11: {=IFERROR(INDEX(_xlfn._xlws.FILTER(INDIRECT(D$1&"!$E1:$E10000"),INDIRECT(D$1&"!$a1:$a10000")=汇总!$A11),COUNTIF(INDIRECT(D$1&"!$a1:$a10000"),汇总!$A11)),D10)} -> 597 | E11: {=IFERROR(INDEX(_xlfn._xlws.FILTER(INDIRECT(E$1&"!$E1:$E10000"),INDIRECT(E$1&"!$a1:$a10000")=汇总!$A11),COUNTIF(INDIRECT(E$1&"!$a1:$a10000"),汇总!$A11)),E10)} -> 1100.2633 | F11: {=IFERROR(INDEX(_xlfn._xlws.FILTER(INDIRECT(F$1&"!$E1:$E10000"),INDIRECT(F$1&"!$a1:$a10000")=汇总!$A11),COUNTIF(INDIRECT(F$1&"!$a1:$a10000"),汇总!$A11)),F10)} -> 199.56 | G11: {=IFERROR(INDEX(_xlfn._xlws.FILTER(INDIRECT(G$1&"!$E1:$E10000"),INDIRECT(G$1&"!$a1:$a10000")=汇总!$A11),COUNTIF(INDIRECT(G$1&"!$a1:$a10000"),汇总!$A11)),G10)} -> 93.352 | H11: {=IFERROR(INDEX(_xlfn._xlws.FILTER(INDIRECT(H$1&"!$E1:$E10000"),INDIRECT(H$1&"!$a1:$a10000")=汇总!$A11),COUNTIF(INDIRECT(H$1&"!$a1:$a10000"),汇总!$A11)),H10)} -> 48.7 | I11: {=IFERROR(INDEX(_xlfn._xlws.FILTER(INDIRECT(I$1&"!$E1:$E10000"),INDIRECT(I$1&"!$a1:$a10000")=汇总!$A11),COUNTIF(INDIRECT(I$1&"!$a1:$a10000"),汇总!$A11)),I10)} -> 11 | ... S11: {=IFERROR(INDEX(_xlfn._xlws.FILTER(INDIRECT(S$1&"!$E1:$E10000"),INDIRECT(S$1&"!$a1:$a10000")=汇总!$A11),COUNTIF(INDIRECT(S$1&"!$a1:$a10000"),汇总!$A11)),S10)} -> #VALUE!
A12: =+A11+1 -> 46033 | B12: {=IFERROR(INDEX(_xlfn._xlws.FILTER(INDIRECT(B$1&"!$E1:$E10000"),INDIRECT(B$1&"!$a1:$a10000")=汇总!$A12),COUNTIF(INDIRECT(B$1&"!$a1:$a10000"),汇总!$A12)),B11)} -> 466 | C12: {=IFERROR(INDEX(_xlfn._xlws.FILTER(INDIRECT(C$1&"!$E1:$E10000"),INDIRECT(C$1&"!$a1:$a10000")=汇总!$A12),COUNTIF(INDIRECT(C$1&"!$a1:$a10000"),汇总!$A12)),C11)} -> 2486 | D12: {=IFERROR(INDEX(_xlfn._xlws.FILTER(INDIRECT(D$1&"!$E1:$E10000"),INDIRECT(D$1&"!$a1:$a10000")=汇总!$A12),COUNTIF(INDIRECT(D$1&"!$a1:$a10000"),汇总!$A12)),D11)} -> 597 | E12: {=IFERROR(INDEX(_xlfn._xlws.FILTER(INDIRECT(E$1&"!$E1:$E10000"),INDIRECT(E$1&"!$a1:$a10000")=汇总!$A12),COUNTIF(INDIRECT(E$1&"!$a1:$a10000"),汇总!$A12)),E11)} -> 1100.2633 | F12: {=IFERROR(INDEX(_xlfn._xlws.FILTER(INDIRECT(F$1&"!$E1:$E10000"),INDIRECT(F$1&"!$a1:$a10000")=汇总!$A12),COUNTIF(INDIRECT(F$1&"!$a1:$a10000"),汇总!$A12)),F11)} -> 199.56 | G12: {=IFERROR(INDEX(_xlfn._xlws.FILTER(INDIRECT(G$1&"!$E1:$E10000"),INDIRECT(G$1&"!$a1:$a10000")=汇总!$A12),COUNTIF(INDIRECT(G$1&"!$a1:$a10000"),汇总!$A12)),G11)} -> 93.352 | H12: {=IFERROR(INDEX(_xlfn._xlws.FILTER(INDIRECT(H$1&"!$E1:$E10000"),INDIRECT(H$1&"!$a1:$a10000")=汇总!$A12),COUNTIF(INDIRECT(H$1&"!$a1:$a10000"),汇总!$A12)),H11)} -> 48.7 | I12: {=IFERROR(INDEX(_xlfn._xlws.FILTER(INDIRECT(I$1&"!$E1:$E10000"),INDIRECT(I$1&"!$a1:$a10000")=汇总!$A12),COUNTIF(INDIRECT(I$1&"!$a1:$a10000"),汇总!$A12)),I11)} -> 11 | ... S12: {=IFERROR(INDEX(_xlfn._xlws.FILTER(INDIRECT(S$1&"!$E1:$E10000"),INDIRECT(S$1&"!$a1:$a10000")=汇总!$A12),COUNTIF(INDIRECT(S$1&"!$a1:$a10000"),汇总!$A12)),S11)} -> #VALUE!
A13: =+A12+1 -> 46034 | B13: {=IFERROR(INDEX(_xlfn._xlws.FILTER(INDIRECT(B$1&"!$E1:$E10000"),INDIRECT(B$1&"!$a1:$a10000")=汇总!$A13),COUNTIF(INDIRECT(B$1&"!$a1:$a10000"),汇总!$A13)),B12)} -> 764.5 | C13: {=IFERROR(INDEX(_xlfn._xlws.FILTER(INDIRECT(C$1&"!$E1:$E10000"),INDIRECT(C$1&"!$a1:$a10000")=汇总!$A13),COUNTIF(INDIRECT(C$1&"!$a1:$a10000"),汇总!$A13)),C12)} -> 258 | D13: {=IFERROR(INDEX(_xlfn._xlws.FILTER(INDIRECT(D$1&"!$E1:$E10000"),INDIRECT(D$1&"!$a1:$a10000")=汇总!$A13),COUNTIF(INDIRECT(D$1&"!$a1:$a10000"),汇总!$A13)),D12)} -> 173.75875 | E13: {=IFERROR(INDEX(_xlfn._xlws.FILTER(INDIRECT(E$1&"!$E1:$E10000"),INDIRECT(E$1&"!$a1:$a10000")=汇总!$A13),COUNTIF(INDIRECT(E$1&"!$a1:$a10000"),汇总!$A13)),E12)} -> 1100.2633 | F13: {=IFERROR(INDEX(_xlfn._xlws.FILTER(INDIRECT(F$1&"!$E1:$E10000"),INDIRECT(F$1&"!$a1:$a10000")=汇总!$A13),COUNTIF(INDIRECT(F$1&"!$a1:$a10000"),汇总!$A13)),F12)} -> 204.71 | G13: {=IFERROR(INDEX(_xlfn._xlws.FILTER(INDIRECT(G$1&"!$E1:$E10000"),INDIRECT(G$1&"!$a1:$a10000")=汇总!$A13),COUNTIF(INDIRECT(G$1&"!$a1:$a10000"),汇总!$A13)),G12)} -> 93.352 | H13: {=IFERROR(INDEX(_xlfn._xlws.FILTER(INDIRECT(H$1&"!$E1:$E10000"),INDIRECT(H$1&"!$a1:$a10000")=汇总!$A13),COUNTIF(INDIRECT(H$1&"!$a1:$a10000"),汇总!$A13)),H12)} -> 48.7 | I13: {=IFERROR(INDEX(_xlfn._xlws.FILTER(INDIRECT(I$1&"!$E1:$E10000"),INDIRECT(I$1&"!$a1:$a10000")=汇总!$A13),COUNTIF(INDIRECT(I$1&"!$a1:$a10000"),汇总!$A13)),I12)} -> 11 | ... S13: {=IFERROR(INDEX(_xlfn._xlws.FILTER(INDIRECT(S$1&"!$E1:$E10000"),INDIRECT(S$1&"!$a1:$a10000")=汇总!$A13),COUNTIF(INDIRECT(S$1&"!$a1:$a10000"),汇总!$A13)),S12)} -> #VALUE!
A14: =+A13+1 -> 46035 | B14: {=IFERROR(INDEX(_xlfn._xlws.FILTER(INDIRECT(B$1&"!$E1:$E10000"),INDIRECT(B$1&"!$a1:$a10000")=汇总!$A14),COUNTIF(INDIRECT(B$1&"!$a1:$a10000"),汇总!$A14)),B13)} -> 232.4 | C14: {=IFERROR(INDEX(_xlfn._xlws.FILTER(INDIRECT(C$1&"!$E1:$E10000"),INDIRECT(C$1&"!$a1:$a10000")=汇总!$A14),COUNTIF(INDIRECT(C$1&"!$a1:$a10000"),汇总!$A14)),C13)} -> 708 | D14: {=IFERROR(INDEX(_xlfn._xlws.FILTER(INDIRECT(D$1&"!$E1:$E10000"),INDIRECT(D$1&"!$a1:$a10000")=汇总!$A14),COUNTIF(INDIRECT(D$1&"!$a1:$a10000"),汇总!$A14)),D13)} -> 369.021 | E14: {=IFERROR(INDEX(_xlfn._xlws.FILTER(INDIRECT(E$1&"!$E1:$E10000"),INDIRECT(E$1&"!$a1:$a10000")=汇总!$A14),COUNTIF(INDIRECT(E$1&"!$a1:$a10000"),汇总!$A14)),E13)} -> 1100.2633 | F14: {=IFERROR(INDEX(_xlfn._xlws.FILTER(INDIRECT(F$1&"!$E1:$E10000"),INDIRECT(F$1&"!$a1:$a10000")=汇总!$A14),COUNTIF(INDIRECT(F$1&"!$a1:$a10000"),汇总!$A14)),F13)} -> 204.71 | G14: {=IFERROR(INDEX(_xlfn._xlws.FILTER(INDIRECT(G$1&"!$E1:$E10000"),INDIRECT(G$1&"!$a1:$a10000")=汇总!$A14),COUNTIF(INDIRECT(G$1&"!$a1:$a10000"),汇总!$A14)),G13)} -> 93.352 | H14: {=IFERROR(INDEX(_xlfn._xlws.FILTER(INDIRECT(H$1&"!$E1:$E10000"),INDIRECT(H$1&"!$a1:$a10000")=汇总!$A14),COUNTIF(INDIRECT(H$1&"!$a1:$a10000"),汇总!$A14)),H13)} -> 48.7 | I14: {=IFERROR(INDEX(_xlfn._xlws.FILTER(INDIRECT(I$1&"!$E1:$E10000"),INDIRECT(I$1&"!$a1:$a10000")=汇总!$A14),COUNTIF(INDIRECT(I$1&"!$a1:$a10000"),汇总!$A14)),I13)} -> 11 | ... S14: {=IFERROR(INDEX(_xlfn._xlws.FILTER(INDIRECT(S$1&"!$E1:$E10000"),INDIRECT(S$1&"!$a1:$a10000")=汇总!$A14),COUNTIF(INDIRECT(S$1&"!$a1:$a10000"),汇总!$A14)),S13)} -> #VALUE!
... A97: =+A96+1 -> 46118 | B97: {=IFERROR(INDEX(_xlfn._xlws.FILTER(INDIRECT(B$1&"!$E1:$E10000"),INDIRECT(B$1&"!$a1:$a10000")=汇总!$A97),COUNTIF(INDIRECT(B$1&"!$a1:$a10000"),汇总!$A97)),B96)} -> 2136.9726 | C97: {=IFERROR(INDEX(_xlfn._xlws.FILTER(INDIRECT(C$1&"!$E1:$E10000"),INDIRECT(C$1&"!$a1:$a10000")=汇总!$A97),COUNTIF(INDIRECT(C$1&"!$a1:$a10000"),汇总!$A97)),C96)} -> 1799.0525 | D97: {=IFERROR(INDEX(_xlfn._xlws.FILTER(INDIRECT(D$1&"!$E1:$E10000"),INDIRECT(D$1&"!$a1:$a10000")=汇总!$A97),COUNTIF(INDIRECT(D$1&"!$a1:$a10000"),汇总!$A97)),D96)} -> 2104.7305 | E97: {=IFERROR(INDEX(_xlfn._xlws.FILTER(INDIRECT(E$1&"!$E1:$E10000"),INDIRECT(E$1&"!$a1:$a10000")=汇总!$A97),COUNTIF(INDIRECT(E$1&"!$a1:$a10000"),汇总!$A97)),E96)} -> 3235 | F97: {=IFERROR(INDEX(_xlfn._xlws.FILTER(INDIRECT(F$1&"!$E1:$E10000"),INDIRECT(F$1&"!$a1:$a10000")=汇总!$A97),COUNTIF(INDIRECT(F$1&"!$a1:$a10000"),汇总!$A97)),F96)} -> 7350 | G97: {=IFERROR(INDEX(_xlfn._xlws.FILTER(INDIRECT(G$1&"!$E1:$E10000"),INDIRECT(G$1&"!$a1:$a10000")=汇总!$A97),COUNTIF(INDIRECT(G$1&"!$a1:$a10000"),汇总!$A97)),G96)} -> 6771.4 | H97: {=IFERROR(INDEX(_xlfn._xlws.FILTER(INDIRECT(H$1&"!$E1:$E10000"),INDIRECT(H$1&"!$a1:$a10000")=汇总!$A97),COUNTIF(INDIRECT(H$1&"!$a1:$a10000"),汇总!$A97)),H96)} -> 431.92997 | I97: {=IFERROR(INDEX(_xlfn._xlws.FILTER(INDIRECT(I$1&"!$E1:$E10000"),INDIRECT(I$1&"!$a1:$a10000")=汇总!$A97),COUNTIF(INDIRECT(I$1&"!$a1:$a10000"),汇总!$A97)),I96)} -> 834.68823 | ... S97: {=IFERROR(INDEX(_xlfn._xlws.FILTER(INDIRECT(S$1&"!$E1:$E10000"),INDIRECT(S$1&"!$a1:$a10000")=汇总!$A97),COUNTIF(INDIRECT(S$1&"!$a1:$a10000"),汇总!$A97)),S96)} -> 107.36596
A98: =+A97+1 -> 46119 | B98: {=IFERROR(INDEX(_xlfn._xlws.FILTER(INDIRECT(B$1&"!$E1:$E10000"),INDIRECT(B$1&"!$a1:$a10000")=汇总!$A98),COUNTIF(INDIRECT(B$1&"!$a1:$a10000"),汇总!$A98)),B97)} -> 382.97263 | C98: {=IFERROR(INDEX(_xlfn._xlws.FILTER(INDIRECT(C$1&"!$E1:$E10000"),INDIRECT(C$1&"!$a1:$a10000")=汇总!$A98),COUNTIF(INDIRECT(C$1&"!$a1:$a10000"),汇总!$A98)),C97)} -> 1799.0525 | D98: {=IFERROR(INDEX(_xlfn._xlws.FILTER(INDIRECT(D$1&"!$E1:$E10000"),INDIRECT(D$1&"!$a1:$a10000")=汇总!$A98),COUNTIF(INDIRECT(D$1&"!$a1:$a10000"),汇总!$A98)),D97)} -> 2104.7305 | E98: {=IFERROR(INDEX(_xlfn._xlws.FILTER(INDIRECT(E$1&"!$E1:$E10000"),INDIRECT(E$1&"!$a1:$a10000")=汇总!$A98),COUNTIF(INDIRECT(E$1&"!$a1:$a10000"),汇总!$A98)),E97)} -> 3235 | F98: {=IFERROR(INDEX(_xlfn._xlws.FILTER(INDIRECT(F$1&"!$E1:$E10000"),INDIRECT(F$1&"!$a1:$a10000")=汇总!$A98),COUNTIF(INDIRECT(F$1&"!$a1:$a10000"),汇总!$A98)),F97)} -> 7350 | G98: {=IFERROR(INDEX(_xlfn._xlws.FILTER(INDIRECT(G$1&"!$E1:$E10000"),INDIRECT(G$1&"!$a1:$a10000")=汇总!$A98),COUNTIF(INDIRECT(G$1&"!$a1:$a10000"),汇总!$A98)),G97)} -> 6771.4 | H98: {=IFERROR(INDEX(_xlfn._xlws.FILTER(INDIRECT(H$1&"!$E1:$E10000"),INDIRECT(H$1&"!$a1:$a10000")=汇总!$A98),COUNTIF(INDIRECT(H$1&"!$a1:$a10000"),汇总!$A98)),H97)} -> 431.92997 | I98: {=IFERROR(INDEX(_xlfn._xlws.FILTER(INDIRECT(I$1&"!$E1:$E10000"),INDIRECT(I$1&"!$a1:$a10000")=汇总!$A98),COUNTIF(INDIRECT(I$1&"!$a1:$a10000"),汇总!$A98)),I97)} -> 171.20811 | ... T98: {=IFERROR(INDEX(_xlfn._xlws.FILTER(INDIRECT(T$1&"!$E1:$E10000"),INDIRECT(T$1&"!$a1:$a10000")=汇总!$A98),COUNTIF(INDIRECT(T$1&"!$a1:$a10000"),汇总!$A98)),T97)} -> 0
A99: =+A98+1 -> 46120 | B99: {=IFERROR(INDEX(_xlfn._xlws.FILTER(INDIRECT(B$1&"!$E1:$E10000"),INDIRECT(B$1&"!$a1:$a10000")=汇总!$A99),COUNTIF(INDIRECT(B$1&"!$a1:$a10000"),汇总!$A99)),B98)} -> 319.27263 | C99: {=IFERROR(INDEX(_xlfn._xlws.FILTER(INDIRECT(C$1&"!$E1:$E10000"),INDIRECT(C$1&"!$a1:$a10000")=汇总!$A99),COUNTIF(INDIRECT(C$1&"!$a1:$a10000"),汇总!$A99)),C98)} -> 2141.7865 | D99: {=IFERROR(INDEX(_xlfn._xlws.FILTER(INDIRECT(D$1&"!$E1:$E10000"),INDIRECT(D$1&"!$a1:$a10000")=汇总!$A99),COUNTIF(INDIRECT(D$1&"!$a1:$a10000"),汇总!$A99)),D98)} -> 80.46049 | E99: {=IFERROR(INDEX(_xlfn._xlws.FILTER(INDIRECT(E$1&"!$E1:$E10000"),INDIRECT(E$1&"!$a1:$a10000")=汇总!$A99),COUNTIF(INDIRECT(E$1&"!$a1:$a10000"),汇总!$A99)),E98)} -> 25.88085 | F99: {=IFERROR(INDEX(_xlfn._xlws.FILTER(INDIRECT(F$1&"!$E1:$E10000"),INDIRECT(F$1&"!$a1:$a10000")=汇总!$A99),COUNTIF(INDIRECT(F$1&"!$a1:$a10000"),汇总!$A99)),F98)} -> 7350 | G99: {=IFERROR(INDEX(_xlfn._xlws.FILTER(INDIRECT(G$1&"!$E1:$E10000"),INDIRECT(G$1&"!$a1:$a10000")=汇总!$A99),COUNTIF(INDIRECT(G$1&"!$a1:$a10000"),汇总!$A99)),G98)} -> 6771.4 | H99: {=IFERROR(INDEX(_xlfn._xlws.FILTER(INDIRECT(H$1&"!$E1:$E10000"),INDIRECT(H$1&"!$a1:$a10000")=汇总!$A99),COUNTIF(INDIRECT(H$1&"!$a1:$a10000"),汇总!$A99)),H98)} -> 431.92997 | I99: {=IFERROR(INDEX(_xlfn._xlws.FILTER(INDIRECT(I$1&"!$E1:$E10000"),INDIRECT(I$1&"!$a1:$a10000")=汇总!$A99),COUNTIF(INDIRECT(I$1&"!$a1:$a10000"),汇总!$A99)),I98)} -> 171.20811 | ... T99: {=IFERROR(INDEX(_xlfn._xlws.FILTER(INDIRECT(T$1&"!$E1:$E10000"),INDIRECT(T$1&"!$a1:$a10000")=汇总!$A99),COUNTIF(INDIRECT(T$1&"!$a1:$a10000"),汇总!$A99)),T98)} -> 0
A100: =+A99+1 -> 46121 | B100: {=IFERROR(INDEX(_xlfn._xlws.FILTER(INDIRECT(B$1&"!$E1:$E10000"),INDIRECT(B$1&"!$a1:$a10000")=汇总!$A100),COUNTIF(INDIRECT(B$1&"!$a1:$a10000"),汇总!$A100)),B99)} -> 1059.2726 | C100: {=IFERROR(INDEX(_xlfn._xlws.FILTER(INDIRECT(C$1&"!$E1:$E10000"),INDIRECT(C$1&"!$a1:$a10000")=汇总!$A100),COUNTIF(INDIRECT(C$1&"!$a1:$a10000"),汇总!$A100)),C99)} -> 1141.7865 | D100: {=IFERROR(INDEX(_xlfn._xlws.FILTER(INDIRECT(D$1&"!$E1:$E10000"),INDIRECT(D$1&"!$a1:$a10000")=汇总!$A100),COUNTIF(INDIRECT(D$1&"!$a1:$a10000"),汇总!$A100)),D99)} -> 2080.4605 | E100: {=IFERROR(INDEX(_xlfn._xlws.FILTER(INDIRECT(E$1&"!$E1:$E10000"),INDIRECT(E$1&"!$a1:$a10000")=汇总!$A100),COUNTIF(INDIRECT(E$1&"!$a1:$a10000"),汇总!$A100)),E99)} -> 25.88085 | F100: {=IFERROR(INDEX(_xlfn._xlws.FILTER(INDIRECT(F$1&"!$E1:$E10000"),INDIRECT(F$1&"!$a1:$a10000")=汇总!$A100),COUNTIF(INDIRECT(F$1&"!$a1:$a10000"),汇总!$A100)),F99)} -> 7350 | G100: {=IFERROR(INDEX(_xlfn._xlws.FILTER(INDIRECT(G$1&"!$E1:$E10000"),INDIRECT(G$1&"!$a1:$a10000")=汇总!$A100),COUNTIF(INDIRECT(G$1&"!$a1:$a10000"),汇总!$A100)),G99)} -> 6771.4 | H100: {=IFERROR(INDEX(_xlfn._xlws.FILTER(INDIRECT(H$1&"!$E1:$E10000"),INDIRECT(H$1&"!$a1:$a10000")=汇总!$A100),COUNTIF(INDIRECT(H$1&"!$a1:$a10000"),汇总!$A100)),H99)} -> 431.92997 | I100: {=IFERROR(INDEX(_xlfn._xlws.FILTER(INDIRECT(I$1&"!$E1:$E10000"),INDIRECT(I$1&"!$a1:$a10000")=汇总!$A100),COUNTIF(INDIRECT(I$1&"!$a1:$a10000"),汇总!$A100)),I99)} -> 171.20811 | ... T100: {=IFERROR(INDEX(_xlfn._xlws.FILTER(INDIRECT(T$1&"!$E1:$E10000"),INDIRECT(T$1&"!$a1:$a10000")=汇总!$A100),COUNTIF(INDIRECT(T$1&"!$a1:$a10000"),汇总!$A100)),T99)} -> 0
A101: =+A100+1 -> 46122 | B101: {=IFERROR(INDEX(_xlfn._xlws.FILTER(INDIRECT(B$1&"!$E1:$E10000"),INDIRECT(B$1&"!$a1:$a10000")=汇总!$A101),COUNTIF(INDIRECT(B$1&"!$a1:$a10000"),汇总!$A101)),B100)} -> 59.272627 | C101: {=IFERROR(INDEX(_xlfn._xlws.FILTER(INDIRECT(C$1&"!$E1:$E10000"),INDIRECT(C$1&"!$a1:$a10000")=汇总!$A101),COUNTIF(INDIRECT(C$1&"!$a1:$a10000"),汇总!$A101)),C100)} -> 1074.962 | D101: {=IFERROR(INDEX(_xlfn._xlws.FILTER(INDIRECT(D$1&"!$E1:$E10000"),INDIRECT(D$1&"!$a1:$a10000")=汇总!$A101),COUNTIF(INDIRECT(D$1&"!$a1:$a10000"),汇总!$A101)),D100)} -> 1972.5585 | E101: {=IFERROR(INDEX(_xlfn._xlws.FILTER(INDIRECT(E$1&"!$E1:$E10000"),INDIRECT(E$1&"!$a1:$a10000")=汇总!$A101),COUNTIF(INDIRECT(E$1&"!$a1:$a10000"),汇总!$A101)),E100)} -> 1748.4758 | F101: {=IFERROR(INDEX(_xlfn._xlws.FILTER(INDIRECT(F$1&"!$E1:$E10000"),INDIRECT(F$1&"!$a1:$a10000")=汇总!$A101),COUNTIF(INDIRECT(F$1&"!$a1:$a10000"),汇总!$A101)),F100)} -> 7350 | G101: {=IFERROR(INDEX(_xlfn._xlws.FILTER(INDIRECT(G$1&"!$E1:$E10000"),INDIRECT(G$1&"!$a1:$a10000")=汇总!$A101),COUNTIF(INDIRECT(G$1&"!$a1:$a10000"),汇总!$A101)),G100)} -> 6771.4 | H101: {=IFERROR(INDEX(_xlfn._xlws.FILTER(INDIRECT(H$1&"!$E1:$E10000"),INDIRECT(H$1&"!$a1:$a10000")=汇总!$A101),COUNTIF(INDIRECT(H$1&"!$a1:$a10000"),汇总!$A101)),H100)} -> 119 | I101: {=IFERROR(INDEX(_xlfn._xlws.FILTER(INDIRECT(I$1&"!$E1:$E10000"),INDIRECT(I$1&"!$a1:$a10000")=汇总!$A101),COUNTIF(INDIRECT(I$1&"!$a1:$a10000"),汇总!$A101)),I100)} -> 17.531309 | ... T101: {=IFERROR(INDEX(_xlfn._xlws.FILTER(INDIRECT(T$1&"!$E1:$E10000"),INDIRECT(T$1&"!$a1:$a10000")=汇总!$A101),COUNTIF(INDIRECT(T$1&"!$a1:$a10000"),汇总!$A101)),T100)} -> 0
A102: =+A101+1 -> 46123 | B102: {=IFERROR(INDEX(_xlfn._xlws.FILTER(INDIRECT(B$1&"!$E1:$E10000"),INDIRECT(B$1&"!$a1:$a10000")=汇总!$A102),COUNTIF(INDIRECT(B$1&"!$a1:$a10000"),汇总!$A102)),B101)} -> 59.272627 | C102: {=IFERROR(INDEX(_xlfn._xlws.FILTER(INDIRECT(C$1&"!$E1:$E10000"),INDIRECT(C$1&"!$a1:$a10000")=汇总!$A102),COUNTIF(INDIRECT(C$1&"!$a1:$a10000"),汇总!$A102)),C101)} -> 1074.962 | D102: {=IFERROR(INDEX(_xlfn._xlws.FILTER(INDIRECT(D$1&"!$E1:$E10000"),INDIRECT(D$1&"!$a1:$a10000")=汇总!$A102),COUNTIF(INDIRECT(D$1&"!$a1:$a10000"),汇总!$A102)),D101)} -> 1972.5585 | E102: {=IFERROR(INDEX(_xlfn._xlws.FILTER(INDIRECT(E$1&"!$E1:$E10000"),INDIRECT(E$1&"!$a1:$a10000")=汇总!$A102),COUNTIF(INDIRECT(E$1&"!$a1:$a10000"),汇总!$A102)),E101)} -> 1748.4758 | F102: {=IFERROR(INDEX(_xlfn._xlws.FILTER(INDIRECT(F$1&"!$E1:$E10000"),INDIRECT(F$1&"!$a1:$a10000")=汇总!$A102),COUNTIF(INDIRECT(F$1&"!$a1:$a10000"),汇总!$A102)),F101)} -> 7350 | G102: {=IFERROR(INDEX(_xlfn._xlws.FILTER(INDIRECT(G$1&"!$E1:$E10000"),INDIRECT(G$1&"!$a1:$a10000")=汇总!$A102),COUNTIF(INDIRECT(G$1&"!$a1:$a10000"),汇总!$A102)),G101)} -> 6771.4 | H102: {=IFERROR(INDEX(_xlfn._xlws.FILTER(INDIRECT(H$1&"!$E1:$E10000"),INDIRECT(H$1&"!$a1:$a10000")=汇总!$A102),COUNTIF(INDIRECT(H$1&"!$a1:$a10000"),汇总!$A102)),H101)} -> 119 | I102: {=IFERROR(INDEX(_xlfn._xlws.FILTER(INDIRECT(I$1&"!$E1:$E10000"),INDIRECT(I$1&"!$a1:$a10000")=汇总!$A102),COUNTIF(INDIRECT(I$1&"!$a1:$a10000"),汇总!$A102)),I101)} -> 17.531309 | ... T102: {=IFERROR(INDEX(_xlfn._xlws.FILTER(INDIRECT(T$1&"!$E1:$E10000"),INDIRECT(T$1&"!$a1:$a10000")=汇总!$A102),COUNTIF(INDIRECT(T$1&"!$a1:$a10000"),汇总!$A102)),T101)} -> 0
A103: =+A102+1 -> 46124 | B103: {=IFERROR(INDEX(_xlfn._xlws.FILTER(INDIRECT(B$1&"!$E1:$E10000"),INDIRECT(B$1&"!$a1:$a10000")=汇总!$A103),COUNTIF(INDIRECT(B$1&"!$a1:$a10000"),汇总!$A103)),B102)} -> 59.272627 | C103: {=IFERROR(INDEX(_xlfn._xlws.FILTER(INDIRECT(C$1&"!$E1:$E10000"),INDIRECT(C$1&"!$a1:$a10000")=汇总!$A103),COUNTIF(INDIRECT(C$1&"!$a1:$a10000"),汇总!$A103)),C102)} -> 1074.962 | D103: {=IFERROR(INDEX(_xlfn._xlws.FILTER(INDIRECT(D$1&"!$E1:$E10000"),INDIRECT(D$1&"!$a1:$a10000")=汇总!$A103),COUNTIF(INDIRECT(D$1&"!$a1:$a10000"),汇总!$A103)),D102)} -> 1972.5585 | E103: {=IFERROR(INDEX(_xlfn._xlws.FILTER(INDIRECT(E$1&"!$E1:$E10000"),INDIRECT(E$1&"!$a1:$a10000")=汇总!$A103),COUNTIF(INDIRECT(E$1&"!$a1:$a10000"),汇总!$A103)),E102)} -> 1748.4758 | F103: {=IFERROR(INDEX(_xlfn._xlws.FILTER(INDIRECT(F$1&"!$E1:$E10000"),INDIRECT(F$1&"!$a1:$a10000")=汇总!$A103),COUNTIF(INDIRECT(F$1&"!$a1:$a10000"),汇总!$A103)),F102)} -> 7350 | G103: {=IFERROR(INDEX(_xlfn._xlws.FILTER(INDIRECT(G$1&"!$E1:$E10000"),INDIRECT(G$1&"!$a1:$a10000")=汇总!$A103),COUNTIF(INDIRECT(G$1&"!$a1:$a10000"),汇总!$A103)),G102)} -> 6771.4 | H103: {=IFERROR(INDEX(_xlfn._xlws.FILTER(INDIRECT(H$1&"!$E1:$E10000"),INDIRECT(H$1&"!$a1:$a10000")=汇总!$A103),COUNTIF(INDIRECT(H$1&"!$a1:$a10000"),汇总!$A103)),H102)} -> 119 | I103: {=IFERROR(INDEX(_xlfn._xlws.FILTER(INDIRECT(I$1&"!$E1:$E10000"),INDIRECT(I$1&"!$a1:$a10000")=汇总!$A103),COUNTIF(INDIRECT(I$1&"!$a1:$a10000"),汇总!$A103)),I102)} -> 17.531309 | ... T103: {=IFERROR(INDEX(_xlfn._xlws.FILTER(INDIRECT(T$1&"!$E1:$E10000"),INDIRECT(T$1&"!$a1:$a10000")=汇总!$A103),COUNTIF(INDIRECT(T$1&"!$a1:$a10000"),汇总!$A103)),T102)} -> 0
A104: =+A103+1 -> 46125 | B104: {=IFERROR(INDEX(_xlfn._xlws.FILTER(INDIRECT(B$1&"!$E1:$E10000"),INDIRECT(B$1&"!$a1:$a10000")=汇总!$A104),COUNTIF(INDIRECT(B$1&"!$a1:$a10000"),汇总!$A104)),B103)} -> 662 | C104: {=IFERROR(INDEX(_xlfn._xlws.FILTER(INDIRECT(C$1&"!$E1:$E10000"),INDIRECT(C$1&"!$a1:$a10000")=汇总!$A104),COUNTIF(INDIRECT(C$1&"!$a1:$a10000"),汇总!$A104)),C103)} -> 1074.962 | D104: {=IFERROR(INDEX(_xlfn._xlws.FILTER(INDIRECT(D$1&"!$E1:$E10000"),INDIRECT(D$1&"!$a1:$a10000")=汇总!$A104),COUNTIF(INDIRECT(D$1&"!$a1:$a10000"),汇总!$A104)),D103)} -> 1679.7385 | E104: {=IFERROR(INDEX(_xlfn._xlws.FILTER(INDIRECT(E$1&"!$E1:$E10000"),INDIRECT(E$1&"!$a1:$a10000")=汇总!$A104),COUNTIF(INDIRECT(E$1&"!$a1:$a10000"),汇总!$A104)),E103)} -> 1748.4758 | F104: {=IFERROR(INDEX(_xlfn._xlws.FILTER(INDIRECT(F$1&"!$E1:$E10000"),INDIRECT(F$1&"!$a1:$a10000")=汇总!$A104),COUNTIF(INDIRECT(F$1&"!$a1:$a10000"),汇总!$A104)),F103)} -> 7350 | G104: {=IFERROR(INDEX(_xlfn._xlws.FILTER(INDIRECT(G$1&"!$E1:$E10000"),INDIRECT(G$1&"!$a1:$a10000")=汇总!$A104),COUNTIF(INDIRECT(G$1&"!$a1:$a10000"),汇总!$A104)),G103)} -> 7703 | H104: {=IFERROR(INDEX(_xlfn._xlws.FILTER(INDIRECT(H$1&"!$E1:$E10000"),INDIRECT(H$1&"!$a1:$a10000")=汇总!$A104),COUNTIF(INDIRECT(H$1&"!$a1:$a10000"),汇总!$A104)),H103)} -> 219 | I104: {=IFERROR(INDEX(_xlfn._xlws.FILTER(INDIRECT(I$1&"!$E1:$E10000"),INDIRECT(I$1&"!$a1:$a10000")=汇总!$A104),COUNTIF(INDIRECT(I$1&"!$a1:$a10000"),汇总!$A104)),I103)} -> 17.531309 | ... T104: {=IFERROR(INDEX(_xlfn._xlws.FILTER(INDIRECT(T$1&"!$E1:$E10000"),INDIRECT(T$1&"!$a1:$a10000")=汇总!$A104),COUNTIF(INDIRECT(T$1&"!$a1:$a10000"),汇总!$A104)),T103)} -> 0
A105: =+A104+1 -> 46126 | B105: {=IFERROR(INDEX(_xlfn._xlws.FILTER(INDIRECT(B$1&"!$E1:$E10000"),INDIRECT(B$1&"!$a1:$a10000")=汇总!$A105),COUNTIF(INDIRECT(B$1&"!$a1:$a10000"),汇总!$A105)),B104)} -> 360.1206 | C105: {=IFERROR(INDEX(_xlfn._xlws.FILTER(INDIRECT(C$1&"!$E1:$E10000"),INDIRECT(C$1&"!$a1:$a10000")=汇总!$A105),COUNTIF(INDIRECT(C$1&"!$a1:$a10000"),汇总!$A105)),C104)} -> 1074.962 | D105: {=IFERROR(INDEX(_xlfn._xlws.FILTER(INDIRECT(D$1&"!$E1:$E10000"),INDIRECT(D$1&"!$a1:$a10000")=汇总!$A105),COUNTIF(INDIRECT(D$1&"!$a1:$a10000"),汇总!$A105)),D104)} -> 2018.4385 | E105: {=IFERROR(INDEX(_xlfn._xlws.FILTER(INDIRECT(E$1&"!$E1:$E10000"),INDIRECT(E$1&"!$a1:$a10000")=汇总!$A105),COUNTIF(INDIRECT(E$1&"!$a1:$a10000"),汇总!$A105)),E104)} -> 679.61835 | F105: {=IFERROR(INDEX(_xlfn._xlws.FILTER(INDIRECT(F$1&"!$E1:$E10000"),INDIRECT(F$1&"!$a1:$a10000")=汇总!$A105),COUNTIF(INDIRECT(F$1&"!$a1:$a10000"),汇总!$A105)),F104)} -> 7350 | G105: {=IFERROR(INDEX(_xlfn._xlws.FILTER(INDIRECT(G$1&"!$E1:$E10000"),INDIRECT(G$1&"!$a1:$a10000")=汇总!$A105),COUNTIF(INDIRECT(G$1&"!$a1:$a10000"),汇总!$A105)),G104)} -> 7703 | H105: {=IFERROR(INDEX(_xlfn._xlws.FILTER(INDIRECT(H$1&"!$E1:$E10000"),INDIRECT(H$1&"!$a1:$a10000")=汇总!$A105),COUNTIF(INDIRECT(H$1&"!$a1:$a10000"),汇总!$A105)),H104)} -> 219 | I105: {=IFERROR(INDEX(_xlfn._xlws.FILTER(INDIRECT(I$1&"!$E1:$E10000"),INDIRECT(I$1&"!$a1:$a10000")=汇总!$A105),COUNTIF(INDIRECT(I$1&"!$a1:$a10000"),汇总!$A105)),I104)} -> 17.531309 | ... T105: {=IFERROR(INDEX(_xlfn._xlws.FILTER(INDIRECT(T$1&"!$E1:$E10000"),INDIRECT(T$1&"!$a1:$a10000")=汇总!$A105),COUNTIF(INDIRECT(T$1&"!$a1:$a10000"),汇总!$A105)),T104)} -> 0
A106: =+A105+1 -> 46127 | B106: {=IFERROR(INDEX(_xlfn._xlws.FILTER(INDIRECT(B$1&"!$E1:$E10000"),INDIRECT(B$1&"!$a1:$a10000")=汇总!$A106),COUNTIF(INDIRECT(B$1&"!$a1:$a10000"),汇总!$A106)),B105)} -> 748.1206 | C106: {=IFERROR(INDEX(_xlfn._xlws.FILTER(INDIRECT(C$1&"!$E1:$E10000"),INDIRECT(C$1&"!$a1:$a10000")=汇总!$A106),COUNTIF(INDIRECT(C$1&"!$a1:$a10000"),汇总!$A106)),C105)} -> 1357 | D106: {=IFERROR(INDEX(_xlfn._xlws.FILTER(INDIRECT(D$1&"!$E1:$E10000"),INDIRECT(D$1&"!$a1:$a10000")=汇总!$A106),COUNTIF(INDIRECT(D$1&"!$a1:$a10000"),汇总!$A106)),D105)} -> 62.72031 | E106: {=IFERROR(INDEX(_xlfn._xlws.FILTER(INDIRECT(E$1&"!$E1:$E10000"),INDIRECT(E$1&"!$a1:$a10000")=汇总!$A106),COUNTIF(INDIRECT(E$1&"!$a1:$a10000"),汇总!$A106)),E105)} -> 910.01835 | F106: {=IFERROR(INDEX(_xlfn._xlws.FILTER(INDIRECT(F$1&"!$E1:$E10000"),INDIRECT(F$1&"!$a1:$a10000")=汇总!$A106),COUNTIF(INDIRECT(F$1&"!$a1:$a10000"),汇总!$A106)),F105)} -> 9096 | G106: {=IFERROR(INDEX(_xlfn._xlws.FILTER(INDIRECT(G$1&"!$E1:$E10000"),INDIRECT(G$1&"!$a1:$a10000")=汇总!$A106),COUNTIF(INDIRECT(G$1&"!$a1:$a10000"),汇总!$A106)),G105)} -> 8780.4 | H106: {=IFERROR(INDEX(_xlfn._xlws.FILTER(INDIRECT(H$1&"!$E1:$E10000"),INDIRECT(H$1&"!$a1:$a10000")=汇总!$A106),COUNTIF(INDIRECT(H$1&"!$a1:$a10000"),汇总!$A106)),H105)} -> 219 | I106: {=IFERROR(INDEX(_xlfn._xlws.FILTER(INDIRECT(I$1&"!$E1:$E10000"),INDIRECT(I$1&"!$a1:$a10000")=汇总!$A106),COUNTIF(INDIRECT(I$1&"!$a1:$a10000"),汇总!$A106)),I105)} -> 17.531309 | ... T106: {=IFERROR(INDEX(_xlfn._xlws.FILTER(INDIRECT(T$1&"!$E1:$E10000"),INDIRECT(T$1&"!$a1:$a10000")=汇总!$A106),COUNTIF(INDIRECT(T$1&"!$a1:$a10000"),汇总!$A106)),T105)} -> 0
A107: =+A106+1 -> 46128 | B107: {=IFERROR(INDEX(_xlfn._xlws.FILTER(INDIRECT(B$1&"!$E1:$E10000"),INDIRECT(B$1&"!$a1:$a10000")=汇总!$A107),COUNTIF(INDIRECT(B$1&"!$a1:$a10000"),汇总!$A107)),B106)} -> 748.1206 | C107: {=IFERROR(INDEX(_xlfn._xlws.FILTER(INDIRECT(C$1&"!$E1:$E10000"),INDIRECT(C$1&"!$a1:$a10000")=汇总!$A107),COUNTIF(INDIRECT(C$1&"!$a1:$a10000"),汇总!$A107)),C106)} -> 1662 | D107: {=IFERROR(INDEX(_xlfn._xlws.FILTER(INDIRECT(D$1&"!$E1:$E10000"),INDIRECT(D$1&"!$a1:$a10000")=汇总!$A107),COUNTIF(INDIRECT(D$1&"!$a1:$a10000"),汇总!$A107)),D106)} -> 62.72031 | E107: {=IFERROR(INDEX(_xlfn._xlws.FILTER(INDIRECT(E$1&"!$E1:$E10000"),INDIRECT(E$1&"!$a1:$a10000")=汇总!$A107),COUNTIF(INDIRECT(E$1&"!$a1:$a10000"),汇总!$A107)),E106)} -> 913.00835 | F107: {=IFERROR(INDEX(_xlfn._xlws.FILTER(INDIRECT(F$1&"!$E1:$E10000"),INDIRECT(F$1&"!$a1:$a10000")=汇总!$A107),COUNTIF(INDIRECT(F$1&"!$a1:$a10000"),汇总!$A107)),F106)} -> 11482 | G107: {=IFERROR(INDEX(_xlfn._xlws.FILTER(INDIRECT(G$1&"!$E1:$E10000"),INDIRECT(G$1&"!$a1:$a10000")=汇总!$A107),COUNTIF(INDIRECT(G$1&"!$a1:$a10000"),汇总!$A107)),G106)} -> 8047.4 | H107: {=IFERROR(INDEX(_xlfn._xlws.FILTER(INDIRECT(H$1&"!$E1:$E10000"),INDIRECT(H$1&"!$a1:$a10000")=汇总!$A107),COUNTIF(INDIRECT(H$1&"!$a1:$a10000"),汇总!$A107)),H106)} -> 219 | I107: {=IFERROR(INDEX(_xlfn._xlws.FILTER(INDIRECT(I$1&"!$E1:$E10000"),INDIRECT(I$1&"!$a1:$a10000")=汇总!$A107),COUNTIF(INDIRECT(I$1&"!$a1:$a10000"),汇总!$A107)),I106)} -> 17.531309 | ... T107: {=IFERROR(INDEX(_xlfn._xlws.FILTER(INDIRECT(T$1&"!$E1:$E10000"),INDIRECT(T$1&"!$a1:$a10000")=汇总!$A107),COUNTIF(INDIRECT(T$1&"!$a1:$a10000"),汇总!$A107)),T106)} -> 0
A108: =+A107+1 -> 46129 | B108: {=IFERROR(INDEX(_xlfn._xlws.FILTER(INDIRECT(B$1&"!$E1:$E10000"),INDIRECT(B$1&"!$a1:$a10000")=汇总!$A108),COUNTIF(INDIRECT(B$1&"!$a1:$a10000"),汇总!$A108)),B107)} -> 168.1206 | C108: {=IFERROR(INDEX(_xlfn._xlws.FILTER(INDIRECT(C$1&"!$E1:$E10000"),INDIRECT(C$1&"!$a1:$a10000")=汇总!$A108),COUNTIF(INDIRECT(C$1&"!$a1:$a10000"),汇总!$A108)),C107)} -> 2172 | D108: {=IFERROR(INDEX(_xlfn._xlws.FILTER(INDIRECT(D$1&"!$E1:$E10000"),INDIRECT(D$1&"!$a1:$a10000")=汇总!$A108),COUNTIF(INDIRECT(D$1&"!$a1:$a10000"),汇总!$A108)),D107)} -> 3566.7203 | E108: {=IFERROR(INDEX(_xlfn._xlws.FILTER(INDIRECT(E$1&"!$E1:$E10000"),INDIRECT(E$1&"!$a1:$a10000")=汇总!$A108),COUNTIF(INDIRECT(E$1&"!$a1:$a10000"),汇总!$A108)),E107)} -> 916.29835 | F108: {=IFERROR(INDEX(_xlfn._xlws.FILTER(INDIRECT(F$1&"!$E1:$E10000"),INDIRECT(F$1&"!$a1:$a10000")=汇总!$A108),COUNTIF(INDIRECT(F$1&"!$a1:$a10000"),汇总!$A108)),F107)} -> 11482 | G108: {=IFERROR(INDEX(_xlfn._xlws.FILTER(INDIRECT(G$1&"!$E1:$E10000"),INDIRECT(G$1&"!$a1:$a10000")=汇总!$A108),COUNTIF(INDIRECT(G$1&"!$a1:$a10000"),汇总!$A108)),G107)} -> 5293.4 | H108: {=IFERROR(INDEX(_xlfn._xlws.FILTER(INDIRECT(H$1&"!$E1:$E10000"),INDIRECT(H$1&"!$a1:$a10000")=汇总!$A108),COUNTIF(INDIRECT(H$1&"!$a1:$a10000"),汇总!$A108)),H107)} -> 419 | I108: {=IFERROR(INDEX(_xlfn._xlws.FILTER(INDIRECT(I$1&"!$E1:$E10000"),INDIRECT(I$1&"!$a1:$a10000")=汇总!$A108),COUNTIF(INDIRECT(I$1&"!$a1:$a10000"),汇总!$A108)),I107)} -> 17.531309 | ... T108: {=IFERROR(INDEX(_xlfn._xlws.FILTER(INDIRECT(T$1&"!$E1:$E10000"),INDIRECT(T$1&"!$a1:$a10000")=汇总!$A108),COUNTIF(INDIRECT(T$1&"!$a1:$a10000"),汇总!$A108)),T107)} -> 0
A109: =+A108+1 -> 46130 | B109: {=IFERROR(INDEX(_xlfn._xlws.FILTER(INDIRECT(B$1&"!$E1:$E10000"),INDIRECT(B$1&"!$a1:$a10000")=汇总!$A109),COUNTIF(INDIRECT(B$1&"!$a1:$a10000"),汇总!$A109)),B108)} -> 168.1206 | C109: {=IFERROR(INDEX(_xlfn._xlws.FILTER(INDIRECT(C$1&"!$E1:$E10000"),INDIRECT(C$1&"!$a1:$a10000")=汇总!$A109),COUNTIF(INDIRECT(C$1&"!$a1:$a10000"),汇总!$A109)),C108)} -> 2172 | D109: {=IFERROR(INDEX(_xlfn._xlws.FILTER(INDIRECT(D$1&"!$E1:$E10000"),INDIRECT(D$1&"!$a1:$a10000")=汇总!$A109),COUNTIF(INDIRECT(D$1&"!$a1:$a10000"),汇总!$A109)),D108)} -> 3566.7203 | E109: {=IFERROR(INDEX(_xlfn._xlws.FILTER(INDIRECT(E$1&"!$E1:$E10000"),INDIRECT(E$1&"!$a1:$a10000")=汇总!$A109),COUNTIF(INDIRECT(E$1&"!$a1:$a10000"),汇总!$A109)),E108)} -> 916.29835 | F109: {=IFERROR(INDEX(_xlfn._xlws.FILTER(INDIRECT(F$1&"!$E1:$E10000"),INDIRECT(F$1&"!$a1:$a10000")=汇总!$A109),COUNTIF(INDIRECT(F$1&"!$a1:$a10000"),汇总!$A109)),F108)} -> 11482 | G109: {=IFERROR(INDEX(_xlfn._xlws.FILTER(INDIRECT(G$1&"!$E1:$E10000"),INDIRECT(G$1&"!$a1:$a10000")=汇总!$A109),COUNTIF(INDIRECT(G$1&"!$a1:$a10000"),汇总!$A109)),G108)} -> 5293.4 | H109: {=IFERROR(INDEX(_xlfn._xlws.FILTER(INDIRECT(H$1&"!$E1:$E10000"),INDIRECT(H$1&"!$a1:$a10000")=汇总!$A109),COUNTIF(INDIRECT(H$1&"!$a1:$a10000"),汇总!$A109)),H108)} -> 419 | I109: {=IFERROR(INDEX(_xlfn._xlws.FILTER(INDIRECT(I$1&"!$E1:$E10000"),INDIRECT(I$1&"!$a1:$a10000")=汇总!$A109),COUNTIF(INDIRECT(I$1&"!$a1:$a10000"),汇总!$A109)),I108)} -> 17.531309 | ... T109: {=IFERROR(INDEX(_xlfn._xlws.FILTER(INDIRECT(T$1&"!$E1:$E10000"),INDIRECT(T$1&"!$a1:$a10000")=汇总!$A109),COUNTIF(INDIRECT(T$1&"!$a1:$a10000"),汇总!$A109)),T108)} -> 0
... A168: =+A167+1 -> 46189 | B168: {=IFERROR(INDEX(_xlfn._xlws.FILTER(INDIRECT(B$1&"!$E1:$E10000"),INDIRECT(B$1&"!$a1:$a10000")=汇总!$A168),COUNTIF(INDIRECT(B$1&"!$a1:$a10000"),汇总!$A168)),B167)} -> 78.592656 | C168: {=IFERROR(INDEX(_xlfn._xlws.FILTER(INDIRECT(C$1&"!$E1:$E10000"),INDIRECT(C$1&"!$a1:$a10000")=汇总!$A168),COUNTIF(INDIRECT(C$1&"!$a1:$a10000"),汇总!$A168)),C167)} -> 2090 | D168: {=IFERROR(INDEX(_xlfn._xlws.FILTER(INDIRECT(D$1&"!$E1:$E10000"),INDIRECT(D$1&"!$a1:$a10000")=汇总!$A168),COUNTIF(INDIRECT(D$1&"!$a1:$a10000"),汇总!$A168)),D167)} -> 487.84341 | E168: {=IFERROR(INDEX(_xlfn._xlws.FILTER(INDIRECT(E$1&"!$E1:$E10000"),INDIRECT(E$1&"!$a1:$a10000")=汇总!$A168),COUNTIF(INDIRECT(E$1&"!$a1:$a10000"),汇总!$A168)),E167)} -> -2107.3149 | F168: {=IFERROR(INDEX(_xlfn._xlws.FILTER(INDIRECT(F$1&"!$E1:$E10000"),INDIRECT(F$1&"!$a1:$a10000")=汇总!$A168),COUNTIF(INDIRECT(F$1&"!$a1:$a10000"),汇总!$A168)),F167)} -> 2186.6524 | G168: {=IFERROR(INDEX(_xlfn._xlws.FILTER(INDIRECT(G$1&"!$E1:$E10000"),INDIRECT(G$1&"!$a1:$a10000")=汇总!$A168),COUNTIF(INDIRECT(G$1&"!$a1:$a10000"),汇总!$A168)),G167)} -> 9558.0087 | H168: {=IFERROR(INDEX(_xlfn._xlws.FILTER(INDIRECT(H$1&"!$E1:$E10000"),INDIRECT(H$1&"!$a1:$a10000")=汇总!$A168),COUNTIF(INDIRECT(H$1&"!$a1:$a10000"),汇总!$A168)),H167)} -> -83.365251 | I168: {=IFERROR(INDEX(_xlfn._xlws.FILTER(INDIRECT(I$1&"!$E1:$E10000"),INDIRECT(I$1&"!$a1:$a10000")=汇总!$A168),COUNTIF(INDIRECT(I$1&"!$a1:$a10000"),汇总!$A168)),I167)} -> 14.342121 | ... T168: {=IFERROR(INDEX(_xlfn._xlws.FILTER(INDIRECT(T$1&"!$E1:$E10000"),INDIRECT(T$1&"!$a1:$a10000")=汇总!$A168),COUNTIF(INDIRECT(T$1&"!$a1:$a10000"),汇总!$A168)),T167)} -> 9874.43

Sheet 元康盛景20号
A2: 日期 | B2: 现金流类型 | C2: 现金流入 | D2: 现金流出 | E2: 期末余额
A3: 46023 | E3: 619
A4: 45664 | B4: 雪球申购 | C4: 552 | E4: =E3+C4-D4 -> 1171
A5: 46029 | B5: 诚瑞1A2 | D5: 1003 | E5: 164 | F5: 鑫沅代持
A6: 46031 | B6: 新增申购 | C6: 302 | E6: =E5+C6-D6 -> 466
E7: 460
A8: 46034 | B8: 雪球申购 | C8: 121 | E8: =E7+C8-D8 -> 581
E9: =E8+C9-D9 -> 581
A10: 46034 | B10: 新增申购 | C10: 300 | E10: =E9+C10-D10 -> 881
A11: 46034 | B11: 赎回朗瑞1-5 | C11: 1100 | E11: =E10+C11-D11 -> 1981 | F11: 1-8申请 | G11: 能否提前到1-8的开放日赎回？；然后周一中午到账？
A12: 46034 | B12: 打新 | D12: 1216.5 | E12: =E11+C12-D12 -> 764.5
A13: 46035 | B13: 雪球申购 | C13: 128.4 | E13: =E12+C13-D13 -> 892.9
A14: 46035 | B14: 归还回购 | D14: 660.5 | E14: =E13+C14-D14 -> 232.4
A15: 46036 | B15: 打新 | C15: 1216 | E15: =E14+C15-D15 -> 1448.4 | F15: 涉及回来多少钱
A16: 46036 | B16: 熠然5A3 | D16: 501 | E16: =E15+C16-D16 -> 947.4 | F16: 1、熠然5A3[263739.SH]，500w，净价100元，1月14日，国泰海通 樊文娟 to 元康盛景20号 刘靖涛
A17: 46037 | B17: 云意电气 | C17: 5000 | E17: =E16+C17-D17 -> 5947.4
A18: 46037 | B18: 新增申购 | C18: 1000 | E18: =E17+C18-D18 -> 6947.4
E19: =E18+C19-D19 -> 6947.4
A20: 46037 | B20: 归还熠安02A3回购 | D20: 1247 | E20: =E19+C20-D20 -> 5700.4
A21: 46037 | B21: 回款 | C21: 170 | E21: =E20+C21-D21 -> 5870.4
E22: =E21+C22-D22 -> 5870.4
A23: 46038 | B23: 铁建051C | D23: 738 | E23: =E22+C23-D23 -> 5132.4 | F23: 铁建051C[199768.SH]，665w，111.075,1月16日，方田启航9号 to 元康盛景20号 刘靖涛
E24: 5134
A25: 46041 | B25: 支付增值税 | D25: 19 | E25: =E24+C25-D25 -> 5115
A26: 46041 | B26: 荟享244C | D26: 355 | E26: =E25+C26-D26 -> 4760 | F26: 1/19+0，荟享244C，146608.SZ，353w，净价100.159元，扬讯 出 元康盛景20号 刘靖涛
A27: 46041 | B27: 朗瑞1-5 | D27: 2600 | E27: =E26+C27-D27 -> 2160
A28: 46041 | B28: 雪球申购 | C28: 174 | E28: =E27+C28-D28 -> 2334
A29: 46041 | B29: 熠安02A3 | C29: 1112 | E29: =E28+C29-D29 -> 3446 | F29: 熠安02A3,144651.SZ,1172w,净价94.89, 1月19日，元康20号 to 扬讯
E30: 3441
A31: 46043 | B31: 雪球申购 | C31: 18 | E31: =E30+C31-D31 -> 3459
A32: 46043 | B32: 打新 | D32: 1550 | E32: =E31+C32-D32 -> 1909
E33: =E32+C33-D33 -> 1909
A34: 46044 | B34: =B5 -> 诚瑞1A2 | C34: =D5 -> 1003 | E34: =E33+C34-D34 -> 2912 | F34: 265418.SH，诚瑞1A2，1000W，净价100.15 1月22日，元康盛景20号 刘靖涛 to 新华日报基金：李旭彤2500116861
A35: 46045 | B35: 新增申购 | C35: 105 | E35: =E34+C35-D35 -> 3017
A36: 46045 | B36: 打新回款 | C36: 1550 | E36: =E35+C36-D36 -> 4567
A37: 46048 | B37: 荟享244C | C37: 353 | E37: =E36+C37-D37 -> 4920 | F37: 1/22+0，荟享244C，146608.SZ，353w，净价100.159元，元康盛景20号 刘靖涛 出 粤开证券（许逸潇）
A38: 46048 | B38: 雪球申购 | C38: 180 | E38: =E37+C38-D38 -> 5100
E39: =E38+C39-D39 -> 5100
A40: 46049 | B40: 新增申购 | C40: 100 | E40: 5207
A41: 46050 | B41: 雪球申购 | C41: 200 | E41: =E40+C41-D41 -> 5407 | F41: G铁建82C[266500.SH]，670w，102.104，1月29日，元康盛景20号 Z06308 to 鹏石启航9号 Z13506，约定号：222
A42: 46051 | B42: G铁建82C | C42: =870*1.02104 -> 888.3048 | E42: =E41+C42-D42 -> 6295.3048 | F42: G铁建82C[266500.SH]，200w，102.104，1月29日，元康盛景20号 Z06308 to 鹏石启航9号 Z13506，约定号：333
E43: =E42+C43-D43 -> 6295.3048
A44: 46051 | B44: 朗瑞1-5赎回 | C44: 603 | E44: =E43+C44-D44 -> 6898.3048
A45: 46051 | B45: 赎回 | D45: 6236 | E45: =E44+C45-D45 -> 662.3048
A46: 46052 | B46: 熠然5A3 | C46: 502 | E46: 1167 | F46: 熠然5A3[263739.SH],500w,100.237净价，1-30，元康盛景20号 to 扬讯
A47: 46052 | B47: 美市申购 | C47: 100 | E47: =E46+C47-D47 -> 1267
E48: =E47+C48-D48 -> 1267
A49: 46055 | B49: 雪球申购 | C49: 100 | E49: =E48+C49-D49 -> 1367
A50: 46055 | B50: 打新 | D50: 1019 | E50: =E49+C50-D50 -> 348
A51: 46055 | B51: 支付赎回款 | D51: 200 | E51: =E50+C51-D51 -> 148
E52: =E51+C52-D52 -> 148
A53: 46056 | B53: 赎回朗瑞1-5 | C53: 200 | E53: =E52+C53-D53 -> 348
A54: 46057 | B54: 雪球申购 | C54: 100 | E54: =E53+C54-D54 -> 448
A55: 46057 | B55: 回款打新 | C55: 1019 | E55: =E54+C55-D55 -> 1467
A56: 46057 | B56: 归还回购 | D56: 1400 | E56: 65
A57: 46062 | B57: 新增申购 | C57: 16 | E57: =E56+C57-D57 -> 81
E58: 81
A59: 46063 | B59: 雪球申购 | C59: 200 | E59: =E58+C59-D59 -> 281
A60: 46065 | B60: 雪球申购 | C60: 410 | E60: =E59+C60-D60 -> 691
A61: 46065 | B61: 4美意6次 | D61: =300*1.09914 -> 329.742 | E61: =E60+C61-D61 -> 361.258 | F61: 4美意6次 (262764.SH)，300w，全价109.914，2026-2-12，国泰海通 樊文娟 to 元康盛景20号 刘靖涛
E62: =E61+C62-D62 -> 361.258
A63: 46068 | B63: 美市申购 | C63: 116 | E63: =E62+C63-D63 -> 477.258
E64: =E63+C64-D64 -> 477.258
A65: 46077 | B65: 雪球申购 | C65: 130 | E65: =E64+C65-D65 -> 607.258
A66: 46077 | B66: 熠安02A3回款兑付 | C66: 285 | E66: =E65+C66-D66 -> 892.258
A67: 46080 | B67: 雪球申购 | C67: 305 | E67: =E66+C67-D67 -> 1197.258
E68: =E67+C68-D68 -> 1197.258
E69: =E68+C69-D69 -> 1197.258 | M69: 交易日 | N69: 收益率
A70: 46083 | B70: 4美意6次 | C70: =300*G70/100 -> 328.26 | E70: =E69+C70-D70 -> 1525.518 | F70: 4美意6次[262764.SH] ,300w,109.42全价，3月2日，元康盛景20号 to 扬讯；4美意6次[262764.SH] ,300w,109.43全价，3月2日，扬讯 to 苏信Z2502； | G70: 109.42 | J70: 5美意1次 | K70: 46079 | L70: 108.7534 | M70: 46083 | N70: 0.059 | O70: =L70*(1+N70/365*(M70-K70)) -> 108.82372
A71: 46083 | B71: 熠安02A3 | C71: =1100*G71/100 -> 763.91873 | E71: =E70+C71-D71 -> 2289.4367 | F71: 熠安02A3[144651.SZ]，1100w，净价69.39, 3/2，元康盛景20号 to 扬讯；熠安02A3[144651.SZ]，1100w，净价69.4, 3/2，扬讯 to 苏信财富Z2502； | G71: =H71+I71 -> 69.447157 | H71: 69.39 | I71: 0.057157014
A72: 46083 | B72: 铁建051C | C72: =665*G72/100 -> 744.0685 | E72: =E71+C72-D72 -> 3033.5052 | F72: 铁建051C（199768.SH），665w，111.89，3/2，元康盛景20号 to 扬讯；铁建051C（199768.SH），665w，111.90，3/2，扬讯 to 苏信财富Z2502； | G72: 111.89 | J72: 铁建051C | K72: 46079 | L72: 111.2463 | M72: 46083 | N72: 0.085 | O72: =L72*(1+N72/365*(M72-K72)) -> 111.34993
A73: 46083 | B73: 5美意1次 | C73: =2000*G73/100 -> 2176.28 | E73: =E72+C73-D73 -> 5209.7852 | F73: 5美意1次[263091.SH] ，2000w，108.814,3/2，元康盛景20号 to 扬讯；5美意1次[263091.SH] ，2000w，108.824,3/2，元康盛景20号 to 扬讯 | G73: 108.814 | J73: 4美意6次 | K73: 46079 | L73: 109.359 | M73: 46083 | N73: 0.059 | O73: =L73*(1+N73/365*(M73-K73)) -> 109.42971
E74: =E73+C74-D74 -> 5209.7852 | J74: 铁建051C | M74: 46038 | N74: 111.075 | O74: =N74*(1+6%/365*(M72-M74)) -> 111.89665
E75: =E74+C75-D75 -> 5209.7852
A76: 46083 | B76: 赎回 | D76: 4828 | E76: =E75+C76-D76 -> 381.78523
A77: 46084 | B77: 新增申购 | C77: 11 | E77: =E76+C77-D77 -> 392.78523
A78: 46085 | B78: 雪球申购 | C78: 45 | E78: =E77+C78-D78 -> 437.78523
E79: =E78+C79-D79 -> 437.78523
A80: 46087 | B80: 申购 | C80: 200 | E80: =E79+C80-D80 -> 637.78523
A81: 46087 | B81: 5美意3次 | C81: =1000*107.625/100 -> 1076.25 | E81: =E80+C81-D81 -> 1714.0352 | F81: 3/6, 5美意3次[263710.SH] ，1000w，107.625，元康盛景20号 刘靖涛 to 粤开证券 许逸潇2881647849 | G81: 107.63
E82: =E81+C82-D82 -> 1714.0352
E83: =E82+C83-D83 -> 1714.0352
A84: 46090 | B84: 雪球申购 | C84: 550 | E84: =E83+C84-D84 -> 2264.0352
A85: 46090 | B85: 申购朗瑞1-7 | D85: 2200 | E85: =E84+C85-D85 -> 64.035227 | F85: 周五定
E86: =E85+C86-D86 -> 64.035227
A87: 46092 | B87: 雪球申购 | C87: 1310 | E87: =E86+C87-D87 -> 1374.0352
A88: 46093 | B88: 荟享244C | D88: 329 | E88: =E87+C88-D88 -> 1045.0352
E89: =E88+C89-D89 -> 1045.0352
A90: 46094 | B90: 朗瑞1-5 | D90: 750 | E90: =E89+C90-D90 -> 295.03523
A91: 46094 | B91: 申购 | C91: 100 | E91: =E90+C91-D91 -> 395.03523
E92: =E91+C92-D92 -> 395.03523
A93: 46097 | B93: 雪球申购 | C93: 129 | E93: =E92+C93-D93 -> 524.03523
A94: 46097 | B94: 启宸6次 | D94: =540*82.512/100 -> 445.5648 | E94: =E93+C94-D94 -> 78.470427 | F94: 启宸6次 (262537.SH)，540w，82.512全价，3/16，西藏君达4号 to 元康盛景20号
E95: =E94+C95-D95 -> 78.470427
A96: 46104 | B96: 朗瑞1-5赎回 | C96: 1000 | E96: =E95+C96-D96 -> 1078.4704
A97: 46104 | B97: 兑付 | C97: 79.5 | E97: =E96+C97-D97 -> 1157.9704
A98: 46104 | B98: 雪球申购 | C98: 237 | E98: =E97+C98-D98 -> 1394.9704
A99: 46104 | B99: 申购朗瑞1-5 | D99: 1300 | E99: =E98+C99-D99 -> 94.970427
A100: 46105 | B100: 新增申购 | C100: 100 | E100: =E99+C100-D100 -> 194.97043
A101: 46106 | B101: 美市申购 | C101: 106 | E101: =E100+C101-D101 -> 300.97043
...

Sheet 元康盛景26号
A2: 日期 | B2: 现金流类型 | C2: 现金流入 | D2: 现金流出 | E2: 期末余额
A3: 46023 | E3: 4182
E4: =+E3+C4-D4 -> 4182
A5: 46027 | E5: 2377
A6: 46030 | B6: 普险29B | C6: 109 | E6: =+E5+C6-D6 -> 2486
A7: 46029 | B7: 盛煜015C | C7: 550 | E7: =+E6+C7-D7 -> 3036
A8: 46029 | B8: 泓晟1号3期优先B级 | C8: 430 | E8: =+E7+C8-D8 -> 3466
A9: 46029 | B9: 五矿赎回 | D9: 3213 | E9: =+E8+C9-D9 -> 253
E10: =+E9+C10-D10 -> 253
A11: 46034 | B11: 兑付回款 | C11: 5 | E11: =+E10+C11-D11 -> 258
A12: 46035 | B12: 五矿申购 | C12: 450 | E12: =+E11+C12-D12 -> 708
A13: 46037 | B13: 兑付回款 | C13: 217 | E13: =+E12+C13-D13 -> 925 | G13: 盘下1月15日的回款，注意质押
A14: 46038 | B14: 25乐信1C | C14: 600 | E14: =+E13+C14-D14 -> 1525 | F14: 25乐信1C[264610.SH]，600w，100，1月16日，元康盛景26号 to 芜湖扬讯 Z11825
A15: 46038 | B15: 炽诚3A3 | C15: 995 | E15: =+E14+C15-D15 -> 2520 | F15: 炽诚3A3[266980.SH]，1000w，99.5，1月16日，元康盛景26号 to 芜湖扬讯 Z11825
A16: 46038 | B16: DY03优3 | C16: 1000 | E16: =+E15+C16-D16 -> 3520 | F16: DY03优3[266192.SH]，1000w，100，1月16日，元康盛景26号 to 芜湖扬讯 Z11825
E17: =+E16+C17-D17 -> 3520
A18: 46038 | B18: 熠安02A3 | D18: 570 | E18: =+E17+C18-D18 -> 2950 | F18: 熠安02A3[144651.SZ]，600w，净价94.95，1月16日，元康22 to 扬讯
E19: 2951 | F19: 熠安02A3[144651.SZ]，600w，净价94.9548，1月16日， 扬讯 to 元康26
A20: 46041 | B20: 归还回购 | D20: 2632 | E20: =+E19+C20-D20 -> 319
A21: 46042 | B21: 新增申购 | C21: 180 | E21: =+E20+C21-D21 -> 499
A22: 46044 | B22: 底层回款 | C22: 462 | E22: =+E21+C22-D22 -> 961
A23: 46045 | B23: 底层回款 | C23: 28 | E23: =+E22+C23-D23 -> 989
E24: 993
A25: 46048 | B25: 底层回款 | C25: 242 | E25: =+E24+C25-D25 -> 1235
A26: 46049 | B26: 五矿追加 | C26: 1070 | E26: =+E25+C26-D26 -> 2305
A27: 46052 | B27: 底层回款 | C27: 53 | E27: =+E26+C27-D27 -> 2358
A28: 46052 | B28: 熠然5A3 | D28: 505 | E28: 1850 | F28: 熠然5A3[263739.SH],500w,100.247净价，1-30，扬讯 to 元康盛景26号
A29: 46058 | B29: 乐信 | D29: 1500 | E29: =+E28+C29-D29 -> 350 | F29: “乐信13C”代码：500421，1500w，3.5%，2-5缴款，2-6起息，元康盛景26号
E30: 347
E31: =+E30+C31-D31 -> 347
A32: 46059 | B32: 增加回购 | C32: 2090 | E32: =+E31+C32-D32 -> 2437
A33: 46063 | B33: 五矿赎回 | D33: =300*1.076 -> 322.8 | E33: =+E32+C33-D33 -> 2114.2
A34: 46065 | B34: 小鹏B | D34: 2000 | E34: =+E33+C34-D34 -> 114.2 | F34: 小鹏5B”代码：500446，2000w，3.3%，2月12日缴款，2月13日起息，元康盛景26号
A35: 46065 | B35: 星灿5A3 | D35: 18 | E35: =+E34+C35-D35 -> 96.2 | F35: 星灿5A3,144780.SZ,18w, 净价100,2月12日，国泰海通樊文娟 to 元康盛景26号 刘靖涛
A36: 46066 | B36: 回款 | C36: 2.7 | E36: =+E35+C36-D36 -> 98.9
E37: =+E36+C37-D37 -> 98.9
A38: 46077 | B38: 回款 | C38: 727 | E38: =+E37+C38-D38 -> 825.9 | F38: 剩余539w质押中
E39: =+E38+C39-D39 -> 825.9
E40: =+E39+C40-D40 -> 825.9
A41: 46078 | B41: 25YH1A2 | C41: 794 | E41: =+E40+C41-D41 -> 1619.9 | F41: 25YH1A2[264411.SH]，净价79.218，2-25，元康盛景26号 刘靖涛3003993899 to 中信证券 xxx
A42: 46078 | B42: 回购归还 | D42: 184.8 | E42: =+E41+C42-D42 -> 1435.1 | F42: 熠然5A3续作的时候，由于面值减少14元，回购续作本金金额会减少184.8
A43: 46079 | B43: 回款 | C43: 5.9 | E43: 1426
A44: 46079 | B44: 新增回购 | C44: 790 | E44: =+E43+C44-D44 -> 2216
A45: 46079 | B45: 归还回购-星灿5A3 | D45: 1625 | E45: =+E44+C45-D45 -> 591
A46: 46079 | B46: 回购释放-星灿5A3 | C46: 593 | E46: =+E45+C46-D46 -> 1184
A47: 46079 | B47: 25鑫驰1B | C47: 814 | E47: =+E46+C47-D47 -> 1998 | F47: 25号碰要素 | G47: 25鑫驰1B[146026.SZ]，800w，净价101.5，2月26日，元康盛景26号 刘靖涛 to 粤开许逸潇
A48: 46080 | B48: 回款 | C48: 15.4 | E48: =+E47+C48-D48 -> 2013.4
A49: 46080 | B49: 归还回购 | D49: 600 | E49: =+E48+C49-D49 -> 1413.4
E50: 1409
A51: 46083 | B51: 德银簿记 | D51: 200 | E51: =+E50+C51-D51 -> 1209 | F51: 德银07B/267906，200w，2.8%，3/2缴款，3/3起息，元康盛景26号
A52: 46083 | B52: 熹焱07A3 | C52: =苏信次级Z2502!D38 -> 327.92911 | E52: =+E51+C52-D52 -> 1536.9291
A53: 46083 | B53: 回款 | C53: 65 | E53: =+E52+C53-D53 -> 1601.9291 | N53: 待定的东方电气 | O53: 1000 | P53: 11000 | Q53: =O53+P53 -> 12000
A54: 46084 | B54: 归还熠然5A3回购 | D54: 1135 | E54: =+E53+C54-D54 -> 466.92911 | F54: 已沟通 | N54: 元康28 | O54: 500 | P54: 4000 | Q54: =O54+P54 -> 4500 | R54: 0.045 | S54: =Q54*R54 -> 202.5
E55: 469 | N55: 外贸1 | P55: =12000*25% -> 3000 | Q55: =O55+P55 -> 3000 | R55: 0.055 | S55: =Q55*R55 -> 165
A56: 46090 | B56: 五矿申购 | C56: 1400 | E56: =+E55+C56-D56 -> 1869 | N56: 元康26 | O56: 500 | P56: 4000 | Q56: =O56+P56 -> 4500 | R56: 0.03 | S56: =Q56*R56 -> 135
A57: 46092 | B57: 归还回购-朗煜1A3 | D57: 1115 | E57: =+E56+C57-D57 -> 754 | O57: =SUM(O54:O56) -> 1000 | P57: =SUM(P54:P56) -> 11000 | Q57: =SUM(Q54:Q56) -> 12000 | R57: =S57/(Q57) -> 0.041875 | S57: =SUM(S54:S56) -> 502.5
A58: 46093 | B58: 归还回购-25鑫驰2B | D58: 702 | E58: =+E57+C58-D58 -> 52
E59: =+E58+C59-D59 -> 52
A60: 46094 | B60: 新增1笔小回购 | C60: 100 | E60: =+E59+C60-D60 -> 152 | F60: 借100w，押券玮盈6B，200w，50%，3.5%，3-13~3-18，到期归还，正回购方：元康26号，逆回购方：粤财信托 吴海滨3007696781
A61: 46094 | B61: 25鑫驰1B | D61: 122 | E61: =+E60+C61-D61 -> 30 | F61: 1、3/13,25鑫驰1B[146026.SZ]，120w，净价101.5，询价是：厦门信托 李丹萍 3003775644+华宝投顾马路遥3007680164 to 中信证券 林秋益3004157238。
E62: =+E61+C62-D62 -> 30 | F62: 2、3/13,25鑫驰1B[146026.SZ]，120w，净价101.503，中信证券 林秋益3004157238 to 元康盛景26号 刘靖涛3003993899
A63: 46097 | B63: 回款 | C63: 749 | E63: =+E62+C63-D63 -> 779
A64: 46097 | B64: 西南证券申购 | C64: 500 | E64: =+E63+C64-D64 -> 1279
A65: 46097 | B65: 五矿申购 | C65: 120 | E65: =+E64+C65-D65 -> 1399
E66: =+E65+C66-D66 -> 1399
A67: 46098 | B67: 星灿5A3 | C67: =+苏信优先级Z2501!N38 -> 1780.3157 | E67: =+E66+C67-D67 -> 3179.3157 | F67: 苏信2501
B68: 熠然5A3 | C68: =+苏信优先级Z2501!N39 -> 2276.8068 | E68: =+E67+C68-D68 -> 5456.1225 | F68: 苏信2501
A69: 46099 | B69: 归还回购 | D69: 101 | E69: =+E68+C69-D69 -> 5355.1225
A70: 46101 | B70: 回款 | C70: 24 | E70: =+E69+C70-D70 -> 5379.1225
A71: 46104 | B71: 归还回购 | D71: 2955 | E71: =+E70+C71-D71 -> 2424.1225
A72: 46104 | B72: 回款 | C72: 336 | E72: =+E71+C72-D72 -> 2760.1225
A73: 46104 | B73: 五矿申购 | C73: 250 | E73: =+E72+C73-D73 -> 3010.1225
E74: =+E73+C74-D74 -> 3010.1225
A75: 46105 | B75: 归还回购 | D75: 850 | E75: =+E74+C75-D75 -> 2160.1225
A76: 46106 | B76: G蔚能1科 | D76: =1000*101.707% -> 1017.07 | E76: =+E75+C76-D76 -> 1143.0525
E77: =+E76+C77-D77 -> 1143.0525
A78: 46108 | B78: 诚惠3B | C78: 1006 | E78: =+E77+C78-D78 -> 2149.0525 | F78: 诚惠3B[266186.SH]，1000w，100.54，3月27日，元康盛景26号 刘靖涛3003993899 to 粤开证券 许逸潇2881647849 | G78: 诚惠3B[266186.SH]，1000w，100.545，3月27日，粤开证券 许逸潇2881647849 to 天风证券 唐德婷qt 2885078648
A79: 46108 | B79: 小鹏5B | C79: 1500 | E79: =+E78+C79-D79 -> 3649.0525 | F79: 小鹏5B[500446.SZ]，1500w，100.202，3月27日，元康盛景26号 刘靖涛3003993899 to 粤开证券 许逸潇2881647849 | G79: 小鹏5B[500446.SZ]，1500w，100.207，3月27日，粤开证券 许逸潇2881647849 to 天风证券 唐德婷qt 2885078648
A80: 46111 | B80: 360优先B | D80: 1900 | E80: =+E79+C80-D80 -> 1749.0525 | F80: 奇消22B 500577，1900w，2.8%，3月30日缴款，国联证券，元康盛景26号缴款
A81: 46112 | B81: 回款 | C81: 50 | E81: =+E80+C81-D81 -> 1799.0525
E82: =+E81+C82-D82 -> 1799.0525
A83: 46120 | B83: 乐信回款 | C83: 1103 | E83: =+E82+C83-D83 -> 2902.0525
A84: 46120 | B84: 赎回 | D84: =759.664103+0.601897 -> 760.266 | E84: =+E83+C84-D84 -> 2141.7865
E85: =+E84+C85-D85 -> 2141.7865
E86: =+E85+C86-D86 -> 2141.7865
A87: 46121 | B87: 考虑归还回购 | D87: 1000 | E87: =+E86+C87-D87 -> 1141.7865 | F87: 诚惠1B、狮桥60A2归还
E88: =+E87+C88-D88 -> 1141.7865
E89: =+E88+C89-D89 -> 1141.7865 | F89: 给中建投
E90: =+E89+C90-D90 -> 1141.7865 | F90: 未超1.2杠杆
A91: 46122 | B91: 管理费 | D91: 27.825586 | E91: =+E90+C91-D91 -> 1113.9609
A92: 46122 | B92: 应付税费 | D92: 38.998923 | E92: =+E91+C92-D92 -> 1074.962
E93: 1077
A94: 46127 | B94: 兑付 | C94: 280 | E94: =+E93+C94-D94 -> 1357
A95: 46128 | B95: 诚惠1B | C95: 305 | E95: =+E94+C95-D95 -> 1662 | F95: 诚惠1B[263867.SH]，300w，101.41，4月16日，元康盛景26号 刘靖涛3003993899 to 中信证券 赵恒昆3004076439 | G95: 诚惠1B[263867.SH]，300w，101.415，4月16日，中信证券 赵恒昆3004076439 to 粤开证券 许逸潇2881647849
E96: =+E95+C96-D96 -> 1662
A97: 46129 | B97: 小鹏5B | C97: 510 | E97: =+E96+C97-D97 -> 2172 | F97: 小鹏5B[500446.SZ]，500w，101.46，4月17日，元康盛景26号 刘靖涛3003993899 to 粤开证券 许逸潇2881647849 | G97: 小鹏5B[500446.SZ]，500w，101.465，4月17日，粤开证券 许逸潇2881647849 to 天风证券 李泽堃3007354220
E98: =+E97+C98-D98 -> 2172
A99: 46133 | B99: 五矿申购 | C99: 150 | E99: =+E98+C99-D99 -> 2322
A100: 46134 | B100: 毓消22B | D100: 1000 | E100: =+E99+C100-D100 -> 1322 | F100: 毓消22B，500693.SZ，1000w，2.8%，4月22日缴款，4月23日起息，元康盛景26号缴款
A101: 46134 | B101: 底层兑付 | C101: 508.27 | E101: =+E100+C101-D101 -> 1830.27
...

Sheet 元康盛景28号
A2: 日期 | B2: 现金流类型 | C2: 现金流入 | D2: 现金流出 | E2: 期末余额
A3: 46023 | E3: 97
A4: 46031 | B4: 新增申购 | C4: 500 | E4: =E3+C4-D4 -> 597
E5: 579
A6: 46034 | B6: 铁建051C | D6: =365*1.11025 -> 405.24125 | E6: =E5+C6-D6 -> 173.75875 | F6: 铁建051C (199768.SH)，365w，111.025，1月12日，方田远见2号 Z06704 （方田资本陈兴宇1519091045 ）to 元康盛景28号 刘靖涛，约定号：592
A7: 46035 | B7: 五矿申购 | C7: 450 | E7: =E6+C7-D7 -> 623.75875
A8: 46035 | B8: 铁建058C | D8: =279*1.09225 -> 304.73775 | E8: =E7+C8-D8 -> 319.021 | F8: 铁建058C[260655.SH]，279w，109.225,1月13日，方田远见9号 to 元康盛景28号 刘靖涛
A9: 46035 | B9: 宝冶兑付 | C9: 50 | E9: =E8+C9-D9 -> 369.021
A10: 46037 | B10: 回款 | C10: 319 | E10: =E9+C10-D10 -> 688.021
A11: 46038 | B11: 付管理费 | D11: 54 | E11: =E10+C11-D11 -> 634.021
A12: 46038 | B12: 新增申购-爱建 | C12: 300 | E12: =E11+C12-D12 -> 934.021
E13: =E12+C13-D13 -> 934.021
A14: 46041 | B14: 支付增值税 | D14: 17.7 | E14: =E13+C14-D14 -> 916.321
A15: 46041 | B15: 卖出给苏信 | E15: =E14+C15-D15 -> 916.321 | F15: 启悦15次，146285.SZ,500w，全价103.606,1月19日，元康28号to 扬讯
B16: 启悦16次 | C16: 308.067 | E16: =E15+C16-D16 -> 1224.388 | F16: 启悦16次,146761.SZ,300w,全价102.679，1月19日，元康28号 to 扬讯
B17: 熹焱03A3 | C17: 385.94788 | E17: =E16+C17-D17 -> 1610.3359 | F17: 熹焱03A3,144237.SZ,1000w,净价38.55，1月19日，元康28号 to 扬讯
B18: 熹焱07A3 | C18: 1864.342 | E18: =E17+C18-D18 -> 3474.6779 | F18: 熹焱07A3,144671.SZ,2310w,净价80.65，1月19日，元康28号 to 扬讯
B19: 启悦15次 | C19: 518.08 | E19: =E18+C19-D19 -> 3992.7579
E20: =E19+C20-D20 -> 3992.7579
A21: 46041 | B21: 归还回购 | D21: 1762 | E21: =E20+C21-D21 -> 2230.7579 | F21: 熠安02A3归还回购
A22: 46041 | B22: 释放回款 | C22: 189 | E22: =E21+C22-D22 -> 2419.7579
A23: 46041 | B23: 云信5美好3次 | D23: =1500*1.07743 -> 1616.145 | E23: =E22+C23-D23 -> 803.61291 | F23: 5美好3次[263313.SH]，1500w面值，107.743,1月19日，云南信托QT3004414706 to 元康盛景28号 刘靖涛qt3003993899
A24: 46041 | B24: 归还回购 | D24: 498 | E24: 298
A25: 46043 | B25: G铁建82C | C25: =1960*1.01973 -> 1998.6708 | E25: =E24+C25-D25 -> 2296.6708 | F25: G铁建82C[266500.SH]，1960w，101.973，1月21日，元康盛景28号 Z06308 to xxxx
A26: 46043 | B26: 京诚153B回款 | C26: 1015 | E26: =E25+C26-D26 -> 3311.6708
A27: 46043 | B27: 归还回购-铁建 | D27: 3206 | E27: =E26+C27-D27 -> 105.6708
A28: 46044 | B28: 回购利息 | D28: 8 | E28: =E27+C28-D28 -> 97.6708
A29: 46044 | B29: 底层回款 | C29: 263 | E29: =E28+C29-D29 -> 360.6708
A30: 46044 | B30: 潍坊保函 | D30: 100 | E30: =E29+C30-D30 -> 260.6708 | F30: 已发--“26潍信2C”：500363，100w.6.5%预期，1-22一级缴款，元康盛景28号
E31: =E30+C31-D31 -> 260.6708
A32: 46044 | B32: 增加回购 | C32: 2050 | E32: =E31+C32-D32 -> 2310.6708 | F32: 押券熠然03A3，2250*60%=1350；盛煜014D，1000*70%=700
A33: 46045 | B33: 4美意6次 | D33: =470*1.08874 -> 511.7078 | E33: =E32+C33-D33 -> 1798.963 | F33: 4美意6次 (262764.SH)，470w，全价108.874，2026-1-23，国泰海通 樊文娟 to 元康盛景28号 刘靖涛
A34: 46045 | B34: 5美意3次 | D34: =350*1.06951 -> 374.3285 | E34: =E33+C34-D34 -> 1424.6345 | F34: 5美意3次[263710.SH] ,350w，全价106.951，2026-1-23，国泰海通 樊文娟 to 元康盛景28号 刘靖涛
E35: 1427
A36: 46048 | B36: 广汽3次 | D36: =400*1.22349 -> 489.396 | E36: =E35+C36-D36 -> 937.604 | F36: 广汽3次[180987.SH]，400w，122.349,1月26日，国元证券 to 元康盛景28号 刘靖涛 qt3003993899
A37: 46048 | B37: 港融6C | D37: 100 | E37: =E36+C37-D37 -> 837.604 | F37: 铁建058C[260655.SH]，279w，109.494,1月28日，元康盛景28号 刘靖涛 to 方田远见9号 Z06704，约定号：617
A38: 46050 | B38: 铁建058C | C38: =279*1.09494 -> 305.48826 | E38: =E37+C38-D38 -> 1143.0923 | F38: 铁建081C[265587.SH], 1010w, 100.381,1月28日，元康盛景28号 刘靖涛 to方田远见8号 Z06704，约定号：618
A39: 46050 | B39: 铁建081C | C39: =1300*1.00381 -> 1304.953 | E39: =E38+C39-D39 -> 2448.0453 | F39: 铁建081C[265587.SH], 290w, 100.381,1月28日，元康盛景28号 刘靖涛 to方田远见8号 Z06704，约定号：619
A40: 46050 | B40: 铁建081C | D40: =1500*1.0002 -> 1500.3 | E40: =E39+C40-D40 -> 947.74526 | F40: 铁建081C[265587.SH] ,1500w,100.02,1月28日，国泰海通 樊文娟 to 元康盛景28号 刘靖涛
E41: =E40+C41-D41 -> 947.74526
E42: =E41+C42-D42 -> 947.74526 | R42: 铁建081C | S42: =XIRR(S43:S46,R43:R46) -> 0.05604926
A43: 46055 | B43: 铁建081C | C43: =1000*1.00456 -> 1004.56 | E43: =E42+C43-D43 -> 1952.3053 | F43: 铁建081C[265587.SH], 1000w, 100.456，2月2日，元康盛景28号 Z06308 to方田维纳3号 Z13506，约定号：621 | R43: 45832 | S43: -100
E44: =E43+C44-D44 -> 1952.3053 | R44: 45955 | S44: 1.726
E45: =E44+C45-D45 -> 1952.3053 | F45: GC广汽次[180718.SH]，700w，97.423，2月5日，粤开证券 to 元康盛景28号 | R45: 46044 | S45: 1.1781
A46: 46057 | B46: 铁建081C | C46: =920*1.00486 -> 924.4712 | E46: =E45+C46-D46 -> 2876.7765 | F46: 1、铁建081C[265587.SH]，920w，100.486，2月4日 | R46: 46058 | S46: =ROUND(-S43*(1+5.5%*(R46-R43)/365)-S44-S45,3) -> 100.501
A47: 46057 | B47: G铁建82C | C47: =620*1.02203 -> 633.6586 | E47: =E46+C47-D47 -> 3510.4351 | F47: 2、G铁建82C[266500.SH]，620w，102.203，2月4日
A48: 46058 | B48: 广汽2C | D48: =700*0.97423 -> 681.961 | E48: =E47+C48-D48 -> 2828.4741
A49: 46058 | B49: 铁建081C | C49: =410*1.00501 -> 412.0541 | E49: =E48+C49-D49 -> 3240.5282 | F49: 3、铁建081C[265587.SH]，410w，100.501，2月5日
A50: 46059 | B50: 荟臻032C卖出 | C50: =1600*1.368 -> 2188.8 | E50: =E49+C50-D50 -> 5429.3282 | F50: 荟臻032C (144302.SZ)，1600w，136.80,2月6日， 元康盛景28号 刘靖涛 to 中金 王思路2881374727
E51: 5420 | R51: G铁建82C | S51: =XIRR(S52:S57,R52:R57) -> 0.061152586
E52: =E51+C52-D52 -> 5420 | R52: 45923 | S52: -100
A53: 46063 | B53: 五矿申购 | C53: 500 | E53: =E52+C53-D53 -> 5920 | H53: 5美好3次 | I53: 1500 | J53: 0.7 | K53: 1050 | L53: 长期
A54: 46063 | B54: 增加回购 | C54: 2187 | E54: =E53+C54-D54 -> 8107 | F54: 已沟通，正常排 | H54: 熠安02A3 | I54: 2000 | J54: 0.6 | K54: =I54*94.79%*J54 -> 1137.48 | L54: 1个月左右
A55: 46063 | B55: 铁建交易 | D55: 1718 | E55: =E54+C55-D55 -> 6389
A56: 46064 | B56: 铁建交易卖出 | C56: =1718 -> 1718 | E56: =E55+C56-D56 -> 8107
E57: =E56+C57-D57 -> 8107 | R57: 46057 | S57: =ROUND(-S52*(1+6%*(R57-R52)/365),3) -> 102.203
A58: 46064 | B58: 赎回 | D58: =302*1.11 -> 335.22 | E58: =E57+C58-D58 -> 7771.78
A59: 46065 | B59: 小鹏次级 | D59: 7505 | E59: =E58+C59-D59 -> 266.78 | F59: “小鹏5次”代码：500447，7505w，6.8%（单利）。2月12日缴款，2月13日起息，元康盛景28号
A60: 46064 | B60: 泸州银行保函 | D60: 100 | E60: =E59+C60-D60 -> 166.78 | F60: 泸融3C(500471)，100w，7%（单利），2月11日缴款，2月12期起息，元康盛景28号
A61: 46065 | B61: 潍坊次级 | D61: 100 | E61: =E60+C61-D61 -> 66.78 | F61: “潍坊01C”267941，100w，2月12期缴款，2月13日起息，元康盛景28号
A62: 46065 | B62: 爱建新增申购 | C62: 400 | E62: =E61+C62-D62 -> 466.78 | F62: 走加急打款流程
A63: 46065 | B63: 新增回购 | C63: 600 | E63: =E62+C63-D63 -> 1066.78 | F63: 借600w，3.5%，14d，2026-2-12~2026-2-26；押券G光环1次，146092.SZ，750w，80%；正回购方：元康盛景28号 刘靖涛，逆回购方：安远 赵英明qq2929561305
A64: 46065 | B64: 熠然5A3 | D64: 898 | E64: =E63+C64-D64 -> 168.78 | F64: 熠然5A3，263739.SH，895w，净价100,2月12日，国泰海通 樊文娟 to 元康盛景28号 刘靖涛
E65: 160
E66: =E65+C66-D66 -> 160
A67: 46077 | B67: 回款 | C67: 748 | E67: =E66+C67-D67 -> 908
A68: 46077 | B68: 熠安02A3回购续作减少 | D68: 305.76 | E68: =E67+C68-D68 -> 602.24
A69: 46078 | B69: 提前归还回购 | D69: 245 | E69: 341
A70: 46080 | B70: 马欢代持买回铁建081C | C70: =1585*100.833/100 -> 1598.203 | E70: =E69+C70-D70 -> 1939.203 | F70: 100.833 | H70: 101.4294 | I70: =H70-F70 -> 0.5964 | J70: 1、铁建081C（265587.SH），240w，100.833，2月27日，元康盛景28号 Z06308 to方田远见5号 Z13506，约定号：631
E71: =E70+C71-D71 -> 1939.203 | J71: 2、铁建081C（265587.SH），830w，100.833，2月27日，元康盛景28号 Z06308 to方田远见8号 Z06704，约定号：632
A72: 46080 | B72: 大业申购 | C72: 2000 | E72: =E71+C72-D72 -> 3939.2031 | J72: 3、铁建081C（265587.SH），515w，100.833，2月27日，元康盛景28号 Z06308 to鹏石启航9号 Z13506，约定号：633
A73: 46080 | B73: 归还回购 | D73: 600 | E73: =E72+C73-D73 -> 3339.2031
A74: 46080 | B74: 新增回购 | C74: 600 | E74: =E73+C74-D74 -> 3939.2031
A75: 46083 | B75: 回款 | C75: 140 | E75: =E74+C75-D75 -> 4079.2031
A76: 46083 | B76: G光环1次回款 | C76: =1100*102.2137/100 -> 1124.3507 | E76: =E75+C76-D76 -> 5203.5538 | O76: 5美意3次 | P76: =XIRR(P77:P78,O77:O78) -> 0.058523878 | R76: 5美意4次 | S76: =XIRR(S77:S78,R77:R78) -> 0.05852972
A77: 46083 | B77: 5美意4次 | D77: =1250*1.07549 -> 1344.3625 | E77: =E76+C77-D77 -> 3859.1912 | F77: 5美意4次，263707.SH，1250w，107.549,3/2, 西藏信托君集2号 2850981264钟振涛 to 元康盛景28号 刘靖涛 | O77: 45615 | P77: -100 | R77: 45616 | S77: -100
A78: 46083 | B78: 启恒次级 | D78: 500 | E78: =E77+C78-D78 -> 3359.1912 | F78: 启恒1次，500486，500w。5.98%预期收益率，3月2日缴款，3月3日起息，元康盛景28号 | O78: 46083 | P78: =ROUND(-P77*(1+5.9%*(O78-O77)/365),3) -> 107.565 | R78: 46083 | S78: =ROUND(-S77*(1+5.9%*(R78-R77)/365),3) -> 107.549
A79: 46083 | B79: 归还回购-熠安02A3 | D79: 831 | E79: =E78+C79-D79 -> 2528.1912
A80: 46083 | B80: 释放回款-熠安02A3 | C80: 500 | E80: =E79+C80-D80 -> 3028.1912
E81: =E80+C81-D81 -> 3028.1912
A82: 46083 | B82: ZJCF08C | D82: =1100*100.894/100 -> 1109.834 | E82: =E81+C82-D82 -> 1918.3572 | F82: 100.894 | G82: ZJCF08C，266715.SH，1100w，100.894全价，3/2，元康盛景22号 to 扬讯 | M82: 2/5+0
A83: 46084 | B83: 提前归还回购DY03优3 | D83: 1800 | E83: =E82+C83-D83 -> 118.35725 | G83: ZJCF08C，266715.SH，1100w，100.904全价，3/2，扬讯 to 元康盛景28号 | M83: ZJCF08C，266715.SH，
A84: 46084 | B84: 宝冶 | C84: =900*101.026/100 -> 909.234 | E84: =E83+C84-D84 -> 1027.5912 | F84: 宝冶25次（265833.SH），101.026,900w，3/3，芜湖元康出给国民信托 | M84: 净价100.55，1100w
A85: 46084 | B85: 元康盛景30号申购 | C85: 400 | E85: =E84+C85-D85 -> 1427.5912 | O85: ZJCF08C | P85: =XIRR(P86:P87,O86:O87) -> 0.051128164
A86: 46085 | B86: 赎回 | D86: =71*1.11 -> 78.81 | E86: 1364 | O86: 46058 | P86: -100.55
A87: 46087 | B87: 新增申购 | C87: 350 | E87: =E86+C87-D87 -> 1714 | O87: 46083 | P87: 100.894 | Q87: =-P86*(1+R87*(O87-O86)/365) -> 100.89435 | R87: 0.05
A88: 46087 | B88: 5美意3次 | C88: =700*1.07625 -> 753.375 | E88: =E87+C88-D88 -> 2467.375 | F88: 3/6, 5美意3次[263710.SH] ，700w，107.625，元康盛景28号 刘靖涛 to 粤开证券 许逸潇2881647849
E89: =E88+C89-D89 -> 2467.375
A90: 46090 | B90: 5美好3次 | D90: =50*1.08535 -> 54.2675 | E90: =E89+C90-D90 -> 2413.1075 | F90: 3/9，5美好3次[263313.SH] ，50w，108.535，国泰海通樊文娟 to元康盛景28号 刘靖涛
A91: 46090 | B91: 5美意3次 | D91: =150*1.07678 -> 161.517 | E91: =E90+C91-D91 -> 2251.5905 | F91: 3/9，5美意3次[263710.SH] ，150w，107.678，国泰海通樊文娟 to元康盛景28号 刘靖涛
E92: =E91+C92-D92 -> 2251.5905
E93: =E92+C93-D93 -> 2251.5905
E94: =E93+C94-D94 -> 2251.5905
A95: 46091 | B95: 新增申购 | C95: 1000 | E95: =E94+C95-D95 -> 3251.5905
A96: 46091 | B96: 新增回购DY03优3 | C96: 1800 | E96: =E95+C96-D96 -> 5051.5905
A97: 46091 | B97: 新增回购-玮盈 | C97: 1080 | E97: =E96+C97-D97 -> 6131.5905
A98: 46091 | B98: 赎回-五矿 | D98: 2549.9 | E98: =E97+C98-D98 -> 3581.6905
A99: 46091 | B99: 工鑫41次 | D99: =1500*103.091/100 -> 1546.365 | E99: =E98+C99-D99 -> 2035.3255
A100: 46092 | B100: 工鑫41次 | C100: =1500*103.109/100 -> 1546.635 | E100: =E99+C100-D100 -> 3581.9605
A101: 46092 | B101: 赎回 | D101: =140*1.116 -> 156.24 | E101: =E100+C101-D101 -> 3425.7205
...

Sheet 元康盛景29号
T1: 剩余待补收益
A2: 日期 | B2: 现金流类型 | C2: 现金流入 | D2: 现金流出 | E2: 期末余额 | R2: 23建鑫8C需补收益 | S2: 591186 | T2: =+S2 -> 591186
A3: 46023 | E3: 234 | R3: 24兴瑞8C补 | S3: 38739.041 | T3: =+T2-S3 -> 552446.96
E4: =+E3+C4-D4 -> 234 | R4: 23中誉1C | S4: 0 | T4: =+T3-S4 -> 552446.96 | U4: 未交易
A5: 46027 | B5: 新增申购 | C5: 972 | E5: =E4+C5-D5 -> 1206 | R5: 24臻粹3C | S5: 525 | T5: =+T4-S5 -> 551921.96
A6: 46030 | B6: 新增申购 | C6: 550 | E6: =E5+C6-D6 -> 1756 | R6: 24邮盈惠兴4C | S6: 18800 | T6: =+T5-S6 -> 533121.96
A7: 46031 | B7: 申购朗瑞1-8 | D7: 1200 | E7: =E6+C7-D7 -> 556 | R7: 23工元至诚8C | S7: 331500 | T7: =+T6-S7 -> 201621.96
A8: 46031 | B8: 支付管理费 | D8: 120 | E8: =E7+C8-D8 -> 436 | R8: 25兴瑞1C | S8: 15480 | T8: =+T7-S8 -> 186141.96
E9: 436 | R9: 25橙益4C | S9: 10010 | T9: =+T8-S9 -> 176131.96
A10: 46037 | B10: 东吴申购 | C10: 5000 | E10: =E9+C10-D10 -> 5436 | R10: 24浦鑫归航8C | S10: 54000 | T10: =+T9-S10 -> 122131.96
A11: 46037 | B11: 新增申购 | C11: 536 | E11: =E10+C11-D11 -> 5972 | R11: 24建欣6C | S11: =朗瑞1_8!T29 -> 13224 | T11: =+T10-S11 -> 108907.96
A12: 46038 | B12: 申购朗瑞1-8 | D12: 500 | E12: =E11+C12-D12 -> 5472 | R12: 24橙益17C | S12: =朗瑞1_8!T30 -> 20020 | T12: =+T11-S12 -> 88887.959
E13: =E12+C13-D13 -> 5472 | R13: 25浦鑫归航1C | S13: =鹏雅120!M16 -> 88884 | T13: =+T12-S13 -> 3.9589041
E14: =E13+C14-D14 -> 5472 | G14: 待买回证券
E15: =E14+C15-D15 -> 5472 | G15: 证券名称 | H15: 合作方 | I15: 资产类别 | J15: 成本 | K15: 合作方最早买入时间 | L15: 买入规模 | M15: 持仓规模 | N15: 剩余本金 | O15: 面值 | P15: 下个本金兑付日 | Q15: 预计交易日期 | R15: 预期交易价格 | S15: 预计交易金额 | T15: 补23建鑫8C收益
A16: 46044 | B16: 申购朗瑞1-8 | D16: 2500 | E16: =E15+C16-D16 -> 2972 | G16: 23中誉1C | H16: 国泰海通 | I16: 住房抵押贷款 | J16: 0.05 | K16: 45023 | L16: 89875 | M16: 75 | N16: 0 | O16: 39.25 | P16: 46079 | Q16: 46041 | R16: =I28 -> 57.8 | S16: =R16*M16 -> 4335 | T16: =+(H28-I28)*M16 -> 210 | U16: 有可能本期本金兑付完毕
A17: 46044 | B17: 申购朗瑞1-5 | D17: 800 | E17: =E16+C17-D17 -> 2172 | G17: 24臻粹3C | H17: 国泰海通 | I17: 信用卡消费贷款 | J17: 0.045 | K17: 45523 | L17: 82500 | M17: 700 | N17: 0 | O17: 40.27 | P17: 46045 | Q17: =+Q16 -> 46041 | R17: =+M30 -> 57.1 | S17: =R17*M17 -> 39970 | T17: =+(L30-M30)*M17 -> 525 | U17: 月付，可推迟到下个月兑付前交易
A18: 46045 | B18: 新增申购 | C18: 678 | E18: =E17+C18-D18 -> 2850 | G18: 24邮盈惠兴4C | H18: 国泰海通 | I18: 信用卡消费贷款 | J18: 0.05 | K18: 45806 | L18: 40000 | M18: 40000 | N18: 440.64 | O18: 23.83 | P18: 46048 | Q18: =+Q17 -> 46041 | R18: =+Q27 -> 35.9 | S18: =R18*M18 -> 1436000 | T18: =+(P27-Q27)*M18 -> 18800 | U18: 本期必须买回
A19: 46045 | B19: 赎回 | D19: 74.6 | E19: =E18+C19-D19 -> 2775.4 | G19: 24邮盈惠兴5C | H19: 银河 | I19: 微小企业贷款 | J19: 0.05 | K19: 45862 | L19: 14000 | M19: 14000 | N19: 88.606 | O19: 40.05 | P19: 46048 | Q19: =+Q18 -> 46041 | R19: =+H40 -> 47.9555 | S19: =R19*M19 -> 671377 | U19: 本期必须买回
A20: 46045 | B20: 中航信托收款 | C20: 80.7 | E20: =E19+C20-D20 -> 2856.1 | G20: 24中誉至诚9C | H20: 国联 | I20: 信用卡消费贷款 | J20: 0.05 | K20: 45656 | L20: 6800 | M20: 6800 | N20: 68.68 | O20: 100 | P20: 46048 | Q20: =+Q19 -> 46041 | R20: =+L38 -> 106.33 | S20: =R20*M20 -> 723044
A21: 46051 | B21: 赎回朗瑞1-5 | C21: 507 | E21: =E20+C21-D21 -> 3363.1 | S21: =SUM(S17:S20) -> 2870391
E22: =+E21+C22-D22 -> 3363.1
E23: =+E22+C23-D23 -> 3363.1 | G23: 23中誉1C | H23: =XIRR(H24:H30,G24:G30) -> 0.050110647 | I23: =XIRR(I24:I30,G24:G30) -> 0.040020677 | K23: 24臻粹3C | L23: =XIRR(L24:L30,K24:K30) -> 0.045003799 | M23: =XIRR(M24:M30,K24:K30) -> 0.039925483 | O23: 24邮盈惠兴4C | P23: =XIRR(P24:P27,O24:O27) -> 0.050075492 | Q23: =XIRR(Q24:Q30,O24:O30) -> 0.040145227
E24: =+E23+C24-D24 -> 3363.1 | G24: 45023 | H24: -108 | I24: =+H24 -> -108 | K24: 45523 | L24: -111 | M24: =+L24 -> -111 | O24: 45806 | P24: -110.16 | Q24: =+P24 -> -110.16
E25: =+E24+C25-D25 -> 3363.1 | G25: 45530 | H25: 8.78 | I25: =+H25 -> 8.78 | K25: 45894 | L25: 7.55 | M25: =+L25 -> 7.55 | O25: 45866 | P25: 22.53 | Q25: =+P25 -> 22.53
A26: 46052 | B26: 鹏雅120 | D26: 300 | E26: =+E25+C26-D26 -> 3063.1 | G26: 45714 | H26: 31.21 | I26: =+H26 -> 31.21 | K26: 45923 | L26: 10.36 | M26: =+L26 -> 10.36 | O26: 45957 | P26: 53.64 | Q26: =+P26 -> 53.64
A27: 46055 | B27: 新增申购 | C27: 138 | E27: =+E26+C27-D27 -> 3201.1 | G27: 45895 | H27: 20.76 | I27: =+H27 -> 20.76 | K27: 45953 | L27: 14.23 | M27: =+L27 -> 14.23 | O27: =Q18 -> 46041 | P27: 36.37 | Q27: 35.9
A28: 46055 | B28: 赎回 | D28: 47 | E28: =+E27+C28-D28 -> 3154.1 | G28: =+Q16 -> 46041 | H28: 60.6 | I28: 57.8 | K28: 45985 | L28: 14.32 | M28: =+L28 -> 14.32 | P28: 23工元至诚8C[2389487.IB] ，1300w，126.90,1月22日，t+0，国泰海通 冉雅婷 to 外贸信托朗瑞1号8期 孟亚琪
E29: =+E28+C29-D29 -> 3154.1 | K29: 46014 | L29: 13.27 | M29: =+L29 -> 13.27 | P29: 25橙益4C[2589087.IB] ，130w，108.12,1月22日，t+0，国泰海通 冉雅婷 to 外贸信托朗瑞1号8期 孟亚琪
E30: =+E29+C30-D30 -> 3154.1 | K30: =+Q17 -> 46041 | L30: 57.85 | M30: 57.1 | P30: 25兴瑞1C[2589025.IB] ，180w，108.48,1月22日，t+0，国泰海通 冉雅婷 to 外贸信托朗瑞1号8期 孟亚琪
A31: 46056 | B31: 全景1号 | D31: 2000 | E31: =+E30+C31-D31 -> 1154.1 | P31: 24浦鑫归航8C[2489436.IB]，500w，104.29,1月22日，t+0，国泰海通 冉雅婷 to 外贸信托朗瑞1号8期 孟亚琪
E32: =+E31+C32-D32 -> 1154.1 | G32: 24臻粹3C[2489229.IB]，7w，全价57.1,1月16日，t+0，国泰海通 冉雅婷 to 外贸信托朗瑞1号8期 孟亚琪 | P32: 23工元至诚8C | Q32: =XIRR(Q33:Q34,P33:P34) -> 0.050032941 | R32: =XIRR(R33:R34,P33:P34) -> 0.039995083 | T32: 25橙益4C | U32: =XIRR(U33:U34,T33:T34) -> 0.050026986 | V32: =XIRR(V33:V34,T33:T34) -> 0.040075198
A33: 46062 | B33: 申购 | C33: 1449 | E33: 2600 | G33: 24邮盈惠兴4C[2489188.IB]，400w，全价35.9,1月16日，t+0，国泰海通 冉雅婷 to 外贸信托朗瑞1号8期 孟亚琪 | P33: 45288 | Q33: -117 | R33: =Q33 -> -117 | T33: 45772 | U33: -105 | V33: =U33 -> -105
A34: 46062 | B34: 追加鹏雅120 | D34: 1850 | E34: =+E33+C34-D34 -> 750 | G34: 24邮盈惠兴5C[2489255.IB]，140w，全价47.9555, 1月19日，t+0，银河 赵恩聪 to 外贸信托朗瑞1号8期 孟亚琪 | P34: 46044 | Q34: 129.45 | R34: 126.9 | T34: 46044 | U34: 108.89 | V34: 108.12
A35: 46065 | B35: 申购 | C35: 56 | E35: =+E34+C35-D35 -> 806 | G35: 24中誉至诚9C[2489430.IB]，68w，全价106.33,1月16日，t+0，国联 to 外贸信托朗瑞1号8期 孟亚琪（未成交） | P35: 交易份额 | Q35: 1300 | R35: =Q35 -> 1300 | T35: 交易份额 | U35: 130 | V35: =U35 -> 130
E36: 809 | G36: 24邮盈惠兴5C | H36: =XIRR(H37:H40,G37:G40) -> 0.050026587 | K36: 24中誉至诚9C | L36: =XIRR(L37:L43,K37:K43) -> 0.049963519 | P36: 交易金额 | Q36: =Q35*Q34*100 -> 16828500 | R36: =R35*R34*100 -> 16497000 | T36: 交易金额 | U36: =U35*U34*100 -> 1415570 | V36: =V35*V34*100 -> 1405560
A37: 46078 | B37: 回款 | C37: 451 | E37: =+E36+C37-D37 -> 1260 | G37: 45862 | H37: -106.22 | K37: 45656 | L37: -101 | P37: 补23建鑫8C收益 | Q37: =Q36-R36 -> 331500 | T37: 补23建鑫8C收益 | U37: =U36-V36 -> 10010
A38: 46078 | B38: 赎回 | D38: 105.8 | E38: =+E37+C38-D38 -> 1154.2 | G38: 45866 | H38: 17.02 | K38: =+Q20 -> 46041 | L38: 106.33
A39: 46079 | B39: 赎回 | D39: =9.9*1.07 -> 10.593 | E39: =+E38+C39-D39 -> 1143.607 | G39: 45957 | H39: 42.93 | P39: 25兴瑞1C | Q39: =XIRR(Q40:Q41,P40:P41) -> 0.04999927 | R39: =XIRR(R40:R41,P40:P41) -> 0.040058771 | T39: 24浦鑫归航8C | U39: =XIRR(U40:U41,T40:T41) -> 0.050041315 | V39: =XIRR(V40:V41,T40:T41) -> 0.039991048
E40: =+E39+C40-D40 -> 1143.607 | G40: =Q19 -> 46041 | H40: 47.9555 | P40: 45741 | Q40: -105 | R40: -105 | T40: 45653 | U40: -100 | V40: =U40 -> -100
E41: =+E40+C41-D41 -> 1143.607 | P41: 46044 | Q41: 109.34 | R41: 108.48 | T41: 46044 | U41: 105.37 | V41: 104.29
E42: =+E41+C42-D42 -> 1143.607 | F42: 2/27赎回 | P42: 交易份额 | Q42: 180 | R42: =Q42 -> 180 | T42: 交易份额 | U42: 500 | V42: =U42 -> 500
A43: 46084 | B43: 朗瑞1-8赎回 | C43: 1200 | E43: =+E42+C43-D43 -> 2343.607 | F43: 2/27赎回 | P43: 交易金额 | Q43: =Q42*Q41*100 -> 1968120 | R43: =R42*R41*100 -> 1952640 | T43: 交易金额 | U43: =U42*U41*100 -> 5268500 | V43: =V42*V41*100 -> 5214500
A44: 46084 | B44: 全景1号 | D44: 1000 | E44: =+E43+C44-D44 -> 1343.607 | P44: 补23建鑫8C收益 | Q44: =Q43-R43 -> 15480 | T44: 补23建鑫8C收益 | U44: =U43-V43 -> 54000
A45: 46085 | B45: 鹏雅120提取 | C45: 660 | E45: =+E44+C45-D45 -> 2003.607
A46: 46085 | B46: 申购朗瑞1-5 | D46: 5 | E46: 2001
A47: 46086 | B47: 申购 | C47: 900 | E47: =+E46+C47-D47 -> 2901
E48: =+E47+C48-D48 -> 2901
A49: 46094 | B49: 申购 | C49: 1084 | E49: =+E48+C49-D49 -> 3985
A50: 46094 | B50: 申购朗瑞1-8 | D50: 100 | E50: =+E49+C50-D50 -> 3885
A51: 46094 | B51: 朗瑞1-8赎回 | C51: 2200 | E51: =+E50+C51-D51 -> 6085
E52: =+E51+C52-D52 -> 6085
A53: 46099 | B53: 鹏雅120提取 | C53: 276 | E53: =+E52+C53-D53 -> 6361
A54: 46100 | B54: 新增申购 | C54: 606 | E54: =+E53+C54-D54 -> 6967
E55: =+E54+C55-D55 -> 6967
A56: 46104 | B56: 朗瑞1-5申购 | D56: 300 | E56: =+E55+C56-D56 -> 6667
A57: 46105 | B57: 鹏雅120追加 | D57: 1030 | E57: =+E56+C57-D57 -> 5637
A58: 46105 | B58: 回款-天启 | C58: 368 | E58: =+E57+C58-D58 -> 6005
E59: =+E58+C59-D59 -> 6005
E60: 6004
E61: =+E60+C61-D61 -> 6004
A62: 46111 | B62: 申购 | C62: 880 | E62: =+E61+C62-D62 -> 6884
E63: =+E62+C63-D63 -> 6884
A64: 46111 | B64: 朗瑞1-8赎回 | C64: 1663 | E64: =+E63+C64-D64 -> 8547
A65: 46111 | B65: 赎回 | D65: 745 | E65: =+E64+C65-D65 -> 7802
E66: =+E65+C66-D66 -> 7802
A67: 46112 | B67: 申购鹏雅120 | D67: 2150 | E67: =+E66+C67-D67 -> 5652
A68: 46115 | B68: 赎回 | D68: 786.13602 | E68: =+E67+C68-D68 -> 4865.864
E69: =+E68+C69-D69 -> 4865.864
A70: 46115 | B70: 申购 | C70: 130 | E70: =+E69+C70-D70 -> 4995.864
A71: 46115 | B71: 赎回斑羚8号 | C71: 110 | E71: =+E70+C71-D71 -> 5105.864
A72: 46119 | B72: 申购鹏雅120 | D72: 750 | E72: =+E71+C72-D72 -> 4355.864
A73: 46120 | B73: 全景1号 | D73: 650 | E73: =+E72+C73-D73 -> 3705.864
A74: 46120 | B74: 管理费 | D74: 140.13587 | E74: =+E73+C74-D74 -> 3565.7281
A75: 46120 | B75: 托管行政费 | D75: =1.40136*2 -> 2.80272 | E75: =+E74+C75-D75 -> 3562.9254
E76: =+E75+C76-D76 -> 3562.9254
E77: =+E76+C77-D77 -> 3562.9254
E78: =+E77+C78-D78 -> 3562.9254
A79: 46121 | B79: 追加鹏雅120 | D79: 150 | E79: =+E78+C79-D79 -> 3412.9254
A80: 46122 | B80: 申购 | C80: 139 | E80: =+E79+C80-D80 -> 3551.9254
A81: 46122 | B81: 赎回 | D81: 3491.76 | E81: =+E80+C81-D81 -> 60.165387
A82: 46122 | B82: 支付业绩报酬 | D82: 14.645 | E82: =+E81+C82-D82 -> 45.520387
E83: =+E82+C83-D83 -> 45.520387
A84: 46128 | B84: 申购 | C84: 342 | E84: =+E83+C84-D84 -> 387.52039
A85: 46134 | B85: 鹏雅120期 | D85: 210 | E85: =+E84+C85-D85 -> 177.52039 | F85: 已发
A86: 46135 | B86: 申购 | C86: 225 | E86: =+E85+C86-D86 -> 402.52039
A87: 46135 | B87: 信托利益分配 | C87: 324 | E87: =+E86+C87-D87 -> 726.52039
E88: =+E87+C88-D88 -> 726.52039
A89: 46140 | B89: 朗瑞1-8赎回 | C89: 2300 | E89: =+E88+C89-D89 -> 3026.5204
A90: 46140 | B90: 鹏雅120 | D90: 1500 | E90: =+E89+C90-D90 -> 1526.5204 | F90: 已发
A91: 46141 | B91: 申购朗瑞1-8 | D91: 30 | E91: =+E90+C91-D91 -> 1496.5204
E92: =+E91+C92-D92 -> 1496.5204
A93: 46142 | B93: 申购 | C93: 100 | E93: =+E92+C93-D93 -> 1596.5204
E94: =+E93+C94-D94 -> 1596.5204
A95: 46150 | B95: 申购 | C95: 190 | E95: =+E94+C95-D95 -> 1786.5204
A96: 46150 | B96: 赎回 | E96: =+E95+C96-D96 -> 1786.5204
E97: =+E96+C97-D97 -> 1786.5204
A98: 46156 | B98: 申购（含东吴） | C98: 5140 | E98: =+E97+C98-D98 -> 6926.5204 | F98: 催估值
E99: =+E98+C99-D99 -> 6926.5204
A100: 46156 | B100: 申购鹏雅120 | D100: 4800 | E100: =+E99+C100-D100 -> 2126.5204 | F100: 已发
...

Sheet 外贸信托_元康盛景1号
G1: 每周五开放
A2: 日期 | B2: 现金流类型 | C2: 现金流入 | D2: 现金流出 | E2: 期末余额
E3: 289
A4: 46028 | B4: 底层回款 | C4: 6.8 | E4: =E3+C4-D4 -> 295.8
A5: 46029 | B5: 荟煜035D | C5: 5324 | E5: =E4+C5-D5 -> 5619.8 | F5: 53245589
A6: 46029 | B6: 25君惠融ABN001优先B | D6: =1000*(100.48+0.120247)/100 -> 1006.0025 | E6: =E5+C6-D6 -> 4613.7975 | F6: 已发要素
E7: =E6+C7-D7 -> 4613.7975
A8: 46030 | B8: 25熠顺ABN001优先A3 | D8: 1006 | E8: =E7+C8-D8 -> 3607.7975 | F8: 1、25熠顺ABN001优先A3[082580640.IB] ，1000w，100净价，应计利息0.26301，1月8日，云南信托云乾10号 云南信托 陈文利3004414705 to 天风证券 唐德婷qt 2885078648 2、25熠顺ABN001优先A3[082580640.IB] ，1000w，100净价，应计利息0.26301，1月8日，天风证券 唐德婷qt 2885078648 to 外贸信托-元康盛景1号 赵婷婷
A9: 46030 | B9: 25和赢蔚能ABN001BC优先A2(科创) | D9: =2500*(1+0.0030137) -> 2507.5342 | E9: =E8+C9-D9 -> 1100.2633 | F9: 3、25和赢蔚能ABN001BC优先A2(科创)[082580537.IB]，2500w，100净价，应计利息0.30137，1月8日，云南信托云乾10号 云南信托 陈文利3004414705 to 天风证券 唐德婷qt 2885078648 4、25和赢蔚能ABN001BC优先A2(科创)[082580537.IB]，2500w，100.01净价，应计利息0.30137，1月8日，天风证券 唐德婷qt 2885078648 to 外贸信托-元康盛景1号 赵婷婷
E10: 1104
A11: 46036 | B11: 25光大环保ABN001次 | D11: 95.53 | E11: 1005 | F11: 25光大环保ABN001次(碳中和债)[082581155.IB] ,95w,100.5562,1月14日，t+0，国泰海通 xx to 外贸元康盛景1号 赵婷婷
A12: 46037 | B12: 回款 | C12: 3.4 | E12: =E11+C12-D12 -> 1008.4
A13: 46038 | B13: 回款 | C13: 3.5 | E13: =E12+C13-D13 -> 1011.9
A14: 46038 | B14: 元康盛景1号申购 | C14: 400 | E14: =E13+C14-D14 -> 1411.9
A15: 46038 | B15: 元康9申购 | C15: 150 | E15: =E14+C15-D15 -> 1561.9
E16: =E15+C16-D16 -> 1561.9
A17: 46041 | B17: 锦新26-1次级 | D17: 800 | E17: =E16+C17-D17 -> 761.9 | F17: 自持；26锦新小微ABN001次，082680037，800w，5.7%，1-19日缴款，1-20起息，外贸信托-元康盛景1号一级缴款。
E18: =E17+C18-D18 -> 761.9
A19: 46041 | B19: 回购归还 | D19: 360 | E19: =E18+C19-D19 -> 401.9 | F19: 金城
A20: 46041 | B20: 回款 | C20: 155 | E20: =E19+C20-D20 -> 556.9 | G20: 待定蔚能持有型不动产
A21: 46042 | B21: 元康盛景17号赎回 | D21: 350 | E21: =E20+C21-D21 -> 206.9 | F21: 1-16发起
A22: 46042 | B22: 底层回款 | C22: 24.7 | E22: =E21+C22-D22 -> 231.6
A23: 46044 | B23: 底层回款 | C23: 122 | E23: =E22+C23-D23 -> 353.6
A24: 46044 | B24: =B6 -> 25君惠融ABN001优先B | C24: =D6 -> 1006.0025 | E24: =E23+C24-D24 -> 1359.6025 | F24: 1月22日，082580061.IB，25君惠融ABN001优先B，1000W，100.48净价，应计利息0.28422；外贸信托：赵婷婷qt2850551246 to 招商证券：3007229341 赵漂琳
A25: 46044 | B25: 温兴 | D25: =1000*1.003 -> 1003 | E25: =E24+C25-D25 -> 356.60247 | F25: 25温兴1次级[2589143.IB] ，1月22日，1000w，100.3，t+0，国泰海通 冉雅婷 to 外贸信托元康盛景1号 赵婷婷
E26: =E25+C26-D26 -> 356.60247
A27: 46045 | B27: 元康盛景1号申购 | C27: 900 | E27: =E26+C27-D27 -> 1256.6025
E28: 1263
A29: 46048 | B29: 美歆8期 | D29: 1000 | E29: =E28+C29-D29 -> 263 | F29: 美歆8C（267647），1000w，4.8%，1月26日缴款，1月27日起息，外贸信托元康盛景1号缴款
A30: 46048 | B30: 回款 | C30: 113 | E30: =E29+C30-D30 -> 376
E31: 380
E32: 386
A33: 46062 | B33: 尚亦017D回款 | C33: 1551 | E33: 1936
A34: 46063 | B34: 阳光金科赎回兑付 | D34: 110.5 | E34: =E33+C34-D34 -> 1825.5
A35: 46063 | B35: 24京能3号ABN001次 | D35: 1101 | E35: =E34+C35-D35 -> 724.5 | F35: 24京能3号ABN001次 (082482325.IB)，1100w，100.12元/百元面值，2月10日，24京能3号ABN001次 (082482325.IB)，100w，100元/百元面值，12月30日，五矿信托和玉系列-元康盛景系列【2】号集合资金信托计划 to 国泰海通 冉雅婷
A36: 46063 | B36: 25东裕7叔裕ABN001次 | D36: =410*1.033333 -> 423.66653 | E36: =E35+C36-D36 -> 300.83347 | F36: 1、25东裕7叔裕ABN001次,082501056.IB,410w,103.3333, 2-10，t+0，国泰海通 夏雪 QT号：3007305611to 外贸信托元康盛景1号 赵婷婷
A37: 46064 | B37: 信保基金 | C37: 18 | E37: =E36+C37-D37 -> 318.83347
A38: 46065 | B38: 5美意3次 | D38: =120*1.07274 -> 128.7288 | E38: =E37+C38-D38 -> 190.10467 | F38: 5美意3次[263710.SH] ,120w，全价107.274，2026-2-12，国泰海通 樊文娟 to 外贸信托元康盛景1号 吕韩晶 2853866770
A39: 46067 | B39: 回款 | C39: 3.18 | E39: =E38+C39-D39 -> 193.28467
A40: 46077 | B40: 回款 | C40: 112 | E40: =E39+C40-D40 -> 305.28467
A41: 46078 | B41: 回款 | C41: 26 | E41: =E40+C41-D41 -> 331.28467
A42: 46079 | B42: 回款 | C42: 358 | E42: =E41+C42-D42 -> 689.28467
A43: 46080 | B43: 回款 | C43: 20 | E43: =E42+C43-D43 -> 709.28467
E44: =E43+C44-D44 -> 709.28467 | J44: 25东裕7叔裕ABN001次 | K44: =XIRR(K45:K46,J45:J46) -> 0.047860697
A45: 46080 | B45: 元康盛景30号 | C45: 400 | E45: =E44+C45-D45 -> 1109.2847 | J45: 45807 | K45: -100
A46: 46084 | B46: 元康盛景9号赎回 | D46: 750 | E46: =E45+C46-D46 -> 359.28467 | F46: 2/27赎回 | J46: 46063 | K46: 103.3333 | L46: =-K45*(1+4.9%*(J46-J45)/365) -> 103.43671
A47: 46084 | B47: 阳光金科赎回兑付 | D47: 26 | E47: =E46+C47-D47 -> 333.28467
A48: 46084 | B48: 元康17号赎回 | D48: 200 | E48: =E47+C48-D48 -> 133.28467 | F48: 2/27赎回 | J48: 24京能3号ABN001次 | K48: =XIRR(K49:K54,J49:J54) -> 0.074647418
A49: 46087 | B49: 5美意3次 | C49: =120*1.07625 -> 129.15 | E49: =E48+C49-D49 -> 262.43467 | F49: 3/6, 5美意3次[263710.SH] ，120w，107.625，外贸元康盛景1号赵婷婷 to 粤开证券 许逸潇2881647849 | J49: 45653 | K49: -100
E50: =E49+C50-D50 -> 262.43467 | J50: 45737 | K50: 1.9562 | L50: =-K50/$K$49*365/(J50-J49) -> 0.085001548
A51: 46090 | B51: 回款 | C51: 7 | E51: =E50+C51-D51 -> 269.43467 | J51: 45821 | K51: 1.9562 | L51: =-K51/$K$49*365/(J51-J50) -> 0.085001548
E52: =E51+C52-D52 -> 269.43467 | J52: 45896 | K52: 1.7466 | L52: =-K52/$K$49*365/(J52-J51) -> 0.0850012
E53: =E52+C53-D53 -> 269.43467 | J53: 45996 | K53: 2.3288 | L53: =-K53/$K$49*365/(J53-J52) -> 0.0850012
E54: =E53+C54-D54 -> 269.43467 | J54: 46063 | K54: 100.12 | L54: =-K49*(1+8.5%*(J54-J49)/365)-SUM(K50:K53) -> 101.56015
E55: =E54+C55-D55 -> 269.43467
E56: =E55+C56-D56 -> 269.43467
A57: 46091 | B57: 阳光金科赎回兑付 | D57: =511098/10000 -> 51.1098 | E57: =E56+C57-D57 -> 218.32487
A58: 46094 | B58: 慧聚领航1号配置 | C58: =慧聚领航1号!D9 -> 225 | E58: =E57+C58-D58 -> 443.32487
A59: 46097 | B59: 兑付回款 | C59: 5.5 | E59: =E58+C59-D59 -> 448.82487
A60: 46098 | B60: 25和赢蔚能ABN001BC优先A2(科创) | C60: =4000*(1.0029+0.0027397) -> 4022.5588 | E60: =E59+C60-D60 -> 4471.3837 | F60: 3/17, 25和赢蔚能ABN001BC优先A2(科创)[082580537.IB] ，4000w，净价100.29，应计利息 0.27397，外贸信托元康盛景1号 赵婷婷 to 天风证券 唐德婷2885078648
A61: 46098 | B61: 元康9赎回 | D61: 1600 | E61: =E60+C61-D61 -> 2871.3837 | F61: 3/17, 25和赢蔚能ABN001BC优先A2(科创)[082580537.IB] ，2500w，净价100.30，应计利息 0.27397， 天风证券 唐德婷2885078648 to 粤财信托 杭雅1号 吴海滨 2880690705+华宝投顾 马路遥3007680164
A62: 46098 | B62: 元康17赎回 | D62: 2701 | E62: =E61+C62-D62 -> 170.38367 | F62: 3/17, 25和赢蔚能ABN001BC优先A2(科创)[082580537.IB] ，1500w，净价100.30，应计利息 0.27397，天风证券 唐德婷2885078648 to 云南信托 云乾10号 陈文利3004414705
A63: 46098 | B63: 阳光金科赎回兑付 | D63: 26.79 | E63: =E62+C63-D63 -> 143.59367
E64: =E63+C64-D64 -> 143.59367
A65: 46100 | B65: 兑付回款 | C65: 6 | E65: =E64+C65-D65 -> 149.59367
A66: 46101 | B66: 中建投TOF申购 | C66: 400 | E66: =E65+C66-D66 -> 549.59367
A67: 46104 | B67: 兑付回款 | C67: 151 | E67: =E66+C67-D67 -> 700.59367
A68: 46105 | B68: 阳光金科赎回兑付 | D68: 34 | E68: =E67+C68-D68 -> 666.59367
E69: =E68+C69-D69 -> 666.59367
E70: =E69+C70-D70 -> 666.59367
A71: 46107 | B71: 回款 | C71: 110.6 | E71: =E70+C71-D71 -> 777.19367
A72: 46107 | B72: 温州回款 | C72: 756.5 | E72: =E71+C72-D72 -> 1533.6937
A73: 46108 | B73: 回款 | C73: 69 | E73: =E72+C73-D73 -> 1602.6937
A74: 46112 | B74: 元康盛景1号赎回 | D74: 720 | E74: =E73+C74-D74 -> 882.69367
A75: 46112 | B75: 元康盛景9号赎回 | D75: 650 | E75: =E74+C75-D75 -> 232.69367
E76: 230
A77: 46115 | B77: 爱建申购 | C77: 3000 | E77: 3235
A78: 46120 | B78: 铁建061C | D78: =元康盛景28号!N151 -> 733.1939 | E78: =E77+C78-D78 -> 2501.8061 | F78: 铁建061C[260663.SH]，655w，111.938，4月8日，【】 to 外贸信托-元康盛景1号 赵婷婷 qt2850551246
A79: 46120 | B79: G铁建82C | D79: =元康盛景28号!N152 -> 1029.7252 | E79: =E78+C79-D79 -> 1472.0808 | F79: G铁建82C[266500.SH]，1025w，100.461，4月8日，【】 to 外贸信托-元康盛景1号 赵婷婷 qt2850551246
E80: =E79+C80-D80 -> 1472.0808
A81: 46120 | B81: 阳光金科赎回兑付 | D81: 146.8 | E81: =E80+C81-D81 -> 1325.2808
A82: 46120 | B82: 元康17赎回 | D82: 1299.4 | E82: =E81+C82-D82 -> 25.88085
A83: 46122 | B83: 元康20申购 | C83: 1000 | E83: =E82+C83-D83 -> 1025.8808 | G83: 25鼎柚3次级 | H83: =XIRR(H84:H86,G84:G86) -> 0.044961324
A84: 46122 | B84: 慧聚领航1号配置 | C84: 2250 | E84: =E83+C84-D84 -> 3275.8808 | G84: 46009 | H84: -101.1998
A85: 46122 | B85: 25鼎柚3次级 | D85: =1500*H86/100 -> 1527.405 | E85: =E84+C85-D85 -> 1748.4758 | F85: 25鼎柚3次级[2589212.IB]，2400w，101.827，4月10日，国泰海通 冉雅婷 2881971956 to 外贸信托-元康盛景1号 赵婷婷 qt2850551246 | G85: 46079 | H85: 0.7562
B86: 应付税费 | D86: 2.5 | E86: =E85+C86-D86 -> 1745.9758 | G86: 46122 | H86: 101.827
A87: 46126 | B87: 新增回购 | C87: 900 | E87: =E86+C87-D87 -> 2645.9758 | F87: 质押G铁建82C
A88: 46126 | B88: 通合新能源 | D88: 1800 | E88: =E87+C88-D88 -> 845.97585
E89: =E88+C89-D89 -> 845.97585
A90: 46126 | B90: 支付银行间费用 | D90: 1.05 | E90: =E89+C90-D90 -> 844.92585
A91: 46126 | B91: 阳光金科赎回兑付 | D91: =135*1.2245 -> 165.3075 | E91: =E90+C91-D91 -> 679.61835 | H91: 25464.76
A92: 46127 | B92: 小鹏4次 | D92: =500*101.2% -> 506 | E92: =E91+C92-D92 -> 173.61835 | F92: 2、4/15 小鹏4次 146862.SZ 50,000.00 101.2000 粤财信托·鹏雅8号（交易商代码：000170 交易员代码：004Q0001 交易主体代码：3600000004）to 【外贸信托-元康盛景1号 （交易商代码：【000680】；交易主体代码：【3600003118】；交易员代码：【00IW0011 机构经纪1】 ）】
A93: 46128 | B93: 铁建061C | C93: 733 | E93: =E92+C93-D93 -> 906.61835 | F93: 铁建061C[260663.SH]，655w，112.01，4月16日，【外贸信托-元康盛景1号 赵婷婷 qt2850551246】 to 中信证券 赵恒昆3004076439 | G93: 铁建061C[260663.SH]，655w，112.015，4月16日，中信证券 赵恒昆3004076439 to 粤开证券 许逸潇2881647849
A94: 46127 | B94: 蔚能电池兑付 | C94: 3.4 | E94: =E93+C94-D94 -> 910.01835
A95: 46128 | B95: 致远11号兑付 | C95: 2.99 | E95: =E94+C95-D95 -> 913.00835
A96: 46129 | B96: 25熠顺ABN001优先A3兑付 | C96: 3.29 | E96: =E95+C96-D96 -> 916.29835
A97: 46133 | B97: 元康20号 | C97: 730 | E97: =E96+C97-D97 -> 1646.2983 | F97: 已发
A98: 46133 | B98: 阳光金科赎回兑付 | D98: =179*1.2263 -> 219.5077 | E98: =E97+C98-D98 -> 1426.7906
A99: 46133 | B99: 和赢蔚能ABN001、和赢蔚能ABN002兑付 | C99: =5.92+3.7 -> 9.62 | E99: =E98+C99-D99 -> 1436.4106
A100: 46134 | B100: 玮盈兑付 | C100: 169 | E100: =E99+C100-D100 -> 1605.4106
...

Sheet 西南证券-东方
D3: 46097 | E3: 4月底 | F3: 合计 | I3: 收益率预期
C4: 申购 | D4: 1000 | E4: 6000 | F4: =SUM(D4:E4) -> 7000 | I4: =SUMPRODUCT(I5:I9,F5:F9)/F4 -> 0.043214286
C5: 元康26 | D5: 500 | E5: 4000 | F5: =SUM(D5:E5) -> 4500 | I5: 0.035
C6: 元康28 | D6: 500 | F6: =SUM(D6:E6) -> 500 | I6: 0.05
C7: 外贸元康1 | F7: =SUM(D7:E7) -> 0 | I7: 0.055
C8: 元康31 | E8: 2000 | F8: =SUM(D8:E8) -> 2000 | I8: 0.06
C9: 元康32 | F9: =SUM(D9:E9) -> 0

Sheet 元康盛景30号
A2: 日期 | B2: 现金流类型 | C2: 现金流入 | D2: 现金流出 | E2: 期末余额
A3: 46049 | B3: 东吴代销成立 | C3: 1920 | E3: 1920
A4: 46050 | B4: 购买货基 | D4: 1920 | E4: =+E3+C4-D4 -> 0
E5: =+E4+C5-D5 -> 0 | K5: 申购开放 | L5: 1、4、7、10月10号
E6: =+E5+C6-D6 -> 0 | K6: 赎回开放 | L6: 1、4、7、10月10号
E7: =+E6+C7-D7 -> 0 | K7: 赎回预约 | L7: T-30日至T-20日（工作日）
A8: 46079 | B8: 赎回货基 | C8: 1920 | E8: =+E7+C8-D8 -> 1920 | K8: 申购费A类 | L8: 300w优先0.25%
A9: 46080 | B9: 外贸元康1 | D9: 400 | E9: =+E8+C9-D9 -> 1520 | F9: 今天先沟通提供空白合同 | H9: =D9/1920 -> 0.20833333 | K9: 赎回费 | L9: 180d以内1%
A10: 46080 | B10: 元康28 | D10: 400 | E10: =+E9+C10-D10 -> 1120 | H10: =D10/1920 -> 0.20833333 | K10: 锁定期 | L10: 180d
A11: 46080 | B11: 朗瑞1-5 | D11: 400 | E11: =+E10+C11-D11 -> 720 | H11: =D11/1920 -> 0.20833333 | K11: 管理费 | L11: 0.011 | M11: A类
A12: 46080 | B12: 鹏雅119 | D12: 380 | E12: 342 | H12: =D12/1920 -> 0.19791667 | L12: 0.006 | M12: B类
A13: 46090 | B13: 朗瑞1-7 | D13: 340 | E13: =+E12+C13-D13 -> 2 | H13: =D13/1920 -> 0.17708333 | K13: carry | L13: 3.5以上35% | M13: A类
E14: =+E13+C14-D14 -> 2 | L14: 3.5以上28% | M14: B类 | N14: 本基金管理人及其从业人员、本基金管理人关联方及其员工、专业机构投资者为B类份额的委托人
E15: =+E14+C15-D15 -> 2 | F15: 待定
E16: =+E15+C16-D16 -> 2
E17: =+E16+C17-D17 -> 2

Sheet 慧聚领航1号
A2: 日期 | B2: 现金流类型 | C2: 现金流入 | D2: 现金流出 | E2: 期末余额
A3: 46087 | E3: 1500
E4: =+E3+C4-D4 -> 1500 | I4: 申购开放 | J4: 1、4、7、10月初5个工作日
A5: 46092 | B5: 元康28号 | D5: =$E$4*F5 -> 300 | E5: =+E4+C5-D5 -> 1200 | F5: 0.2 | I5: 赎回开放 | J5: 1、4、7、10月初第5个工作日
A6: 46091 | B6: 朗瑞1-5 | D6: =$E$4*F6 -> 300 | E6: =+E5+C6-D6 -> 900 | F6: 0.2 | I6: 赎回预约 | J6: T-90日至T-20日（工作日）
A7: 46091 | B7: 全景1号 | D7: =$E$4*F7 -> 375 | E7: =+E6+C7-D7 -> 525 | F7: 0.25 | I7: 赎回费 | J7: 3个月内0.5%
E8: =+E7+C8-D8 -> 525 | F8: 0.2 | G8: 311定 | J8: 3-6个月0.2%
A9: 46094 | B9: 外贸元康1 | D9: =$E$4*F9 -> 225 | E9: =+E8+C9-D9 -> 300 | F9: 0.15 | G9: 311定 | I9: 管理费 | J9: 0.01
A10: 46094 | B10: 鹏雅120 | D10: 300 | E10: =+E9+C10-D10 -> 0 | G10: 311定 | I10: carry | J10: 0以上10% | K10: A类
A11: 46114 | B11: 赎回全景1号 | C11: 107.36596 | E11: =+E10+C11-D11 -> 107.36596 | F11: 赎回100w份额 | J11: 0 | K11: B类 | L11: 管理人及其从业人员、管理人关联方及其员工为B类份额的委托人
E12: 108
A13: 46120 | B13: 东吴追加申购 | C13: 9600 | E13: =+E12+C13-D13 -> 9708 | M13: 1st | N13: 2nd | T13: 4月底
E14: =+E13+C14-D14 -> 9708 | G14: 待定 | M14: =SUM(M15:M28) -> 1500 | N14: 9720 | O14: =SUM(M14:N14) -> 11220 | Q14: 波动率 | R14: 收益率 | T14: 11500 | V14: 波动率 | W14: 收益率
A15: 46120 | B15: 朗瑞1-7 | D15: 850 | E15: =+E14+C15-D15 -> 8858 | G15: ok | I15: ABS策略 | J15: 0.5 | K15: 固收 | L15: 元康28 | M15: 300 | N15: 0 | O15: =M15+N15 -> 300 | P15: =O15/$O$14 -> 0.026737968 | Q15: 0.01 | R15: 0.06 | T15: =O15+S15 -> 300 | U15: =T15/$T$14 -> 0.026086957 | V15: 0.01 | W15: 0.06
A16: 46120 | B16: 鹏雅120 | D16: =N20 -> 2364 | E16: =+E15+C16-D16 -> 6494 | G16: ok | I16: 全天候策略 | J16: 0.15 | K16: 固收 | L16: 朗瑞1-5 | M16: 300 | O16: =M16+N16 -> 300 | P16: =O16/$O$14 -> 0.026737968 | Q16: 0.01 | R16: 0.06 | S16: =-200 -> -200 | T16: =O16+S16 -> 100 | U16: =T16/$T$14 -> 0.0086956522 | V16: 0.01 | W16: 0.06
A17: 46120 | B17: 全景1号 | D17: 1400 | E17: =+E16+C17-D17 -> 5094 | G17: ok | I17: 期权策略 | J17: 0 | K17: 固收 | L17: 朗瑞1-7 | N17: 850 | O17: =M17+N17 -> 850 | P17: =O17/$O$14 -> 0.075757576 | Q17: 0.01 | R17: 0.06 | T17: =O17+S17 -> 850 | U17: =T17/$T$14 -> 0.073913043 | V17: 0.01 | W17: 0.06
E18: =+E17+C18-D18 -> 5094 | G18: ok | I18: REITs策略 | J18: 0.1 | K18: 衍生品 | L18: 全景1号 | M18: 275 | N18: 1400 | O18: =M18+N18 -> 1675 | P18: =O18/$O$14 -> 0.14928699 | Q18: 0.22 | R18: 0.3 | T18: =O18+S18 -> 1675 | U18: =T18/$T$14 -> 0.14565217 | V18: 0.22 | W18: 0.3
A19: 46121 | B19: 可交债 | D19: 2200 | E19: =+E18+C19-D19 -> 2894 | I19: ABS-NPL策略 | J19: 0.2 | K19: 固收 | L19: 外贸元康1 | M19: 225 | N19: 2250 | O19: =M19+N19 -> 2475 | P19: =O19/$O$14 -> 0.22058824 | Q19: 0.01 | R19: 0.055 | T19: =O19+S19 -> 2475 | U19: =T19/$T$14 -> 0.21521739 | V19: 0.01 | W19: 0.055
A20: 46122 | B20: 外贸元康1 | D20: 2250 | E20: =+E19+C20-D20 -> 644 | I20: 大类资产指数期权 | J20: 0.05 | K20: 固收 | L20: 鹏雅120 | M20: 300 | N20: 2364 | O20: =M20+N20 -> 2664 | P20: =O20/$O$14 -> 0.23743316 | Q20: 0.01 | R20: 0.1 | T20: =O20+S20 -> 2664 | U20: =T20/$T$14 -> 0.23165217 | V20: 0.01 | W20: 0.1
A21: 46122 | B21: 衡景1号 | D21: 100 | E21: =+E20+C21-D21 -> 544 | K21: 衍生品 | L21: 大类期权 | P21: =O21/$O$14 -> 0 | Q21: =25*3.5% -> 0.875 | R21: 2 | S21: 0 | T21: =O21+S21 -> 0 | U21: =T21/$T$14 -> 0 | V21: =25*3.5% -> 0.875 | W21: 2
A22: 46122 | B22: 申购 | C22: 120 | E22: =+E21+C22-D22 -> 664 | F22: 后续调整仓位，500w到reits战配，1000w到持有型不动产31号 | K22: 固收 | L22: 可交债 | N22: 2200 | O22: =M22+N22 -> 2200 | P22: =O22/$O$14 -> 0.19607843 | Q22: 0 | R22: 0.6 | S22: =-2200+1000 -> -1200 | T22: 0 | U22: =T22/$T$14 -> 0
A23: 46122 | B23: 朗瑞1-8 | D23: 30 | E23: =+E22+C23-D23 -> 634 | K23: 固收 | L23: 通合新能源 | N23: 600 | O23: =M23+N23 -> 600 | P23: =O23/$O$14 -> 0.053475936 | Q23: 0.01 | R23: 0.073 | T23: =O23+S23 -> 600 | U23: =T23/$T$14 -> 0.052173913 | V23: 0.01 | W23: 0.073
A24: 46126 | B24: 通合新能源 | D24: 600 | E24: =+E23+C24-D24 -> 34 | K24: 固收 | L24: 朗瑞1-8 | N24: 30 | O24: =M24+N24 -> 30 | P24: =O24/$O$14 -> 0.0026737968 | Q24: 0.01 | R24: 0.1 | S24: 600 | T24: =O24+S24 -> 630 | U24: =T24/$T$14 -> 0.054782609 | V24: 0.01 | W24: 0.1
E25: =+E24+C25-D25 -> 34 | K25: 衍生品 | L25: 衡景1号 | N25: 100 | O25: =M25+N25 -> 100 | P25: =O25/$O$14 -> 0.008912656 | Q25: 0.05 | R25: 0.1 | T25: =O25+S25 -> 100 | U25: =T25/$T$14 -> 0.0086956522 | V25: 0.05 | W25: 0.1
A26: 46132 | B26: 可交债 | C26: 2824.88 | E26: =+E25+C26-D26 -> 2858.88 | L26: 公募reits | S26: 370 | T26: =O26+S26 -> 370 | U26: =T26/$T$14 -> 0.032173913 | V26: 0.05 | W26: 0.1
A27: 46133 | B27: 朗瑞1-8 | D27: 600 | E27: =+E26+C27-D27 -> 2258.88 | F27: 已发 | L27: 皓月1号 | S27: 1000 | T27: =O27+S27 -> 1000 | U27: =T27/$T$14 -> 0.086956522 | V27: 0.25 | W27: 0.3
A28: 46136 | B28: 朗瑞1-5赎回 | C28: 200 | E28: =+E27+C28-D28 -> 2458.88 | F28: 已发 | L28: 现金 | M28: 100 | N28: =E12+N14-SUM(N15:N25) -> 34 | O28: =N28 -> 34 | P28: =O28/$O$14 -> 0.003030303 | Q28: 0 | R28: 0 | T28: 1147 | U28: =T28/$T$14 -> 0.09973913 | V28: 0 | W28: 0
A29: 46136 | B29: 蜀道可交债 | D29: 1000 | E29: =+E28+C29-D29 -> 1458.88 | Q29: =SUMPRODUCT(Q15:Q28,P15:P28) -> 0.039722816 | R29: =SUMPRODUCT(R15:R28,P15:P28) -> 0.21112522 | V29: =SUMPRODUCT(V15:V28,U15:U28) -> 0.062451304 | W29: =SUMPRODUCT(W15:W28,U15:U28) -> 0.12468043
E30: =+E29+C30-D30 -> 1458.88 | O30: 固收 | P30: =SUMIFS($O$15:$O$25,$K$15:$K$25,O30)/SUM($O$15:$O$25) -> 0.84143291 | T30: 固收 | U30: =(U15+U16+U17+U19+U20+U23+U24+U22)/SUM($U$15:$U$27) -> 0.70782237
A31: 46149 | B31: 瑞景3号 | D31: 370 | E31: =+E30+C31-D31 -> 1088.88 | F31: 已发 | O31: 权益 | P31: =SUMIFS($O$15:$O$25,$K$15:$K$25,O31)/SUM($O$15:$O$25) -> 0 | T31: 权益 | U31: =(U26+U27)/SUM(U15:U27) -> 0.12727611
A32: 46150 | B32: 皓月 | D32: 1000 | E32: =+E31+C32-D32 -> 88.88 | F32: 已发 | O32: 衍生品 | P32: =SUMIFS($O$15:$O$25,$K$15:$K$25,O32)/SUM($O$15:$O$25) -> 0.15856709 | T32: 衍生品 | U32: =(U18+U21+U25)/SUM(U15:U27) -> 0.16490152
A33: 46150 | B33: 蜀道EB | C33: =10*105.8 -> 1058 | E33: =+E32+C33-D33 -> 1146.88
E34: =+E33+C34-D34 -> 1146.88
B35: 中金逆回购 | D35: 1000 | E35: =+E34+C35-D35 -> 146.88
E36: =+E35+C36-D36 -> 146.88
E37: =+E36+C37-D37 -> 146.88
E38: =+E37+C38-D38 -> 146.88
E39: =+E38+C39-D39 -> 146.88
E40: =+E39+C40-D40 -> 146.88
E41: =+E40+C41-D41 -> 146.88
E42: =+E41+C42-D42 -> 146.88
E43: =+E42+C43-D43 -> 146.88
E44: =+E43+C44-D44 -> 146.88

Sheet 苏信优先级Z2501
A2: 日期 | B2: 现金流类型 | C2: 现金流入 | D2: 现金流出 | E2: 期末余额
A3: 46023 | E3: 192
E4: =+E3+C4-D4 -> 192
E5: =+E4+C5-D5 -> 192
E6: =+E5+C6-D6 -> 192
E7: =+E6+C7-D7 -> 192 | H7: 1月份排券计划 | T7: 46036
A8: 46030 | B8: 回款 | C8: 7.56 | E8: =+E7+C8-D8 -> 199.56 | H8: 证券名称 | I8: 代码 | J8: 票息（预期） | K8: 数量 | L8: 净价 | M8: 全价 | N8: 规模 | O8: 交易日期 | P8: 后手收益率 | Q8: 上家 | R8: 过桥 | S8: 过桥费 | T8: 中债估值 | U8: 估值后手收益率 | V8: 最新评级 | W8: 上个付息日 | X8: 应计利息 | Y8: 起息日 | Z8: 本金开始摊还日 | AA8: 预计到期日 | AB8: 剩余面值 | AC8: 卖家交易员 | AD8: 买家交易员 | AE8: 交易要素
A9: 46034 | B9: 回款 | C9: 5.15 | E9: =+E8+C9-D9 -> 204.71 | H9: 狮桥62A2 | I9: 500193.SZ | J9: 0.032 | K9: 600 | L9: 100.003 | M9: =L9+X9 -> 100.40629 | N9: =+M9*K9/100 -> 602.43773 | O9: 46041 | P9: 0.032 | Q9: 渣打 | R9: 中信 | S9: 0.003 | T9: 100.079 | U9: 0.031967 | V9: AA+ | W9: 45996 | X9: =+J9*(O9-W9+1)/365*100 -> 0.40328767 | Y9: 45996 | AA9: 46890 | AB9: 100 | AC9: 渣打（） | AD9: 苏信Z2501 | AE9: 狮桥62A2[500193.SZ]，600w，净价100.003，1月19日，中信证券 3004076439 to 苏信财富组合添利Z2501集合资金信托计划 徐健 qq455768073 邮箱xuj@trustsz.com
E10: 215 | G10: A | H10: 乐信12C | I10: 500210.SZ | J10: 0.03 | K10: 1500 | L10: 100 | M10: =L10+X10 -> 100.29589 | N10: =+M10*K10/100 -> 1504.4384 | O10: 46038 | P10: 0.03 | Q10: 富民 | R10: NA | T10: 99.991 | U10: 0.0304 | V10: A | W10: 46003 | X10: =+J10*(O10-W10+1)/365*100 -> 0.29589041 | Y10: 46003 | AA10: 46549 | AB10: 100 | AC10: 富民（） | AD10: 苏信Z2501 | AE10: 乐信12C[500210.SZ]，1500w，净价100，1月16日，富民王雪乔 to 苏信财富组合添利Z2501集合资金信托计划 徐健 qq455768073 邮箱xuj@trustsz.com
A11: 46036 | B11: 熠然02A3 | D11: 100 | E11: =+E10+C11-D11 -> 115 | F11: 熠安02A3[144651.SZ]，100w，净价100元，1月14日，国泰海通 樊文娟 to 苏信财富组合添利Z2501集合资金信托计划 徐健 | G11: A-待定 | H11: 分期乐1号3期 | J11: 0.033 | K11: 1500 | L11: 100 | N11: =+M11*K11/100 -> 0 | O11: 46038 | Q11: 一级 | R11: NA | AE11: =H11&"["&I11&"]，"&K11&"w，"&L11&"，"&TEXT(O11,"m月d日")&"，"&AC11&" to "&AD11 -> 分期乐1号3期[]，1500w，100，1月16日， to
E12: =+E11+C12-D12 -> 115 | G12: A | H12: 25乐信1C | I12: 264610.SH | J12: 0.033 | K12: 600 | L12: 100.01 | M12: =L12+X12+S12 -> 100.06521 | N12: =+M12*K12/100 -> 600.39123 | O12: 46038 | P12: 0.033 | Q12: 26号 | R12: 扬讯 | S12: 0.01 | T12: 100.1481 | U12: 0.029642 | V12: A | W12: 46034 | X12: =+J12*(O12-W12+1)/365*100 -> 0.045205479 | Y12: 45757 | AA12: 46213 | AB12: 100 | AC12: 芜湖扬讯 Z11825 | AD12: 苏信Z2501 | AE12: =H12&"["&I12&"]，"&K12&"w，"&L12&"，"&TEXT(O12,"m月d日")&"，"&AC12&" to "&AD12 -> 25乐信1C[264610.SH]，600w，100.01，1月16日，芜湖扬讯 Z11825 to 苏信Z2501
A13: 46037 | B13: 申购 | C13: 8245 | E13: =+E12+C13-D13 -> 8360 | H13: 炽诚3A3 | I13: 266980.SH | J13: 0.036 | K13: 1000 | L13: 99.51 | M13: =L13+X13+S13 -> 100.11178 | N13: =+M13*K13/100 -> 1001.1178 | O13: 46038 | P13: 0.039 | Q13: 26号 | R13: 扬讯 | S13: 0.01 | T13: 98.8973 | U13: 0.042447 | V13: AAA | W13: 45979 | X13: =+J13*(O13-W13+1)/365*100 -> 0.59178082 | Y13: 45979 | AA13: 47072 | AB13: 100 | AC13: 芜湖扬讯 Z11825 | AD13: 苏信Z2501 | AE13: =H13&"["&I13&"]，"&K13&"w，"&L13&"，"&TEXT(O13,"m月d日")&"，"&AC13&" to "&AD13 -> 炽诚3A3[266980.SH]，1000w，99.51，1月16日，芜湖扬讯 Z11825 to 苏信Z2501
A14: 46037 | B14: 兑付 | C14: 1006 | E14: =+E13+C14-D14 -> 9366 | F14: 注意买入的熠然02A3也会有兑付 | H14: DY03优3 | I14: 266192.SH | J14: 0.041 | K14: 1000 | L14: 100.01 | M14: =L14+X14+S14 -> 100.04247 | N14: =+M14*K14/100 -> 1000.4247 | O14: 46038 | P14: 0.041 | Q14: 26号 | R14: 扬讯 | S14: 0.01 | T14: 99.7106 | U14: 0.04162 | V14: AAA | W14: 46037 | X14: =+J14*(O14-W14+1)/365*100 -> 0.022465753 | Y14: 45891 | AA14: 46980 | AB14: 100 | AC14: 芜湖扬讯 Z11825 | AD14: 苏信Z2501 | AE14: =H14&"["&I14&"]，"&K14&"w，"&L14&"，"&TEXT(O14,"m月d日")&"，"&AC14&" to "&AD14 -> DY03优3[266192.SH]，1000w，100.01，1月16日，芜湖扬讯 Z11825 to 苏信Z2501
A15: 46038 | D15: 4106 | E15: =+E14+C15-D15 -> 5260 | F15: 已发
A16: 46041 | D16: 602 | E16: =+E15+C16-D16 -> 4658 | M16: 总规模 | N16: =SUM(N9:N15) -> 4708.8098 | O16: 加权收益 | P16: =SUMPRODUCT(P9:P14,N9:N14)/N16 -> 0.034888875
E17: 4662
A18: 46045 | B18: 回款 | C18: 354 | E18: =+E17+C18-D18 -> 5016
A19: 46048 | B19: 回款 | C19: 654 | E19: =+E18+C19-D19 -> 5670
A20: 46049 | B20: 回款 | C20: 517 | E20: =+E19+C20-D20 -> 6187
A21: 46050 | B21: 回款 | C21: 176 | E21: =+E20+C21-D21 -> 6363 | AC21: 元康盛景26号 | AD21: 芜湖扬讯 Z11825 | AE21: =H12&"["&I12&"]，"&K12&"w，"&L12-0.01&"，"&TEXT(O12,"m月d日")&"，"&AC21&" to "&AD21 -> 25乐信1C[264610.SH]，600w，100，1月16日，元康盛景26号 to 芜湖扬讯 Z11825
E22: =+E21+C22-D22 -> 6363 | AC22: 元康盛景26号 | AD22: 芜湖扬讯 Z11825 | AE22: =H13&"["&I13&"]，"&K13&"w，"&L13-0.01&"，"&TEXT(O13,"m月d日")&"，"&AC22&" to "&AD22 -> 炽诚3A3[266980.SH]，1000w，99.5，1月16日，元康盛景26号 to 芜湖扬讯 Z11825
A23: 46051 | E23: 6367 | AC23: 元康盛景26号 | AD23: 芜湖扬讯 Z11825 | AE23: =H14&"["&I14&"]，"&K14&"w，"&L14-0.01&"，"&TEXT(O14,"m月d日")&"，"&AC23&" to "&AD23 -> DY03优3[266192.SH]，1000w，100，1月16日，元康盛景26号 to 芜湖扬讯 Z11825
A24: 46066 | B24: 回款 | C24: 213 | E24: =+E23+C24-D24 -> 6580
A25: 46077 | B25: 回款 | C25: 2081 | E25: =+E24+C25-D25 -> 8661
E26: =+E25+C26-D26 -> 8661
E27: =+E26+C27-D27 -> 8661
A28: 46077 | B28: 申购 | C28: 2614 | E28: =+E27+C28-D28 -> 11275
A29: 46079 | B29: 兑付赎回 | D29: 4533 | E29: =+E28+C29-D29 -> 6742 | H29: 3月份募集目标 | J29: 优先级户
A30: 46079 | B30: 海云3优A | D30: 1900 | E30: =+E29+C30-D30 -> 4842 | F30: 6500 | I30: 1 | J30: 蔚能夹层A3或优先B | K30: 3000
A31: 46080 | B31: 回款 | C31: 291 | E31: =+E30+C31-D31 -> 5133 | I31: 2 | J31: 远东普惠2026-1ABS夹层 | K31: 4000
A32: 46083 | B32: 回款 | C32: 909 | E32: =+E31+C32-D32 -> 6042 | I32: 3 | J32: 星灿5A3 | K32: 3200 | L32: 26号+28号
E33: 5968 | I33: 4 | J33: 熠然5A3 | K33: 2500 | L33: 26号
A34: 46085 | B34: 欧力士缴款 | D34: 500 | E34: =+E33+C34-D34 -> 5468 | F34: 3/4，26OCC1B，267846.SH,苏信Z2501一级缴款 ，500w，发行利率【3.0】%
A35: 46086 | B35: 回款 | C35: 220 | E35: =+E34+C35-D35 -> 5688
A36: 46090 | B36: 鑫驰4B | D36: 2000 | E36: =+E35+C36-D36 -> 3688 | F36: 3/9,鑫驰4B，500492, 2000w一级缴款，利率3.15%， 苏信财富Z2501，3-10起息 | H36: 3月交易安排 | T36: 46094
E37: =+E36+C37-D37 -> 3688 | H37: 证券名称 | I37: 代码 | J37: 票息（预期） | K37: 数量 | L37: 净价 | M37: 全价 | N37: 规模 | O37: 交易日期 | P37: 后手收益率 | Q37: 上家 | R37: 过桥 | S37: 过桥费 | T37: 中债估值 | U37: 估值后手收益率 | V37: 最新评级 | W37: 上个付息日 | X37: 应计利息 | Y37: 起息日 | Z37: 本金开始摊还日 | AA37: 预计到期日 | AB37: 剩余面值 | AC37: 卖家交易员 | AD37: 买家交易员 | AE37: 交易要素
A38: 46097 | B38: 回款 | C38: 1094 | E38: =+E37+C38-D38 -> 4782 | H38: 星灿5A3 | I38: 144780.SZ | J38: 0.043 | K38: 2518 | L38: =79.36-8.68 -> 70.68 | M38: =L38+X38 -> 70.703562 | N38: =+M38*K38/100 -> 1780.3157 | O38: 46098 | Q38: 26号 | R38: NA | T38: 79.3606 | U38: 0.0375 | V38: AAA | W38: 46097 | X38: =+J38*(O38-W38+1)/365*100 -> 0.023561644 | Y38: 45596 | AA38: 46675 | AB38: 70.55 | AC38: 元康26号 | AD38: 苏信Z2501 | AE38: =H38&"["&I38&"]，"&K38&"w，"&L38&"，"&TEXT(O38,"m月d日")&"，"&AC38&" to "&AD38 -> 星灿5A3[144780.SZ]，2518w，70.68，3月17日，元康26号 to 苏信Z2501
A39: 46097 | B39: 申购 | C39: 10006 | E39: =+E38+C39-D39 -> 14788 | H39: 熠然5A3 | I39: 263739.SH | J39: 0.043 | K39: 3000 | L39: =86.15-10.28 -> 75.87 | M39: =L39+X39 -> 75.893562 | N39: =+M39*K39/100 -> 2276.8068 | O39: 46098 | Q39: 26号 | R39: NA | T39: 86.1497 | U39: 0.037565 | V39: AAA | W39: 46097 | X39: =+J39*(O39-W39+1)/365*100 -> 0.023561644 | Y39: 45611 | AA39: 46703 | AB39: 75.72 | AC39: 元康26号 | AD39: 苏信Z2501 | AE39: =H39&"["&I39&"]，"&K39&"w，"&L39&"，"&TEXT(O39,"m月d日")&"，"&AC39&" to "&AD39 -> 熠然5A3[263739.SH]，3000w，75.87，3月17日，元康26号 to 苏信Z2501
A40: 46098 | B40: 星灿5A3 | D40: =N38 -> 1780.3157 | E40: =+E39+C40-D40 -> 13007.684 | H40: 熠然5A3 | I40: 263739.SH | J40: 0.043 | K40: 1385 | L40: =86.15-10.28 -> 75.87 | M40: =L40+X40 -> 75.905342 | N40: =+M40*K40/100 -> 1051.289 | O40: 46099 | Q40: 28号 | R40: NA | T40: 86.1497 | U40: 0.037565 | V40: AAA | W40: 46097 | X40: =+J40*(O40-W40+1)/365*100 -> 0.035342466 | Y40: 45611 | AA40: 46703 | AB40: 75.72 | AC40: 元康28号 | AD40: 苏信Z2501 | AE40: =H40&"["&I40&"]，"&K40&"w，"&L40&"，"&TEXT(O40,"m月d日")&"，"&AC40&" to "&AD40 -> 熠然5A3[263739.SH]，1385w，75.87，3月18日，元康28号 to 苏信Z2501
B41: 熠然5A3 | D41: =N39 -> 2276.8068 | E41: =+E40+C41-D41 -> 10730.877 | G41: 待定 | H41: 蔚能夹层A3或优先B | K41: 3000 | L41: 100 | M41: =L41+X41 -> 100 | N41: =+M41*K41/100 -> 3000 | Q41: 一级 | R41: NA | X41: =+J41*(O41-W41+1)/365*100 -> 0 | AB41: 100 | AD41: 苏信Z2501 | AE41: =H41&"["&I41&"]，"&K41&"w，"&L41&"，"&TEXT(O41,"m月d日")&"，"&AC41&" to "&AD41 -> 蔚能夹层A3或优先B[]，3000w，100，1月0日， to 苏信Z2501
A42: 46099 | B42: 熠然5A3 | D42: =N50+N51 -> 1051.289 | E42: =+E41+C42-D42 -> 9679.5885 | G42: 待定 | H42: 远东普惠2026-1ABS夹层 | K42: 4000 | L42: 100 | M42: =L42+X42 -> 100 | N42: =+M42*K42/100 -> 4000 | Q42: 一级 | R42: NA | X42: =+J42*(O42-W42+1)/365*100 -> 0 | AB42: 100 | AD42: 苏信Z2501 | AE42: =H42&"["&I42&"]，"&K42&"w，"&L42&"，"&TEXT(O42,"m月d日")&"，"&AC42&" to "&AD42 -> 远东普惠2026-1ABS夹层[]，4000w，100，1月0日， to 苏信Z2501
E43: =+E42+C43-D43 -> 9679.5885 | F43: 元康28 | T43: 46094
E44: =+E43+C44-D44 -> 9679.5885 | H44: 证券名称 | I44: 代码 | J44: 票息（预期） | K44: 数量 | L44: 净价 | M44: 全价 | N44: 规模 | O44: 交易日期 | P44: 后手收益率 | Q44: 上家 | R44: 过桥 | S44: 过桥费 | T44: 中债估值 | U44: 估值后手收益率 | V44: 最新评级 | W44: 上个付息日 | X44: 应计利息 | Y44: 起息日 | Z44: 本金开始摊还日 | AA44: 预计到期日 | AB44: 剩余面值 | AC44: 卖家交易员 | AD44: 买家交易员 | AE44: 交易要素
A45: 46101 | B45: 回款 | C45: 345 | E45: =+E44+C45-D45 -> 10024.588 | H45: 星灿5A3 | I45: 144780.SZ | J45: 0.043 | K45: 1400 | L45: =79.36-8.68 -> 70.68 | M45: =L45+X45 -> 70.703562 | N45: =+M45*K45/100 -> 989.84986 | O45: 46098 | Q45: 26号 | R45: 芜湖扬讯 | T45: 79.3606 | U45: 0.0375 | V45: AAA | W45: 46097 | X45: =+J45*(O45-W45+1)/365*100 -> 0.023561644 | Y45: 45596 | AA45: 46675 | AB45: 70.55 | AC45: 芜湖扬讯 | AD45: 苏信Z2501 | AE45: 星灿5A3[144780.SZ]，1400w，70.68，3月17日，芜湖扬讯 to 苏信Z2501
E46: =+E45+C46-D46 -> 10024.588 | H46: 星灿5A3 | I46: 144780.SZ | J46: 0.043 | K46: =+K38-K45 -> 1118 | L46: =79.36-8.68 -> 70.68 | M46: =L46+X46 -> 70.703562 | N46: =+M46*K46/100 -> 790.46582 | O46: 46098 | Q46: 26号 | R46: 芜湖扬讯 | T46: 79.3606 | U46: 0.0375 | V46: AAA | W46: 46097 | X46: =+J46*(O46-W46+1)/365*100 -> 0.023561644 | Y46: 45596 | AA46: 46675 | AB46: 70.55 | AC46: 芜湖扬讯 | AD46: 苏信Z2501 | AE46: 星灿5A3[144780.SZ]，1118w，70.68，3月17日，芜湖扬讯 to 苏信Z2501
A47: 46106 | B47: 回款 | C47: 94 | E47: =+E46+C47-D47 -> 10118.588 | H47: 熠然5A3 | I47: 263739.SH | J47: 0.043 | K47: 1300 | L47: =86.15-10.28 -> 75.87 | M47: =L47+X47 -> 75.893562 | N47: =+M47*K47/100 -> 986.6163 | O47: 46098 | Q47: 26号 | R47: 芜湖扬讯 | T47: 86.1497 | U47: 0.037565 | V47: AAA | W47: 46097 | X47: =+J47*(O47-W47+1)/365*100 -> 0.023561644 | Y47: 45611 | AA47: 46703 | AB47: 75.72 | AC47: 芜湖扬讯 | AD47: 苏信Z2501 | AE47: 熠然5A3[263739.SH]，1300w，75.87，3月17日，芜湖扬讯 to 苏信Z2501
E48: =+E47+C48-D48 -> 10118.588 | H48: 熠然5A3 | I48: 263739.SH | J48: 0.043 | K48: 1200 | L48: =86.15-10.28 -> 75.87 | M48: =L48+X48 -> 75.893562 | N48: =+M48*K48/100 -> 910.72274 | O48: 46098 | Q48: 26号 | R48: 芜湖扬讯 | T48: 86.1497 | U48: 0.037565 | V48: AAA | W48: 46097 | X48: =+J48*(O48-W48+1)/365*100 -> 0.023561644 | Y48: 45611 | AA48: 46703 | AB48: 75.72 | AC48: 芜湖扬讯 | AD48: 苏信Z2501 | AE48: 熠然5A3[263739.SH]，1200w，75.87，3月17日，芜湖扬讯 to 苏信Z2501
E49: =+E48+C49-D49 -> 10118.588 | H49: 熠然5A3 | I49: 263739.SH | J49: 0.043 | K49: =K39-K47-K48 -> 500 | L49: =86.15-10.28 -> 75.87 | M49: =L49+X49 -> 75.893562 | N49: =+M49*K49/100 -> 379.46781 | O49: 46098 | Q49: 26号 | R49: 芜湖扬讯 | T49: 86.1497 | U49: 0.037565 | V49: AAA | W49: 46097 | X49: =+J49*(O49-W49+1)/365*100 -> 0.023561644 | Y49: 45611 | AA49: 46703 | AB49: 75.72 | AC49: 芜湖扬讯 | AD49: 苏信Z2501 | AE49: 熠然5A3[263739.SH]，500w，75.87，3月17日，芜湖扬讯 to 苏信Z2501
A50: 46108 | B50: 回款 | C50: 514 | E50: =+E49+C50-D50 -> 10632.588 | H50: 熠然5A3 | I50: 263739.SH | J50: 0.043 | K50: 700 | L50: =86.15-10.28 -> 75.87 | M50: =L50+X50 -> 75.905342 | N50: =+M50*K50/100 -> 531.3374 | O50: 46099 | Q50: 28号 | R50: NA | T50: 75.8655 | U50: 0.037565 | V50: AAA | W50: 46097 | X50: =+J50*(O50-W50+1)/365*100 -> 0.035342466 | Y50: 45611 | AA50: 46703 | AB50: 75.72 | AC50: 芜湖扬讯 | AD50: 苏信Z2501 | AE50: 熠然5A3[263739.SH]，700w，75.87，3月18日，芜湖扬讯 to 苏信Z2501
E51: =+E50+C51-D51 -> 10632.588 | H51: 熠然5A3 | I51: 263739.SH | J51: 0.043 | K51: =+K40-K50 -> 685 | L51: =86.15-10.28 -> 75.87 | M51: =L51+X51 -> 75.905342 | N51: =+M51*K51/100 -> 519.9516 | O51: 46099 | Q51: 一级 | R51: NA | T51: 75.8655 | U51: 0.037565 | V51: AAA | W51: 46097 | X51: =+J51*(O51-W51+1)/365*100 -> 0.035342466 | Y51: 45611 | AA51: 46703 | AB51: 75.72 | AC51: 芜湖扬讯 | AD51: 苏信Z2501 | AE51: 熠然5A3[263739.SH]，685w，75.87，3月18日，芜湖扬讯 to 苏信Z2501
A52: 46108 | B52: 诚惠3B | D52: 1006 | E52: =+E51+C52-D52 -> 9626.5885 | F52: 诚惠3B[266186.SH]，1000w，100.555，3月27日，天风证券 唐德婷qt 2885078648 to 苏信Z2501 徐健 qt455768073 | Q52: 一级 | R52: NA | T52: 46106 | X52: =+J72*(O71-W52+1)/365*100 -> 0 | AB52: 100
A53: 46108 | B53: 小鹏5B | D53: 1500 | E53: 8170 | F53: 小鹏5B[500446.SZ]，1500w，100.217，3月27日，天风证券 唐德婷qt 2885078648 to 苏信Z2501 徐健 qt455768073 | H53: 证券名称 | I53: 代码 | J53: 票息（预期） | K53: 数量 | L53: 净价 | M53: 全价 | N53: 规模 | O53: 交易日期 | P53: 后手收益率 | Q53: 上家 | R53: 过桥 | S53: 过桥费 | T53: 中债估值 | U53: 估值后手收益率 | V53: 最新评级 | W53: 上个付息日 | X53: 应计利息 | Y53: 起息日 | Z53: 本金开始摊还日 | AA53: 预计到期日 | AB53: 剩余面值 | AC53: 卖家交易员 | AD53: 买家交易员 | AE53: 交易要素 | AF53: 上家 | AG53: 过券1 | AH53: 过券2
A54: 46111 | B54: 回款 | C54: 182 | E54: =+E53+C54-D54 -> 8352 | H54: 诚惠3B | I54: 266186.SH | J54: 0.033 | K54: 1000 | L54: =AH54 -> 100.555 | M54: =L54+X54 -> 100.57308 | N54: =+M54*K54/100 -> 1005.7308 | O54: 46108 | Q54: 26号 | R54: 芜湖扬讯 | T54: 100.5482 | U54: 0.0294 | V54: AAA | W54: 46107 | X54: =+J54*(O54-W54+1)/365*100 -> 0.018082192 | Y54: 45909 | AA54: 46686 | AB54: 100 | AC54: 天风证券 唐德婷qt 2885078648 | AD54: 苏信Z2501 徐健 qt455768073 | AE54: =H54&"["&I54&"]，"&K54&"w，"&L54&"，"&TEXT(O54,"m月d日")&"，"&AC54&" to "&AD54 -> 诚惠3B[266186.SH]，1000w，100.555，3月27日，天风证券 唐德婷qt 2885078648 to 苏信Z2501 徐健 qt455768073 | AF54: 100.54 | AG54: =+AF54+0.005 -> 100.545 | AH54: =+AG54+0.01 -> 100.555
E55: =+E54+C55-D55 -> 8352 | H55: 小鹏5B | I55: 500446.SZ | J55: 0.033 | K55: 1500 | L55: =AH55 -> 100.217 | M55: =L55+X55 -> 100.60577 | N55: =+M55*K55/100 -> 1509.0865 | O55: 46108 | Q55: 26号 | R55: 芜湖扬讯 | T55: 100.2092 | U55: 0.0326 | V55: AA+ | W55: 46066 | X55: =+J55*(O55-W55+1)/365*100 -> 0.38876712 | Y55: 46066 | AA55: 47154 | AB55: 100 | AC55: 天风证券 唐德婷qt 2885078648 | AD55: 苏信Z2501 徐健 qt455768073 | AE55: =H55&"["&I55&"]，"&K55&"w，"&L55&"，"&TEXT(O55,"m月d日")&"，"&AC55&" to "&AD55 -> 小鹏5B[500446.SZ]，1500w，100.217，3月27日，天风证券 唐德婷qt 2885078648 to 苏信Z2501 徐健 qt455768073 | AF55: 100.202 | AG55: =+AF55+0.005 -> 100.207 | AH55: =+AG55+0.01 -> 100.217
A56: 46112 | B56: 鑫驰4B | D56: 1002 | E56: =+E55+C56-D56 -> 7350
E57: =+E56+C57-D57 -> 7350
E58: =+E57+C58-D58 -> 7350 | F58: 如元康26号有需要，可以转让1-2000w过来
E59: =+E58+C59-D59 -> 7350
E60: 7369
A61: 46127 | B61: 回款 | C61: 1727 | E61: =+E60+C61-D61 -> 9096 | H61: 4-16交易 | T61: 46125
A62: 46128 | B62: 申购 | C62: 2691 | E62: =+E61+C62-D62 -> 11787 | H62: 证券名称 | I62: 代码 | J62: 票息（预期） | K62: 数量 | L62: 净价 | M62: 全价 | N62: 规模 | O62: 交易日期 | P62: 后手收益率 | Q62: 上家 | R62: 过桥 | S62: 过桥费 | T62: 中债估值 | U62: 估值后手收益率 | V62: 最新评级 | W62: 上个付息日 | X62: 应计利息 | Y62: 起息日 | Z62: 本金开始摊还日 | AA62: 预计到期日 | AB62: 剩余面值 | AC62: 卖家交易员 | AD62: 买家交易员 | AE62: 交易要素
A63: 46128 | E63: =+E62+C63-D63 -> 11787 | H63: 诚惠1B | I63: 263867.SH | J63: 0.044 | K63: 300 | L63: 101.42 | M63: =L63+X63 -> 101.68521 | N63: =+M63*K63/100 -> 305.05562 | O63: 46128 | P63: 0.028 | Q63: 26号 | R63: 芜湖扬讯 | T63: 101.42 | U63: 0.028 | V63: AA+ | W63: 46107 | X63: =AB63*J63*(O63-W63+1)/365 -> 0.26520548 | Y63: 45624 | AA63: 46503 | AB63: 100 | AC63: 【】 | AD63: 苏信Z2501 | AE63: =H63&"["&I63&"]，"&K63&"w，"&L63&"，"&TEXT(O63,"m月d日")&"，"&AC63&" to "&AD63 -> 诚惠1B[263867.SH]，300w，101.42，4月16日，【】 to 苏信Z2501
A64: 46128 | B64: 诚惠1B | D64: 305 | E64: =+E63+C64-D64 -> 11482 | F64: 诚惠1B[263867.SH]，300w，101.42，4月16日，粤开证券 许逸潇2881647849 to 苏信Z2501 徐健 qt455768073
E65: =+E64+C65-D65 -> 11482
E66: =+E65+C66-D66 -> 11482 | H66: 4-21交易 | T66: 46126
E67: =+E66+C67-D67 -> 11482 | H67: 证券名称 | I67: 代码 | J67: 票息（预期） | K67: 数量 | L67: 净价 | M67: 全价 | N67: 规模 | O67: 交易日期 | P67: 后手收益率 | Q67: 上家 | R67: 过桥 | S67: 过桥费 | T67: 中债估值 | U67: 估值后手收益率 | V67: 最新评级 | W67: 上个付息日 | X67: 应计利息 | Y67: 起息日 | Z67: 本金开始摊还日 | AA67: 预计到期日 | AB67: 剩余面值 | AC67: 卖家交易员 | AD67: 买家交易员 | AE67: 交易要素
A68: 46133 | B68: 晨惠2期优先B | D68: 700 | E68: =+E67+C68-D68 -> 10782 | F68: 已发 | G68: 待确定要素 | H68: 朗煜1A3 | I68: 264213.SH | J68: 0.043 | K68: 400 | L68: =+T68-7.84+0.005 -> 87.5846 | M68: =L68+X68 -> 87.656617 | N68: =+M68*K68/100 -> 350.62647 | O68: 46133 | P68: =+U68 -> 0.0376 | Q68: 26号 | R68: 芜湖扬讯 | T68: 95.4196 | U68: 0.0376 | V68: AAA | W68: 46127 | X68: =AB68*J68*(O68-W68+1)/365 -> 0.072017342 | Y68: 45678 | Z68: 46097 | AA68: 46736 | AB68: 87.33 | AC68: 【】 | AD68: 苏信Z2501 | AE68: =H68&"["&I68&"]，"&K68&"w，"&L68&"，"&TEXT(O68,"m月d日")&"，"&AC68&" to "&AD68 -> 朗煜1A3[264213.SH]，400w，87.5846，4月21日，【】 to 苏信Z2501
E69: =+E68+C69-D69 -> 10782
A70: 46134 | B70: 鑫驰5B | D70: 500 | E70: =+E69+C70-D70 -> 10282 | F70: 鑫驰5B，500701.SZ，500w，3.15%，4-22缴款，4-23起息，苏信添利2501
A71: 46134 | B71: 回款 | C71: 456 | E71: =+E70+C71-D71 -> 10738
A72: 46136 | B72: 盛煜013C | C72: 2076.52 | E72: 12823
E73: =+E72+C73-D73 -> 12823
A74: 46139 | B74: 熠安02A3 | C74: =2300*52.5188% -> 1207.9324 | E74: =+E73+C74-D74 -> 14030.932 | F74: 熠安02A3[144651.SZ]，2300w，52.5188，4月27日，苏信 徐健 xuj@trustsz.com to 中信证券 赵恒昆 zhaohengkun@citics.com
A75: 46140 | B75: 回款 | C75: 1683 | E75: =+E74+C75-D75 -> 15713.932
A76: 46139 | B76: 国金保理优A | D76: 1000 | E76: =+E75+C76-D76 -> 14713.932 | F76: 已发
E77: =+E76+C77-D77 -> 14713.932
A78: 46141 | B78: 启恒2期优先B | D78: 800 | E78: =+E77+C78-D78 -> 13913.932 | F78: 启恒2B，500690.SZ，苏信2501，800w，3.0%，4月29日缴款、4月30日设立
E79: =+E78+C79-D79 -> 13913.932
A80: 46141 | B80: 蔚能A3 | D80: 3500 | E80: =+E79+C80-D80 -> 10413.932 | F80: 已发
A81: 46141 | B81: 狮桥兑付 | C81: 7.63 | E81: =+E80+C81-D81 -> 10421.562
E82: =+E81+C82-D82 -> 10421.562
A83: 46153 | B83: 回款 | C83: 16 | E83: =+E82+C83-D83 -> 10437.562
A84: 46154 | B84: 诚远3期 | D84: 1500 | E84: =+E83+C84-D84 -> 8937.5624 | F84: 5/12，诚远3期优先B[500665.SZ]，1500w，净价100，渣打证券 计艳杰 to 芜湖元康 Z06308，刘靖涛qt3003993899
E85: =+E84+C85-D85 -> 8937.5624
A86: 46157 | B86: 平安普惠回款 | C86: 1562 | E86: =+E85+C86-D86 -> 10499.562
A87: 46157 | B87: 赎回 | D87: =12330*1.027-5350 -> 7312.91 | E87: =+E86+C87-D87 -> 3186.6524
E88: =+E87+C88-D88 -> 3186.6524
A89: 46160 | B89: 国健租赁优先级B | D89: 1000 | E89: =+E88+C89-D89 -> 2186.6524 | F89: 5/18缴款，5/19起息，国健11B，268605.SH，1000w，3%，苏信Z2501
E90: =+E89+C90-D90 -> 2186.6524
E91: =+E90+C91-D91 -> 2186.6524 | G91: 出券
E92: =+E91+C92-D92 -> 2186.6524
E93: =+E92+C93-D93 -> 2186.6524
E94: =+E93+C94-D94 -> 2186.6524 | F94: 流动性诉求 | G94: =+(81529-6850)*0.1 -> 7467.9
B95: 预期底层分配 | C95: 1000 | E95: =+E94+C95-D95 -> 3186.6524 | I95: 苏信2501 | J95: 尚赢2-6 | K95: 2000 | L95: 0.031
E96: =+E95+C96-D96 -> 3186.6524 | I96: 苏信2501 | J96: 诚瑞4期ABS | K96: 2000 | L96: 0.03
E97: =+E96+C97-D97 -> 3186.6524 | I97: 苏信2501 | J97: 尚乘1期abs | K97: 2000 | L97: 0.032
E98: =+E97+C98-D98 -> 3186.6524
E99: =+E98+C99-D99 -> 3186.6524 | K99: =SUM(K95:K97) -> 6000 | L99: =SUMPRODUCT(L95:L97,K95:K97)/K99 -> 0.031
E100: =+E99+C100-D100 -> 3186.6524
B101: 搭售优先级 | D101: 3000 | E101: =+E100+C101-D101 -> 186.6524
...

Sheet 苏信次级Z2502
A2: 日期 | B2: 现金流类型 | C2: 现金流入 | D2: 现金流出 | E2: 期末余额
A3: 46023 | E3: 202
A4: 46031 | B4: 4美意6次 | D4: =100*1.08648 -> 108.648 | E4: =E3+C4-D4 -> 93.352 | F4: 4美意6次 (262764.SH)，100w，全价108.648，2026-1-9，国泰海通 樊文娟 to 苏信财富组合添利Z2502集合资金信托计划 徐健
E5: =E4+C5-D5 -> 93.352
E6: 94
E7: =E6+C7-D7 -> 94 | F7: 待定 | J7: 1月份排券计划
E8: =E7+C8-D8 -> 94 | F8: 待定 | J8: 证券名称 | K8: 代码 | L8: 票息（预期） | M8: 数量 | N8: 净价 | O8: 全价 | P8: 规模 | Q8: 交易日期 | R8: 后手收益率 | S8: 上家 | T8: 过桥 | U8: 过桥费 | V8: 最新估值 | W8: 估值日期 | X8: 估值后手收益率 | Y8: 最新评级 | Z8: 上个付息日 | AA8: 应计利息 | AB8: 起息日 | AC8: 本金开始摊还日 | AD8: 预计到期日 | AE8: 剩余面值
E9: =E8+C9-D9 -> 94 | J9: 启悦15次 | K9: 146285.SZ | L9: 0.07 | M9: 500 | O9: =ROUND(V9*(1+6.5%/365*(Q9-W9)),3)+U9 -> 103.616 | P9: =O9*M9/100 -> 518.08 | Q9: 46041 | R9: 0.07 | S9: 28号 | T9: 扬讯 | U9: 0.01 | V9: 103.5134 | W9: 46036 | X9: 0.07
E10: =E9+C10-D10 -> 94 | J10: 启悦16次 | K10: 146761.SZ | L10: 0.065 | M10: 300 | O10: =ROUND(V10*(1+6.5%/365*(Q10-W10)),3)+U10 -> 102.689 | P10: =O10*M10/100 -> 308.067 | Q10: 46041 | R10: 0.0664 | S10: 28号 | T10: 扬讯 | U10: 0.01 | V10: 102.5881 | W10: 46036 | X10: 0.0665 | Z10: na | AB10: 45888 | AC10: 46468 | AD10: 46590 | AE10: 100 | AF10: 按预计估值，平价出
E11: =+E10+C11-D11 -> 94 | J11: 熹焱03A3 | K11: 144237.SZ | L11: 0.047 | M11: 1000 | N11: 38.56 | O11: =N11+U11+AA11 -> 38.594788 | P11: =O11*M11/100 -> 385.94788 | Q11: 46041 | R11: 0.044 | S11: 28号 | T11: 扬讯 | U11: 0.01 | V11: 38.562 | W11: 46037 | X11: 0.03873 | Y11: AAA | Z11: 46037 | AA11: =AE11*L11/365*(Q11-Z11+1) -> 0.024787671 | AB11: 45439 | AC11: 45915 | AD11: 46310 | AE11: 38.5 | AF11: 根据估值出 | AG11: =(V11-N11)*M11*100 -> 200
E12: =+E11+C12-D12 -> 94 | J12: 熹焱07A3 | K12: 144671.SZ | L12: 0.043 | M12: 2310 | N12: 80.65 | O12: =N12+U12+AA12 -> 80.707447 | P12: =O12*M12/100 -> 1864.342 | Q12: 46041 | R12: 0.041 | S12: 28号 | T12: 扬讯 | U12: 0.01 | V12: 80.7103 | W12: 46037 | X12: 0.0395 | Y12: AAA | Z12: 46037 | AA12: =AE12*L12/365*(Q12-Z12+1) -> 0.04744726 | AB12: 45562 | AC12: 45976 | AD12: 46492 | AE12: 80.55 | AF12: 根据估值出 | AG12: =(V12-N12)*M12*100 -> 13929.3
A13: 46037 | B13: 兑付 | C13: 251 | E13: =+E12+C13-D13 -> 345 | J13: 工鑫39次 | K13: 265852.SH | L13: 0.065 | M13: 1100 | O13: 103.418 | P13: =O13*M13/100 -> 1137.598 | Q13: 46045 | R13: 0.06 | S13: 中金 | Z13: na | AB13: 45882 | AC13: 46976 | AD13: 46976 | AF13: 中金代持期间5.5%
A14: 46038 | B14: 申购 | C14: 9089 | E14: =+E13+C14-D14 -> 9434 | J14: 工鑫41次 | K14: 266482.SH | L14: 0.065 | M14: 1260 | O14: 102.825 | P14: =O14*M14/100 -> 1295.595 | Q14: 46045 | R14: 0.06 | S14: 中金 | Z14: na | AB14: 45918 | AC14: 47014 | AD14: 47014 | AF14: 中金代持期间5.5%
A15: 46041 | B15: 启悦15次 | D15: =P9 -> 518.08 | E15: =+E14+C15-D15 -> 8915.92 | F15: 启悦15次，146285.SZ,500w，全价103.616,1月19日，芜湖扬讯 to 苏信Z2502 | H15: 启悦15次，146285.SZ,500w，全价103.606,1月19日，元康28号to 扬讯 | I15: 待上市 | J15: 铁建Y28C | K15: 267372.SH | L15: 0.055 | M15: 2860 | O15: 100.481 | P15: =O15*M15/100 -> 2873.7566 | Q15: 46045 | R15: 0.055 | S15: 国泰海通 | Z15: na | AB15: 46006 | AC15: 46188 | AD15: 46188 | AF15: 国泰代持期间4.5%
A16: 46041 | B16: 启悦16次 | D16: =P10 -> 308.067 | E16: =+E15+C16-D16 -> 8607.853 | F16: 启悦16次,146761.SZ,300w,全价102.689，1月19日，芜湖扬讯 to 苏信Z2502 | H16: 启悦16次,146761.SZ,300w,全价102.679，1月19日，元康28号 to 扬讯 | J16: 熠安02A3 | K16: 144651.SZ | L16: 0.043 | M16: 1172 | N16: 94.9 | O16: =N16+U16+AA16 -> 94.955835 | P16: =O16*M16/100 -> 1112.8824 | Q16: 46041 | R16: 0.04 | S16: 20号 | T16: 扬讯 | U16: 0 | V16: 94.9534 | W16: 46037 | X16: 0.039312 | Y16: AAA | Z16: 46037 | AA16: =AE16*L16/365*(Q16-Z16+1) -> 0.055835205 | AB16: 45559 | AC16: 46037 | AD16: 46492 | AE16: 94.79 | AF16: 根据估值出 | AG16: =(V16-N16)*M16*100 -> 6258.48
A17: 46041 | B17: 熹焱03A3 | D17: =P11 -> 385.94788 | E17: =+E16+C17-D17 -> 8221.9051 | F17: 熹焱03A3,144237.SZ,1000w,净价38.56，1月19日，芜湖扬讯 to 苏信Z2502 | H17: 熹焱03A3,144237.SZ,1000w,净价38.55，1月19日，元康28号 to 扬讯 | O17: 总规模 | P17: =SUM(P9:P16) -> 9496.2689 | Q17: 加权收益 | R17: =SUMPRODUCT(R9:R16,P9:P16)/P17 -> 0.052515833
A18: 46041 | B18: 熹焱07A3 | D18: =P12 -> 1864.342 | E18: =+E17+C18-D18 -> 6357.5631 | F18: 熹焱07A3,144671.SZ,2310w,净价80.65，1月19日，芜湖扬讯 to 苏信Z2502 | H18: 熹焱07A3,144671.SZ,2310w,净价80.65，1月19日，元康28号 to 扬讯
B19: 熠安02A3 | D19: =P16 -> 1112.8824 | E19: =+E18+C19-D19 -> 5244.6807 | F19: 熠安02A3,144651.SZ,1172w,净价94.9，1月19日，芜湖扬讯 to 苏信Z2502 | H19: 熠安02A3,144651.SZ,1172w,净价94.89, 1月19日，元康20号 to 扬讯
A20: 46042 | B20: 荟享244C | C20: 982 | E20: =+E19+C20-D20 -> 6226.6807 | F20: 1/20+0，荟享244C，146608.SZ，966w，净价100.209元， 苏信财富组合添利Z2502集合资金信托计划 徐健qq455768073 to 粤开证券（许逸潇）
E21: =+E20+C21-D21 -> 6226.6807
A22: 46045 | B22: 工鑫39次 | D22: =P13 -> 1137.598 | E22: =+E21+C22-D22 -> 5089.0827 | F22: 工鑫39次,265852.SH,1100w,全价103.418，1月23日，厦门信托鑫鹭1号李丹萍3003775644 to 苏信财富组合添利Z2502，徐健qq455768073
A23: 46045 | B23: 工鑫41次 | D23: =P14 -> 1295.595 | E23: =+E22+C23-D23 -> 3793.4877 | F23: 工鑫41次,266482.SH,1260w,全价102.825，1月23日，厦门信托鑫鹭1号李丹萍3003775644 to 苏信财富组合添利Z2502，徐健qq455768073
E24: =+E23+C24-D24 -> 3793.4877 | F24: 铁建Y28C,267372.SH,2860w,全价100.481
E25: 3830
A26: 46055 | B26: 一冶 | D26: 900 | E26: =+E25+C26-D26 -> 2930
A27: 46077 | B27: 回款 | C27: 885 | E27: =+E26+C27-D27 -> 3815 | J27: 证券名称 | K27: 代码 | L27: 票息（预期） | M27: 数量 | N27: 净价 | O27: 全价 | P27: 规模 | Q27: 交易日期 | R27: 后手收益率 | T27: 过桥 | U27: 过桥费 | V27: 最新估值 | W27: 估值日期 | X27: 估值后手收益率 | Y27: 最新评级 | Z27: 上个付息日 | AA27: 应计利息 | AB27: 起息日 | AC27: 本金开始摊还日 | AD27: 预计到期日 | AE27: 剩余面值
E28: =+E27+C28-D28 -> 3815 | J28: 熠安02A3 | K28: 144651.SZ | L28: 0.043 | M28: 1100 | N28: 69.39 | O28: =N28+U28+AA28 -> 69.457157 | P28: =M28*O28/100 -> 764.02873 | Q28: 46083 | R28: 0.03885 | T28: 扬讯 | U28: 0.01 | V28: 69.3978 | W28: 46080 | X28: 0.0388 | Y28: AAA | Z28: 46077 | AA28: =AE28*L28/365*(Q28-Z28+1) -> 0.057157014 | AB28: 45559 | AC28: 46037 | AD28: 46492 | AE28: 69.31 | AF28: 20号
E29: =+E28+C29-D29 -> 3815 | J29: 铁建051C | K29: 199768.SH | L29: 0.085 | M29: 665 | N29: 111.89 | O29: =N29+U29 -> 111.9 | P29: =M29*O29/100 -> 744.135 | Q29: 46083 | R29: 0.059 | T29: 扬讯 | U29: 0.01 | V29: 111.2463 | W29: 46079 | X29: 0.085 | Y29: NA | Z29: 45959 | AA29: 0 | AB29: 45068 | AC29: 46164 | AD29: 46164 | AE29: 100 | AF29: 20号
A30: 46080 | B30: 回款 | C30: 338 | E30: =+E29+C30-D30 -> 4153 | J30: 5美意1次 | K30: 263091.SH | L30: 0.059 | M30: 2000 | N30: 108.814 | O30: =N30+U30 -> 108.824 | P30: =M30*O30/100 -> 2176.48 | Q30: 46083 | R30: 0.059 | T30: 扬讯 | U30: 0.01 | V30: 108.7534 | W30: 46079 | X30: 0.059 | Y30: NA | Z30: - | AA30: 0 | AB30: 45532 | AC30: 46138 | AD30: 46138 | AE30: 100 | AF30: 20号
A31: 46080 | B31: 春节后申购 | C31: 6197 | E31: =+E30+C31-D31 -> 10350 | J31: 5美意3次 | K31: 263710.SH | L31: 0.059 | M31: 2100 | N31: 107.565 | O31: =N31+U31 -> 107.565 | P31: =M31*O31/100 -> 2258.865 | Q31: 46083 | R31: 0.059 | V31: 107.6081 | W31: 46079 | X31: 0.059 | Y31: NA | Z31: - | AA31: 0 | AB31: 45615 | AC31: 46168 | AD31: 46168 | AE31: 100 | AF31: 西藏信托
A32: 46083 | B32: 熠安02A3 | D32: =P28 -> 764.02873 | E32: =+E31+C32-D32 -> 9585.9713 | F32: 熠安02A3[144651.SZ]，1100w，净价69.39, 3/2，元康盛景20号 to 扬讯；熠安02A3[144651.SZ]，1100w，净价69.4, 3/2，扬讯 to 苏信财富Z2502； | J32: 铁建Y28C | K32: 267372.SH | L32: 0.055 | M32: 2860 | N32: 100.962 | O32: =N32 -> 100.962 | P32: =M32*O32/100 -> 2887.5132 | Q32: 46084 | R32: 0.063273862 | V32: 无 | Y32: NA | Z32: - | AA32: 0 | AB32: 46006 | AC32: 46188 | AD32: 46188 | AE32: 100 | AF32: 国泰海通
A33: 46083 | B33: 铁建051C | D33: =P29 -> 744.135 | E33: =+E32+C33-D33 -> 8841.8363 | F33: 铁建051C（199768.SH），665w，111.89，3/2，元康盛景20号 to 扬讯；铁建051C（199768.SH），665w，111.90，3/2，扬讯 to 苏信财富Z2502； | J33: 4美意6次 | K33: 262764.SH | L33: 0.059 | M33: 300 | N33: 109.42 | O33: =N33+U33 -> 109.43 | P33: =M33*O33/100 -> 328.29 | Q33: 46083 | R33: 0.059 | T33: 扬讯 | U33: 0.01 | V33: 109.359 | W33: 46079 | X33: 0.059 | Y33: NA | Z33: - | AA33: 0 | AB33: 45496 | AC33: 46092 | AD33: 46092 | AE33: 100 | AF33: 20号
A34: 46083 | B34: 5美意1次 | D34: =P30 -> 2176.48 | E34: =+E33+C34-D34 -> 6665.3563 | F34: 5美意1次[263091.SH] ，2000w，108.814,3/2，元康盛景20号 to 扬讯；5美意1次[263091.SH] ，2000w，108.824,3/2，扬讯to 苏信Z2502 | J34: 睿昕1次 | K34: 144259.SZ | L34: 0.08 | M34: 400 | N34: 63.993 | O34: =N34+U34 -> 64.003 | P34: =M34*O34/100 -> 256.012 | Q34: 46083 | R34: 0.08 | T34: 扬讯 | U34: 0.01 | V34: 63.993 | W34: 46077 | X34: 0.08 | Y34: NA | Z34: - | AA34: 0 | AB34: 45443 | AC34: 46013 | AD34: 46409 | AE34: 56.52 | AF34: 23号
A35: 46083 | B35: 5美意3次 | D35: =P31 -> 2258.865 | E35: =+E34+C35-D35 -> 4406.4913 | F35: 5美意3次[263710.SH] ，2100w，107.565,3/2，西藏信托君集2号 2850981264钟振涛 to 苏信财富组合添利Z2502集合资金信托计划，徐健qq455768073 | J35: 熹焱07A3 | K35: 144671.SZ | L35: 0.043 | M35: 450 | N35: 72.8032 | O35: =N35+U35+AA35 -> 72.873136 | P35: =M35*O35/100 -> 327.92911 | Q35: 46083 | R35: 0.039 | T35: 扬讯 | U35: 0.01 | V35: 72.8127 | W35: 46080 | X35: 0.039 | Y35: NA | Z35: 46077 | AA35: =AE35*L35/365*(Q35-Z35+1) -> 0.05993611 | AE35: 72.68 | AF35: 26号
A36: 46083 | B36: 4美意6次 | D36: =P33 -> 328.29 | E36: =+E35+C36-D36 -> 4078.2013 | F36: 4美意6次[262764.SH] ,300w,109.42全价，3月2日，元康盛景20号 to 扬讯；4美意6次[262764.SH] ,300w,109.43全价，3月2日，扬讯 to 苏信Z2502； | P36: =SUM(P28:P35) -> 9743.253 | Q36: 加权收益率 | R36: =SUMPRODUCT(R28:R35,P28:P35)/SUM(P28:P35) -> 0.058565168
A37: 46083 | B37: 睿昕1次 | D37: =P34 -> 256.012 | E37: =+E36+C37-D37 -> 3822.1893 | F37: 睿昕1次 (144259.SZ)，400w，63.993全价，3/2，元康盛景23号 to 扬讯；睿昕1次 (144259.SZ)，400w，64.003全价，3/2，扬讯 to 苏信Z2502；
A38: 46083 | B38: 熹焱07A3 | D38: =P35 -> 327.92911 | E38: =+E37+C38-D38 -> 3494.2602 | F38: 熹焱07A3[144671.SZ] ，450w，净价72.803，3/2，元康26号 to 扬讯；熹焱07A3[144671.SZ] ，450w，净价72.813，3/2， 扬讯 to 苏信Z2502； | H38: 铁建051C | I38: =XIRR(I39:I40,H39:H40) -> 0.061090407 | M38: 铁建Y28C | N38: =XIRR(N39:N40,M39:M40) -> 0.045820257 | R38: 5美意3次 | S38: =XIRR(S39:S40,R39:R40) -> 0.058523878
A39: 46084 | B39: 铁建Y28C | D39: =P32 -> 2887.5132 | E39: =+E38+C39-D39 -> 606.74696 | F39: 铁建Y28C，267372.SH，2860w，100.962,3/3，国泰海通 樊文娟 to 苏信财富组合添利Z2502集合资金信托计划，徐健qq455768073 | H39: 46038 | I39: -111.075 | M39: 46006 | N39: -100 | R39: 45615 | S39: -100
E40: =+E39+C40-D40 -> 606.74696 | H40: 46083 | I40: 111.89 | J40: =-I39*(1+K40*(H40-H39)/365) -> 111.89665 | K40: 0.06 | M40: 46084 | N40: 100.962 | O40: =-N39*(1+P40*(M40-M39)/365) -> 100.96164 | P40: 0.045 | R40: 46083 | S40: 107.565 | T40: =-S39*(1+U40*(R40-R39)/365) -> 107.56493 | U40: 0.059
A41: 46092 | B41: 回款 | C41: 124.5 | E41: 654 | F41: 支付管理费
A42: 46094 | B42: 睿铭3次 | D42: =600*105.481% -> 632.886 | E42: =+E41+C42-D42 -> 21.114 | F42: 睿铭3次 (264171.SH)，600w，105.481全价，3/13，西藏君集2号 to 苏信Z2502 | H42: 5美意1次 | I42: =XIRR(I43:I44,H43:H44) -> 0.057550624 | M42: 4美意6次 | N42: =XIRR(N43:N44,M43:M44) -> 0.0575735 | R42: 5美好3次 | S42: =XIRR(S43:S44,R43:R44) -> 0.058250323 | U42: 5美意3次 | V42: =XIRR(V43:V44,U43:U44) -> 0.058491322
A43: 46097 | B43: 回款 | C43: 594 | E43: =+E42+C43-D43 -> 615.114 | H43: 45532 | I43: -100 | M43: 45496 | N43: -100 | R43: 45562 | S43: -100 | U43: 45615 | V43: -100
A44: 46097 | B44: 睿铭3次 | D44: =534*105.54% -> 563.5836 | E44: =+E43+C44-D44 -> 51.5304 | F44: 睿铭3次 (264171.SH)，534w，105.54全价，3/16，西藏君达5号 to 苏信Z2502 | H44: 46083 | I44: 108.814 | J44: =-I43*(1+K44*(H44-H43)/365) -> 108.816 | K44: 0.0584 | M44: 46083 | N44: 109.42 | O44: =-N43*(1+P44*(M44-M43)/365) -> 109.42416 | P44: 0.0586 | R44: 46090 | S44: =-S43*(1+5.9%*(R44-R43)/365) -> 108.53479 | U44: 46090 | V44: =-V43*(1+5.9%*(U44-U43)/365) -> 107.67808
E45: =+E44+C45-D45 -> 51.5304
E46: =+E45+C46-D46 -> 51.5304 | AI46: 46100
E47: =+E46+C47-D47 -> 51.5304 | J47: 证券名称 | K47: 代码 | L47: 票息（预期） | M47: 数量 | N47: 净价 | O47: 全价 | P47: 规模 | Q47: 交易日期 | R47: 后手收益率 | S47: 最新估值 | T47: 估值日期 | U47: 估值后手收益率 | V47: 最新评级 | W47: 上个付息日 | X47: 应计利息 | Y47: 起息日 | Z47: 本金开始摊还日 | AA47: 预计到期日 | AB47: 剩余面值 | AD47: 过桥 | AF47: 上家 | AG47: 过券1 | AH47: 过券2 | AI47: 中证
A48: 46101 | B48: 申购 | C48: 11650 | E48: =+E47+C48-D48 -> 11701.53 | J48: 熠安02A3 | K48: 144651.SZ | L48: 0.043 | M48: 3200 | N48: =AH48 -> 61.43 | O48: =N48+AE48+X48 -> 61.495016 | P48: =M48*O48/100 -> 1967.8405 | Q48: 46105 | R48: =U48 -> 0.037134 | S48: 61.4208 | T48: 46101 | U48: 0.037134 | V48: AAA | W48: 46097 | X48: =AB48*L48/365*(Q48-W48+1) -> 0.065016 | Y48: 45559 | Z48: 46037 | AA48: 46461 | AB48: 61.32 | AD48: 粤开、天风 | AF48: 61.42 | AG48: =+AF48+0.005 -> 61.425 | AH48: =+AG48+0.005 -> 61.43 | AI48: 61.71 | AJ48: =+(AI48-AF48)*M48*100 -> 92800 | AK48: =J48&"["&K48&"]，"&M48&"w，"&N48&"，"&TEXT(Q48,"m月d日")&"，"&AD51&" to 苏信2502" -> 熠安02A3[144651.SZ]，3200w，61.43，3月24日， to 苏信2502
A49: 46104 | B49: 底层回款 | C49: 683 | E49: =+E48+C49-D49 -> 12384.53 | J49: 小鹏5次 | K49: 500447.SZ | L49: 0.068 | M49: 2000 | N49: =AH49 -> 101.11 | O49: =N49+AE49+X49 -> 101.11 | P49: =M49*O49/100 -> 2022.2 | Q49: 46105 | R49: 0.0665 | S49: 100.6643 | T49: 46101 | U49: 0.068 | V49: NA | W49: 46066 | X49: 0 | Y49: 46066 | Z49: 47154 | AA49: 47519 | AB49: 100 | AD49: 粤开、天风 | AF49: 101.1 | AG49: =+AF49+0.005 -> 101.105 | AH49: =+AG49+0.005 -> 101.11 | AJ49: =+(S49-AF49)*M49*100 -> -87140 | AK49: =J49&"["&K49&"]，"&M49&"w，"&N49&"，"&TEXT(Q49,"m月d日")&"，"&AD52&" to 苏信2502" -> 小鹏5次[500447.SZ]，2000w，101.11，3月24日， to 苏信2502
E50: =+E49+C50-D50 -> 12384.53 | P50: =SUM(P48:P49) -> 3990.0405 | AJ50: =SUM(AJ48:AJ49) -> 5660
A51: 46105 | B51: 熠安02A3 | D51: =+P48 -> 1967.8405 | E51: =+E50+C51-D51 -> 10416.69 | F51: 熠安02A3[144651.SZ]，3200w，61.43，3月24日，天风证券 唐德婷qt 2885078648 to 苏信2502
A52: 46105 | B52: 小鹏5次 | D52: =+P49 -> 2022.2 | E52: =+E51+C52-D52 -> 8394.4899 | F52: 小鹏5次[500447.SZ]，2000w，101.11，3月24日，天风证券 唐德婷qt 2885078648 to 苏信2502
E53: =+E52+C53-D53 -> 8394.4899 | O53: 铁建081C | P53: =XIRR(P54:P57,O54:O57) -> 0.066252086 | R53: G铁建82C | S53: =XIRR(S54:S57,R54:R57) -> 0.06624873
A54: 46108 | B54: 底层回款 | C54: 340 | E54: 8737 | O54: 45832 | P54: -100 | R54: 45923 | S54: -100
A55: 46111 | B55: 铁建051C | D55: =1755*1.12 -> 1965.6 | E55: =+E54+C55-D55 -> 6771.4 | F55: 3、3-30 铁建051C (199768.SH) 112.488 1755W 粤开证券（QT:2881647849）出 苏信财富Z2502，徐健 | O55: 45958 | P55: 1.726 | R55: 46080 | S55: 2.1506
E56: =+E55+C56-D56 -> 6771.4 | O56: 46044 | P56: 1.1781 | R56: 46132 | S56: 101.571
E57: =+E56+C57-D57 -> 6771.4 | O57: 46132 | P57: 102.438
E58: 6761
A59: 46125 | B59: 泓晟1号3期次级回款 | C59: 942 | E59: =+E58+C59-D59 -> 7703
B60: 5美意1次回款 | C60: 192.4 | E60: =+E59+C60-D60 -> 7895.4
E61: =+E60+C61-D61 -> 7895.4
A62: 46127 | B62: 回款 | C62: 885 | E62: =+E61+C62-D62 -> 8780.4 | N62: =+T62*1.01 -> 112.03016 | T62: =+S64+8.5*4/365 -> 110.92095
E63: =+E62+C63-D63 -> 8780.4 | J63: 证券名称 | K63: 代码 | L63: 票息（预期） | M63: 数量 | N63: 净价 | O63: 全价 | P63: 规模 | Q63: 交易日期 | R63: 后手收益率 | S63: 最新估值 | T63: 估值日期 | U63: 估值后手收益率 | V63: 最新评级 | W63: 上个付息日 | X63: 应计利息 | Y63: 起息日 | Z63: 本金开始摊还日 | AA63: 预计到期日 | AB63: 剩余面值
A64: 46128 | B64: 铁建061C | D64: 733 | E64: =+E63+C64-D64 -> 8047.4 | F64: 铁建061C[260663.SH]，655w，112.02，4月16日，粤开证券 许逸潇2881647849 to 苏信Z2502 徐健 qt455768073 | J64: 铁建061C | K64: 260663.SH | L64: 0.085 | M64: 655 | N64: 112.02 | O64: =+N64 -> 112.02 | P64: =M64*O64/100 -> 733.731 | Q64: 46128 | R64: 0.055 | S64: 110.8278 | T64: 46125 | U64: 0.055 | V64: NR | W64: 45982 | X64: 0 | Y64: 45187 | Z64: 46283 | AA64: 46283 | AB64: 100 | AC64: =J64&"["&K64&"]，"&M64&"w，"&N64&"，"&TEXT(Q64,"m月d日")&"，"&AE64&" to "&AF64 -> 铁建061C[260663.SH]，655w，112.02，4月16日，【】 to 苏信Z2502 | AE64: 【】 | AF64: 苏信Z2502
A65: 46129 | B65: 熠然04A3 | D65: 2754 | E65: =+E64+C65-D65 -> 5293.4 | F65: 熠然04A3[146002.SZ]，2940w，93.671，4月17日，天风证券 李泽堃3007354220 to 苏信Z2502 徐健 qt455768073 | AF65: 苏信Z2502
E66: =+E65+C66-D66 -> 5293.4
A67: 46132 | B67: 申购 | C67: 15445 | E67: =+E66+C67-D67 -> 20738.4 | J67: 4/20交易 | N67: 0.005 | O67: =N69-N67 -> 93.666
A68: 46132 | B68: 铁建081C | D68: 1751.6898 | E68: =+E67+C68-D68 -> 18986.71 | F68: 铁建081C（265587.SH），1045w，102.438，4月20日，清哲清信21号 Z13506 1549350975，李韧 to 苏信2502 徐健 qt455768073；铁建081C（265587.SH），665w，102.438，4月20日，鹏石启航9号 Z13506 3911232885，蔡一茂 to 苏信2502 徐健 qt455768073 | J68: 证券名称 | K68: 代码 | L68: 票息（预期） | M68: 数量 | N68: 净价 | O68: 全价 | P68: 规模 | Q68: 交易日期 | R68: 后手收益率 | S68: 最新估值 | T68: 估值日期 | U68: 估值后手收益率 | V68: 最新评级 | W68: 上个付息日 | X68: 应计利息 | Y68: 起息日 | Z68: 本金开始摊还日 | AA68: 预计到期日 | AB68: 剩余面值
A69: 46132 | B69: G铁建82C | D69: 116.80665 | E69: =+E68+C69-D69 -> 18869.904 | F69: G铁建82C（266500.SH），115w，101.571，4月20日，鹏石启航9号 Z13506 3911232885，蔡一茂 to 苏信2502 徐健 qt455768073 | I69: 待沟通 | J69: 熠然04A3 | K69: 146002.SZ | L69: 0.044 | M69: 2940 | N69: =ROUND(S69+0.005,3) -> 93.671 | O69: =N69+X69 -> 93.704781 | P69: =M69*O69/100 -> 2754.9206 | Q69: 46129 | R69: =+U69 -> 0.0375 | S69: 93.6657 | T69: 46127 | U69: 0.0375 | V69: AAA | W69: 46127 | X69: =AB69*L69/365*(Q69-W69+1) -> 0.033781151 | Y69: 45651 | Z69: 46127 | AA69: 46736 | AB69: 93.41 | AC69: =J69&"["&K69&"]，"&M69&"w，"&N69&"，"&TEXT(Q69,"m月d日")&"，"&AE65&" to "&AF65 -> 熠然04A3[146002.SZ]，2940w，93.671，4月17日， to 苏信Z2502
A70: 46132 | B70: 启臻1次 | D70: 302.955 | E70: =+E69+C70-D70 -> 18566.949 | F70: 启臻1次[266524.SH]，300w，100.986，4月20日， to | J70: 铁建081C | P70: 1751.6898
A71: 46132 | B71: 启悦15次 | D71: 312.837 | E71: =+E70+C71-D71 -> 18254.112 | F71: 启悦15次[146285.SZ]，300w，104.28，4月20日， to | J71: G铁建82C | P71: 116.80665
A72: 46132 | B72: 启恒1次 | D72: 503.955 | E72: =+E71+C72-D72 -> 17750.157 | F72: 启恒1次[500486.SZ]，500w，100.792，4月20日， to | J72: 启臻1次 | K72: 266524.SH | L72: 0.06 | M72: 300 | N72: =100.98+0.006 -> 100.986 | O72: =N72+X72 -> 100.986 | P72: =M72*O72/100 -> 302.958 | Q72: 46132 | R72: 0.06 | S72: 100.7838 | T72: 46125 | V72: NR | W72: 46104 | X72: 0 | Y72: 45947 | AA72: 46958 | AB72: 100 | AC72: =J72&"["&K72&"]，"&M72&"w，"&N72&"，"&TEXT(Q72,"m月d日")&"，"&AE67&" to "&AF67 -> 启臻1次[266524.SH]，300w，100.986，4月20日， to
E73: =+E72+C73-D73 -> 17750.157 | J73: 启悦15次 | K73: 146285.SZ | L73: 0.07 | M73: 300 | N73: =104.274+0.006 -> 104.28 | O73: =N73+X73 -> 104.28 | P73: =M73*O73/100 -> 312.84 | Q73: 46132 | R73: 0.068 | S73: 103.9983 | T73: 46125 | V73: NR | W73: 46104 | X73: 0 | Y73: 45757 | AA73: 46743 | AB73: 100 | AC73: =J73&"["&K73&"]，"&M73&"w，"&N73&"，"&TEXT(Q73,"m月d日")&"，"&AE68&" to "&AF68 -> 启悦15次[146285.SZ]，300w，104.28，4月20日， to
E74: =+E73+C74-D74 -> 17750.157 | J74: 启恒1次 | K74: 500486.SZ | L74: 0.0598 | M74: 500 | N74: =100.786+0.006 -> 100.792 | O74: =N74+X74 -> 100.792 | P74: =M74*O74/100 -> 503.96 | Q74: 46132 | R74: 0.06 | S74: 100.6862 | T74: 46125 | V74: NR | W74: 46084 | X74: 0 | Y74: 46084 | AA74: 47079 | AB74: 100 | AC74: =J74&"["&K74&"]，"&M74&"w，"&N74&"，"&TEXT(Q74,"m月d日")&"，"&AE69&" to "&AF69 -> 启恒1次[500486.SZ]，500w，100.792，4月20日， to
E75: =+E74+C75-D75 -> 17750.157 | J75: 铁建081C | K75: 265587.SH | L75: 0.085 | M75: =1045+665 -> 1710 | N75: 102.438 | O75: 102.438 | P75: =M75*O75/100 -> 1751.6898 | Q75: 46132 | R75: 0.055 | S75: 102.3218 | T75: 46127 | V75: NR | W75: 46044 | X75: 0 | Y75: 45832 | AA75: 46562 | AB75: 100
A76: 46133 | B76: 晨惠2期 | D76: 1000 | E76: =+E75+C76-D76 -> 16750.157 | F76: 已发 | J76: G铁建82C | K76: 266500.SH | L76: 0.085 | M76: 115 | N76: 101.571 | O76: 101.571 | P76: =M76*O76/100 -> 116.80665 | Q76: 46132 | R76: 0.055 | S76: 101.4792 | T76: 46127 | V76: NR | W76: 46080 | X76: 0 | Y76: 45923 | AA76: 46653 | AB76: 100
E77: =+E76+C77-D77 -> 16750.157 | J77: 远东普惠 | P77: 2000 | Q77: 待定
A78: 46134 | B78: 回款 | C78: 402 | E78: =+E77+C78-D78 -> 17152.157 | J78: 蔚能ABS次A级 | P78: 2000 | Q78: 待定
A79: 46134 | B79: 工鑫两期 | D79: =915*105.163%+752*105.692% -> 1757.0453 | E79: =+E78+C79-D79 -> 15395.111 | F79: 4/22，工鑫37次，265580.SH，915w，净价105.158，元康23号 刘靖涛qt3003993899 to 粤开证券 许逸潇2881647849 4/22，工鑫37次，265580.SH，915w，净价105.163，粤开证券 许逸潇2881647849 to 苏信 徐健 qt455768073 4/22，工鑫38次，265651.SH，752w，净价105.687，元康23号 刘靖涛qt3003993899 to 粤开证券 许逸潇2881647849 4/22，工鑫38次，265651.SH，752w，净价105.692，粤开证券 许逸潇2881647849 to 苏信 徐健 qt455768073 | J79: 蔚能ABS优B | P79: 8000 | Q79: 待定
A80: 46134 | B80: 睿铭3次 | D80: =80*105.789% -> 84.6312 | E80: =+E79+C80-D80 -> 15310.48 | F80: 4/22，睿铭3次，264171.SH，80w，净价105.789，粤开证券 许逸潇2881647849 to 苏信 徐健 qt455768073 | J80: 晨惠2期 | P80: 1000 | Q80: 待定
E81: =+E80+C81-D81 -> 15310.48 | J81: 启悦11次 | P81: 580 | Q81: 待定
E82: =+E81+C82-D82 -> 15310.48 | J82: 铁建085C | P82: 1500 | Q82: 待定
A83: 46139 | B83: 熠安02A3 | D83: =2300*52.5268% -> 1208.1164 | E83: =+E82+C83-D83 -> 14102.364 | F83: 熠安02A3[144651.SZ]，2300w，52.5268，4月27日，粤开证券 许逸潇2881647849 to 苏信2502 徐健 qt455768073 | J83: 熠安02A3 | P83: 2700 | Q83: 待定
A84: 46139 | B84: 5美意3次+5美意1次 | C84: 2855 | E84: =+E83+C84-D84 -> 16957.364
A85: 46140 | B85: 23领航3C | C85: 293 | E85: =+E84+C85-D85 -> 17250.364 | P85: =SUM(P69:P84) -> 25391.671
A86: 46140 | B86: 23领航4C | C86: 813.7 | E86: =+E85+C86-D86 -> 18064.064
A87: 46141 | B87: 蔚能ABS次A级 | D87: 2000 | E87: =+E86+C87-D87 -> 16064.064 | F87: 已发
A88: 46141 | B88: 蔚能优B | D88: 6900 | E88: =+E87+C88-D88 -> 9164.0637 | F88: 已发
E89: =+E88+C89-D89 -> 9164.0637
A90: 46141 | B90: 铁建081C | D90: =1000*101.379% -> 1013.79 | E90: =+E89+C90-D90 -> 8150.2737 | F90: 1、铁建081C[265587.SH], 1000w, 101.379，4月29日，方田维纳3号 Z13506 to 苏信 徐健 qt455768073，约定号：668 | K90: 优先级5000 | L90: 新混合1e
A91: 46141 | B91: 铁建051C | D91: =230*112.95% -> 259.785 | E91: =+E90+C91-D91 -> 7890.4887 | F91: 2、铁建051C[199768.SH]，230w，112.95，4月29日，方田维纳3号 Z13506 to 苏信 徐健 qt455768073 ，约定号：669 | AB91: B | AC91: A+C
E92: =+E91+C92-D92 -> 7890.4887 | AA92: =38900+142500+201600 -> 383000 | AB92: =142500/AA92 -> 0.37206266 | AC92: =+(38900+201600)/AA92 -> 0.62793734
A93: 46141 | B93: 启恒2期次级 | D93: 1000 | E93: =+E92+C93-D93 -> 6890.4887 | F93: 启恒2次，500691.SZ，苏信2502，1000w，5.88%，4月29日缴款、4月30日设立
E94: =+E93+C94-D94 -> 6890.4887 | R94: 265651.SH | S94: 752 | W94: 265580.SH | X94: 915
E95: =+E94+C95-D95 -> 6890.4887 | R95: 工鑫38次 | S95: =XIRR(S96:S100,R96:R100) -> 0.062884733 | T95: =XIRR(T97:T100,R97:R100) -> 0.060246268 | W95: 工鑫37次 | X95: =XIRR(X96:X104,W96:W104) -> 0.063017151 | Y95: =XIRR(Y98:Y104,W98:W104) -> 0.060070547
E96: =+E95+C96-D96 -> 6890.4887 | R96: 45834 | S96: -100 | W96: 45820 | X96: -100
A97: 46157 | B97: 平安普惠回款 | C97: 1328 | E97: =+E96+C97-D97 -> 8218.4887 | R97: 46134 | T97: -105.69 | V97: 特别 | W97: 46093 | X97: =3*(W97-W96)/365*AA97 -> 0.83484746 | Z97: =3*(W97-W96)/365*AA97 -> 0.83484746 | AA97: =+$AB$92 -> 0.37206266
E98: =+E97+C98-D98 -> 8218.4887 | R98: 46199 | S98: =-$S$96*3%*(R98-R96)/365 -> 3 | T98: =+S98 -> 3 | W98: 46134 | Y98: -105.16
E99: =+E98+C99-D99 -> 8218.4887 | R99: 46566 | S99: =-$S$96*3%*(R99-R98)/365 -> 3.0164384 | T99: =+S99 -> 3.0164384 | V99: 一般 | W99: 46185 | X99: =3*(W99-W96)/365*AA99 -> 1.883812 | Y99: =+X99 -> 1.883812 | AA99: =+$AC$92 -> 0.62793734
E100: =+E99+C100-D100 -> 8218.4887 | R100: 46930 | S100: =-$S$96*6.5%*(R100-R96)/365-S96-S98-S99 -> 113.50137 | T100: =+S100 -> 113.50137 | U100: =-T97*(1+6%*(R100-R97)/365)-T98-T99 -> 113.50303 | V100: 特别 | W100: 46458 | X100: =3*(W100-W97)/365*AA100 -> 1.116188 | Y100: =+X100 -> 1.116188 | AA100: =+$AB$92 -> 0.37206266
E101: =+E100+C101-D101 -> 8218.4887 | V101: 一般 | W101: 46549 | X101: =3*(W101-W99)/365*AA101 -> 1.8786509 | Y101: =+X101 -> 1.8786509 | AA101: =+$AC$92 -> 0.62793734
...

Sheet 苏信混合Z2603
A2: 日期 | B2: 现金流类型 | C2: 现金流入 | D2: 现金流出 | E2: 期末余额
A3: 46156 | B3: 申购 | C3: 19982 | E3: 19982
A4: 46157 | B4: GC港华智慧能源01 | D4: =2000*101.2214% -> 2024.428 | E4: =E3+C4-D4 -> 17957.572 | F4: 5/15+0，GC港华智慧能源01，[121627.SZ]，2000w，全价101.2214，渣打证券 to 芜湖元康（元康询价，实际交易账户为苏信2603） | J4: 日期 | K4: 项目 | L4: 规模 | M4: 估值收益率
A5: 46157 | B5: 铁建085C | D5: =1950*100.556% -> 1960.842 | E5: =E4+C5-D5 -> 15996.73 | F5: 5/15，铁建085C，【267930.SH】，1950w，100.556，国泰海通 樊文娟 to 苏信2603 徐健 455768073 | J5: 5月底6月初 | K5: 蔚能ABS2期优A5 | L5: 2000 | M5: 0.056 | Q5: G铁建82C | R5: =XIRR(R6:R15,Q6:Q15) -> 0.065687832 | S5: =XIRR(S8:S15,Q8:Q15) -> 0.054906312 | T5: 2026/5/13估值
A6: 46157 | B6: 铁建053C | D6: =3000*112.31% -> 3369.3 | E6: =E5+C6-D6 -> 12627.43 | F6: 铁建053C[199886.SH] ，3000w，112.31全价，山金金泉基金产品：雷宇qq331654633 to 苏信财富组合添利Z2603集合资金信托计划徐健qq455768073 199886.SH 铁建053C 山金金石1号出2537W【中信证券Z06308】 To 苏州信托 199886.SH 铁建053C 山金金石19号出275W【华泰证券Z07409】 To 苏州信托 199886.SH 铁建053C 山金金石20号出131W【中信证券Z06308】 To 苏州信托 199886.SH 铁建053C 山金金石13号出57W【中信证券Z06308】 To 苏州信托 | J6: 5月底6月初 | K6: 蔚能ABS次A | L6: 1000 | M6: 0.08 | Q6: 45923 | R6: -100 | T6: 101.985
E7: =E6+C7-D7 -> 12627.43 | J7: 5-28缴款 | K7: 尚乘1期优先B | L7: 2000 | M7: 0.032 | Q7: 46080 | R7: 2.1506 | T7: 票面价格
A8: 46162 | B8: 尚赢贰6C | D8: 2000 | E8: =E7+C8-D8 -> 10627.43 | J8: 5-28缴款 | K8: 尚乘1期次级 | L8: 2000 | M8: 0.052 | Q8: 46157 | S8: -103.35 | T8: =ROUND(100*(1+6.5%*(Q8-Q6)/365)-R7,3) -> 102.017
A9: 46162 | B9: 美团 | D9: 1000 | E9: =E8+C9-D9 -> 9627.43 | J9: 5月22日簿记 | K9: 盛赢4-3 | L9: 2125 | M9: 0.0455 | Q9: 46167 | R9: =5*(Q9-Q7)/365 -> 1.1917808 | S9: =+R9 -> 1.1917808
E10: =E9+C10-D10 -> 9627.43 | J10: 5月18日簿记 | K10: 美满生意2025年1期1号 | L10: 1000 | M10: 0.047 | Q10: 46254 | R10: =5*(Q10-Q9)/365 -> 1.1917808 | S10: =+R10 -> 1.1917808
A11: 46163 | B11: 金采夹层 | D11: 1000 | E11: =E10+C11-D11 -> 8627.43 | J11: 5月18日簿记 | K11: 尚赢2-6 | L11: 2000 | M11: 0.031 | Q11: 46345 | R11: =5*(Q11-Q10)/365 -> 1.2465753 | S11: =+R11 -> 1.2465753
E12: =E11+C12-D12 -> 8627.43 | J12: 5月中簿记 | K12: 博枫公寓 | L12: 1000 | M12: 0.053 | N12: ？ | Q12: 46443 | R12: =5*(Q12-Q11)/365 -> 1.3424658 | S12: =+R12 -> 1.3424658
A13: 46168 | B13: 盛赢4-3 | D13: 2125 | E13: =E12+C13-D13 -> 6502.43 | J13: 可随时交易 | K13: GC港华智慧能源01[121627.SZ] | L13: 2000 | M13: 0.073 | Q13: 46527 | R13: =5*(Q13-Q12)/365 -> 1.1506849 | S13: =+R13 -> 1.1506849
E14: =E13+C14-D14 -> 6502.43 | J14: 可随时交易 | K14: 铁建085C | L14: 1950 | M14: 0.065 | N14: 平价，帮代持，成本5.5% | Q14: 46618 | R14: =5*(Q14-Q13)/365 -> 1.2465753 | S14: =+R14 -> 1.2465753
E15: =E14+C15-D15 -> 6502.43 | I15: 山金 | J15: 46157 | K15: 铁建053C | L15: 3000 | M15: 0.07 | N15: 6-8到期 | Q15: 46653 | R15: =100*(1+6.5%*(Q15-Q6)/365)-SUM(R7:R14) -> 103.47954 | S15: =+R15 -> 103.47954
E16: =E15+C16-D16 -> 6502.43
A17: 46181 | B17: 铁建053C兑付 | C17: 3372 | E17: =E16+C17-D17 -> 9874.43 | J17: 5月19日簿记 | K17: 金采8-1次级 | L17: 750 | M17: 0.0455
E18: =E17+C18-D18 -> 9874.43 | J18: 5月19日簿记 | K18: 金采8-1夹层 | L18: 1000 | M18: 0.031
E19: =E18+C19-D19 -> 9874.43 | K19: 诚瑞abs优先B | L19: 2000 | M19: 0.029
E20: =E19+C20-D20 -> 9874.43
E21: =E20+C21-D21 -> 9874.43 | L21: =SUM(L5:L18) -> 21825 | M21: =SUMPRODUCT(M5:M19,L5:L19)/L21 -> 0.056108247
E22: =E21+C22-D22 -> 9874.43 | J22: 苏信2603 | K22: 远东 | L22: 2000 | M22: 0.03 | N22: 改6月初发行了，而且结构变了
E23: =E22+C23-D23 -> 9874.43
E24: =E23+C24-D24 -> 9874.43
E25: =E24+C25-D25 -> 9874.43
E26: =E25+C26-D26 -> 9874.43

Sheet 元康1号
A2: 日期 | B2: 现金流类型 | C2: 现金流入 | D2: 现金流出 | E2: 期末余额
A3: 46023 | E3: 151
A4: 46028 | B4: 新增申购 | C4: 450 | E4: =C4+E3-D4 -> 601
A5: 46031 | B5: 新增申购 | C5: 150 | E5: =C5+E4-D5 -> 751
A6: 46031 | B6: 兑付赎回 | D6: 102.3 | E6: =C6+E5-D6 -> 648.7
A7: 46031 | B7: 朗瑞1-5 | D7: 600 | E7: =C7+E6-D7 -> 48.7
E8: =+E7+C8-D8 -> 48.7
A9: 46038 | B9: 新增申购 | C9: 1400 | E9: =+E8+C9-D9 -> 1448.7
A10: 46038 | B10: 外贸元康1 | D10: 400 | E10: =+E9+C10-D10 -> 1048.7
A11: 46045 | B11: 外贸元康1 | D11: 900 | E11: =+E10+C11-D11 -> 148.7
E12: =+E11+C12-D12 -> 148.7
A13: 46052 | B13: 鹏雅119 | D13: 50 | E13: =+E12+C13-D13 -> 98.7
A14: 46055 | B14: 期权补款 | D14: 25 | E14: =+E13+C14-D14 -> 73.7 | F14: 合计连同期权户的27w，=50w投资期权
E15: =+E14+C15-D15 -> 73.7
A16: 46058 | B16: 朗瑞1-5赎回 | C16: 1200 | E16: =+E15+C16-D16 -> 1273.7
A17: 46059 | B17: 赎回 | D17: =9914733*1.029/10000 -> 1020.226 | E17: =+E16+C17-D17 -> 253.47397
A18: 46059 | B18: 雪球申购 | C18: 100 | E18: =+E17+C18-D18 -> 353.47397
E19: =+E18+C19-D19 -> 353.47397
A20: 46062 | B20: 朗瑞1-5申购 | D20: 200 | E20: =+E19+C20-D20 -> 153.47397
A21: 46064 | B21: 期权补款 | D21: 125 | E21: =+E20+C21-D21 -> 28.473974
A22: 46066 | B22: 新增申购 | C22: 200 | E22: =+E21+C22-D22 -> 228.47397
A23: 46066 | B23: 赎回 | D23: 101 | E23: =+E22+C23-D23 -> 127.47397
E24: =+E23+C24-D24 -> 127.47397
E25: =+E24+C25-D25 -> 127.47397
E26: =+E25+C26-D26 -> 127.47397
A27: 46080 | B27: 朗瑞1-5赎回 | C27: 200 | E27: =+E26+C27-D27 -> 327.47397
A28: 46080 | B28: 赎回 | D28: =267*1.032 -> 275.544 | E28: =+E27+C28-D28 -> 51.929974
E29: =+E28+C29-D29 -> 51.929974
A30: 46084 | B30: 朗瑞1-5赎回 | C30: =朗瑞1_5!D54 -> 952 | E30: =+E29+C30-D30 -> 1003.93
E31: =+E30+C31-D31 -> 1003.93
A32: 46087 | B32: 申购 | C32: 180 | E32: =+E31+C32-D32 -> 1183.93
A33: 46090 | B33: 朗瑞1-7 | D33: 550 | E33: =+E32+C33-D33 -> 633.92997
A34: 46093 | B34: 期权补款 | D34: 60 | E34: =+E33+C34-D34 -> 573.92997
A35: 46094 | B35: 赎回 | D35: 519 | E35: =+E34+C35-D35 -> 54.929974
A36: 46094 | B36: 申购 | C36: 100 | E36: =+E35+C36-D36 -> 154.92997
E37: =+E36+C37-D37 -> 154.92997
A38: 46101 | B38: 申购 | C38: 615 | E38: =+E37+C38-D38 -> 769.92997
A39: 46104 | B39: 朗瑞1-5 | D39: 700 | E39: =+E38+C39-D39 -> 69.929974
E40: =+E39+C40-D40 -> 69.929974
E41: =+E40+C41-D41 -> 69.929974
A42: 46108 | B42: 新增申购 | C42: 100 | E42: =+E41+C42-D42 -> 169.92997
A43: 46112 | B43: 外贸元康1号赎回 | C43: 720 | E43: =+E42+C43-D43 -> 889.92997
A44: 46115 | B44: 新增申购 | C44: 201 | E44: =+E43+C44-D44 -> 1090.93
A45: 46115 | B45: 赎回 | D45: =495+164 -> 659 | E45: =+E44+C45-D45 -> 431.92997
E46: =+E45+C46-D46 -> 431.92997
E47: =+E46+C47-D47 -> 431.92997
E48: =+E47+C48-D48 -> 431.92997
A49: 46122 | B49: 赎回 | D49: 310.76 | E49: 119
A50: 46125 | B50: 雪球申购 | C50: 100 | E50: =+E49+C50-D50 -> 219
E51: =+E50+C51-D51 -> 219
E52: =+E51+C52-D52 -> 219
E53: =+E52+C53-D53 -> 219
A54: 46129 | B54: 美市申购 | C54: 200 | E54: =+E53+C54-D54 -> 419
A55: 46132 | B55: 税费 | D55: 10.36 | E55: =+E54+C55-D55 -> 408.64
A56: 46133 | B56: 中航瑞华1号赎回 | C56: 41 | E56: =+E55+C56-D56 -> 449.64
A57: 46133 | B57: 朗瑞1号5期赎回 | C57: 800 | E57: =+E56+C57-D57 -> 1249.64 | F57: 已发
A58: 46134 | B58: 元康28号 | D58: 800 | E58: =+E57+C58-D58 -> 449.64 | F58: 已发
A59: 46136 | B59: 申购 | C59: 200 | E59: =+E58+C59-D59 -> 649.64
E60: =+E59+C60-D60 -> 649.64
E61: =+E60+C61-D61 -> 649.64
A62: 46140 | B62: 外贸-元康1号赎回 | C62: 6795 | E62: =+E61+C62-D62 -> 7444.64
E63: =+E62+C63-D63 -> 7444.64
A64: 46140 | B64: 鹏雅10号119期 | D64: 3000 | E64: =+E63+C64-D64 -> 4444.64 | F64: 已发
A65: 46140 | B65: 新疆国信 | D65: 2500 | E65: =+E64+C65-D65 -> 1944.64 | F65: 4/28, 新疆国信[266682.SH] ，2500w，全价100，协鑫 to 元康盛景1号
E66: =+E65+C66-D66 -> 1944.64
E67: 1946
A68: 46141 | B68: 元康28号申购 | D68: 800 | E68: =+E67+C68-D68 -> 1146 | F68: 已发
E69: =+E68+C69-D69 -> 1146
E70: =+E69+C70-D70 -> 1146
A71: 46142 | B71: 新疆国信分配 | C71: 45.8 | E71: =+E70+C71-D71 -> 1191.8
A72: 46149 | B72: 赎回 | D72: =378.521407+1.958844 -> 380.48025 | E72: =+E71+C72-D72 -> 811.31975
A73: 46150 | B73: 申购 | C73: 100 | E73: =+E72+C73-D73 -> 911.31975
E74: =+E73+C74-D74 -> 911.31975
A75: 46155 | B75: 元康盛景31号申购 | D75: 700 | E75: =+E74+C75-D75 -> 211.31975 | F75: 已发
E76: =+E75+C76-D76 -> 211.31975
A77: 46160 | B77: 申购 | C77: 102.5 | E77: =+E76+C77-D77 -> 313.81975
E78: =+E77+C78-D78 -> 313.81975
A79: 46160 | B79: 工鑫38次 | D79: 88.88 | E79: =+E78+C79-D79 -> 224.93975 | F79: 3、方向：西藏君集1号to【元康盛景1号】 交易日期：2026年5月18日 债券代码：265651.SH 债券简称：工鑫38次 交易全价：105.805元/百元面值 数量：84万面值（8400张，840手） 卖方：西藏信托君集1号集合资金信托计划 卖方询价QQ：2850981264钟振涛 卖方交易员代码：Z07119 买方：【元康盛景1号】 买方询价QQ：【刘靖涛qt3003993899】 买方交易员代码：【Z11825】 约定号：【333】
E80: =+E79+C80-D80 -> 224.93975
E81: =+E80+C81-D81 -> 224.93975
E82: =+E81+C82-D82 -> 224.93975
A83: 46162 | B83: 工鑫38次 | C83: 88.88 | E83: =+E82+C83-D83 -> 313.81975
E84: =+E83+C84-D84 -> 313.81975
A85: 46163 | B85: 场外期权保证金提取 | C85: 252 | E85: =+E84+C85-D85 -> 565.81975
E86: =+E85+C86-D86 -> 565.81975
A87: 46164 | B87: 申购 | C87: 860 | E87: =+E86+C87-D87 -> 1425.8197
A88: 46164 | B88: 赎回 | D88: =272*1.05 -> 285.6 | E88: =+E87+C88-D88 -> 1140.2197
B89: 盛业回购 | D89: 1000 | E89: =+E88+C89-D89 -> 140.21975
E90: =+E89+C90-D90 -> 140.21975
A91: 46164 | B91: 昆仑信托昆银1号 | D91: 100 | E91: =+E90+C91-D91 -> 40.219749
E92: =+E91+C92-D92 -> 40.219749
E93: =+E92+C93-D93 -> 40.219749
E94: =+E93+C94-D94 -> 40.219749
E95: =+E94+C95-D95 -> 40.219749
A96: 46178 | B96: 赎回 | D96: =107*1.05 -> 112.35 | E96: =+E95+C96-D96 -> -72.130251
A97: 46185 | B97: 赎回 | D97: =10.7*1.05 -> 11.235 | E97: =+E96+C97-D97 -> -83.365251
E98: =+E97+C98-D98 -> -83.365251
E99: =+E98+C99-D99 -> -83.365251
E100: =+E99+C100-D100 -> -83.365251
E101: =+E100+C101-D101 -> -83.365251
...

Sheet 元康9号
A2: 日期 | B2: 现金流类型 | C2: 现金流入 | D2: 现金流出 | E2: 期末余额
A3: 46023 | E3: 11
E4: =+E3+C4-D4 -> 11
A5: 46037 | B5: 新增申购 | C5: 200 | E5: =+E4+C5-D5 -> 211
A6: 46038 | B6: 外贸元康1 | D6: 150 | E6: =+E5+C6-D6 -> 61
E7: =+E6+C7-D7 -> 61
A8: 46042 | B8: 新增申购 | C8: 100 | E8: =+E7+C8-D8 -> 161
A9: 46049 | B9: 新增申购 | C9: 233.77734 | E9: =+E8+C9-D9 -> 394.77734
A10: 46052 | B10: 鹏雅119 | D10: 150 | E10: =+E9+C10-D10 -> 244.77734
E11: 245
A12: 46059 | B12: 新增申购 | C12: 995.02982 | E12: =+E11+C12-D12 -> 1240.0298
A13: 46059 | B13: 朗瑞1-5期 | D13: 1100 | E13: =+E12+C13-D13 -> 140.02982 | F13: 涉及新签协议
E14: =+E13+C14-D14 -> 140.02982
E15: =+E14+C15-D15 -> 140.02982
A16: 46066 | B16: 新增申购 | C16: 447.5 | E16: =+E15+C16-D16 -> 587.52982
A17: 46079 | B17: 联储赎回 | D17: 132.25452 | E17: =+E16+C17-D17 -> 455.2753
A18: 46080 | B18: 朗瑞1-5申购 | D18: 200 | E18: =+E17+C18-D18 -> 255.2753
A19: 46085 | B19: 外贸元康盛景1号赎回 | C19: 749.59885 | E19: =+E18+C19-D19 -> 1004.8741
E20: =+E19+C20-D20 -> 1004.8741
A21: 46087 | B21: 赎回 | D21: 102.3732 | E21: =+E20+C21-D21 -> 902.50095
E22: =+E21+C22-D22 -> 902.50095
E23: =+E22+C23-D23 -> 902.50095
A24: 46090 | B24: 朗瑞1-7 | D24: 850 | E24: =+E23+C24-D24 -> 52.500947
A25: 46093 | B25: 申购 | C25: 100 | E25: =+E24+C25-D25 -> 152.50095
A26: 46098 | B26: 赎回外贸1 | C26: 1600.452 | E26: =+E25+C26-D26 -> 1752.9529
E27: =+E26+C27-D27 -> 1752.9529
A28: 46100 | B28: 朗瑞1-7 | D28: 300 | E28: =+E27+C28-D28 -> 1452.9529
E29: =+E28+C29-D29 -> 1452.9529
A30: 46104 | B30: 鹏雅119 | D30: 1000 | E30: =+E29+C30-D30 -> 452.95295
A31: 46108 | B31: 赎回 | D31: 255.3 | E31: =+E30+C31-D31 -> 197.65295
A32: 46112 | B32: 元康盛景1号外贸赎回 | C32: 650.70864 | E32: =+E31+C32-D32 -> 848.36159
A33: 46115 | B33: 管理费 | D33: =13.339862+0.166746+0.166746 -> 13.673354 | E33: =+E32+C33-D33 -> 834.68823
A34: 46119 | B34: 赎回 | D34: 663.48012 | E34: =+E33+C34-D34 -> 171.20811
E35: =+E34+C35-D35 -> 171.20811
E36: =+E35+C36-D36 -> 171.20811
E37: =+E36+C37-D37 -> 171.20811
A38: 46122 | B38: 赎回 | D38: =144*1.0672 -> 153.6768 | E38: =+E37+C38-D38 -> 17.531309
E39: =+E38+C39-D39 -> 17.531309
E40: =+E39+C40-D40 -> 17.531309
E41: =+E40+C41-D41 -> 17.531309
E42: =+E41+C42-D42 -> 17.531309
A43: 46134 | B43: 外贸-元康1号赎回 | C43: 521.1775 | E43: =+E42+C43-D43 -> 538.70881 | F43: 已发
E44: =+E43+C44-D44 -> 538.70881
A45: 46136 | B45: 联储申购 | C45: 204.37 | E45: =+E44+C45-D45 -> 743.07881
E46: =+E45+C46-D46 -> 743.07881
A47: 46140 | B47: 外贸-元康1号赎回 | C47: 1100 | E47: =+E46+C47-D47 -> 1843.0788 | F47: 已发
A48: 46140 | B48: 新疆国信 | D48: 900 | E48: =+E47+C48-D48 -> 943.07881 | F48: 4/28, 新疆国信[266682.SH] ，900w，全价100，协鑫 to 元康盛景9号
A49: 46141 | B49: 元康28号 | D49: 900 | E49: =+E48+C49-D49 -> 43.078809 | F49: 4/28发出
E50: =+E49+C50-D50 -> 43.078809
A51: 46142 | B51: 新疆国信分配 | C51: 16.488 | E51: =+E50+C51-D51 -> 59.566809
E52: =+E51+C52-D52 -> 59.566809
A53: 46150 | B53: 朗瑞1号5期赎回 | C53: 1200 | E53: =+E52+C53-D53 -> 1259.5668 | F53: 4/30发出
E54: =+E53+C54-D54 -> 1259.5668
E55: =+E54+C55-D55 -> 1259.5668
E56: =+E55+C56-D56 -> 1259.5668
A57: 46150 | B57: 联储赎回 | D57: =393.665382+0.503306 -> 394.16869 | E57: =+E56+C57-D57 -> 865.39812
E58: =+E57+C58-D58 -> 865.39812
E59: =+E58+C59-D59 -> 865.39812
A60: 46155 | B60: 元康31号 | D60: 500 | E60: =+E59+C60-D60 -> 365.39812 | F60: 已发
A61: 46157 | B61: 申购 | C61: 200 | E61: =+E60+C61-D61 -> 565.39812
E62: =+E61+C62-D62 -> 565.39812
E63: =+E62+C63-D63 -> 565.39812
E64: =+E63+C64-D64 -> 565.39812
A65: 46163 | B65: 联储赎回 | D65: =383.2*1.08 -> 413.856 | E65: =+E64+C65-D65 -> 151.54212
E66: =+E65+C66-D66 -> 151.54212
E67: =+E66+C67-D67 -> 151.54212
A68: 46168 | B68: 朗瑞1号7期赎回 | C68: 500 | E68: =+E67+C68-D68 -> 651.54212
E69: =+E68+C69-D69 -> 651.54212
A70: 46170 | B70: 联储赎回 | D70: =590*1.08 -> 637.2 | E70: =+E69+C70-D70 -> 14.342121
E71: =+E70+C71-D71 -> 14.342121
E72: =+E71+C72-D72 -> 14.342121
E73: =+E72+C73-D73 -> 14.342121
E74: =+E73+C74-D74 -> 14.342121

Sheet 元康17号
A2: 日期 | B2: 现金流类型 | C2: 现金流入 | D2: 现金流出 | E2: 期末余额
A3: 46023 | E3: 277.92
A4: 45662 | B4: 兑付赎回 | D4: 256 | E4: =E3+C4-D4 -> 21.92
E5: =E4+C5-D5 -> 21.92
A6: 46029 | B6: 新增申购 | C6: 112 | E6: =E5+C6-D6 -> 133.92
A7: 46031 | B7: 新增申购 | C7: 223 | E7: =E6+C7-D7 -> 356.92
A8: 46031 | B8: 申购朗瑞1-5 | D8: 350 | E8: =E7+C8-D8 -> 6.92
E9: 5.8
A10: 46038 | B10: 雪球申购 | C10: 10 | E10: =E9+C10-D10 -> 15.8
A11: 46042 | B11: 赎回元康1 | C11: 350 | E11: =E10+C11-D11 -> 365.8 | F11: 1-16发起
A12: 46045 | B12: 雪球申购 | C12: 152 | E12: =E11+C12-D12 -> 517.8
A13: 46048 | B13: 兑付赎回 | D13: 188 | E13: =E12+C13-D13 -> 329.8
E14: =E13+C14-D14 -> 329.8
A15: 46052 | B15: 雪球申购 | C15: 126 | E15: =E14+C15-D15 -> 455.8
A16: 46055 | B16: 朗瑞1-5 | D16: 100 | E16: =E15+C16-D16 -> 355.8
A17: 46056 | B17: 兑付赎回 | D17: 99 | E17: =E16+C17-D17 -> 256.8
E18: =+E17+C18-D18 -> 256.8
A19: 46059 | B19: 雪球申购 | C19: 161 | E19: =+E18+C19-D19 -> 417.8
A20: 46059 | B20: 朗瑞1-5 | D20: 200 | E20: =+E19+C20-D20 -> 217.8
E21: 214
A22: 46066 | B22: 兑付赎回 | D22: 105 | E22: =+E21+C22-D22 -> 109
A23: 46077 | B23: 雪球申购 | C23: 323 | E23: =+E22+C23-D23 -> 432
E24: =+E23+C24-D24 -> 432
A25: 46080 | B25: 兑付赎回 | D25: =71.28*1.517 -> 108.13176 | E25: =+E24+C25-D25 -> 323.86824
E26: =+E25+C26-D26 -> 323.86824
A27: 46085 | B27: 支付费用 | D27: 2 | E27: =+E26+C27-D27 -> 321.86824
A28: 46085 | B28: 外贸元康盛景1号赎回 | C28: 200 | E28: =+E27+C28-D28 -> 521.86824
A29: 46090 | B29: 新增申购 | C29: 598 | E29: =+E28+C29-D29 -> 1119.8682
A30: 46090 | B30: 兑付赎回 | D30: 259.56 | E30: =+E29+C30-D30 -> 860.30824
E31: =+E30+C31-D31 -> 860.30824
E32: =+E31+C32-D32 -> 860.30824
A33: 46090 | B33: 朗瑞1-7 | D33: 600 | E33: =+E32+C33-D33 -> 260.30824
E34: =+E33+C34-D34 -> 260.30824
A35: 46094 | B35: 兑付赎回 | D35: 207.6 | E35: =+E34+C35-D35 -> 52.70824
A36: 46094 | B36: 雪球申购 | C36: 100 | E36: =+E35+C36-D36 -> 152.70824
A37: 46098 | B37: 外贸元康1赎回 | C37: 2700 | E37: =+E36+C37-D37 -> 2852.7082
A38: 46099 | B38: 朗瑞1-5 | D38: 600 | E38: =+E37+C38-D38 -> 2252.7082
E39: =+E38+C39-D39 -> 2252.7082
E40: =+E39+C40-D40 -> 2252.7082
A41: 46100 | B41: 朗瑞1-7追加 | D41: 1700 | E41: =+E40+C41-D41 -> 552.70824
A42: 46101 | B42: 雪球申购 | C42: 200 | E42: =+E41+C42-D42 -> 752.70824
A43: 46101 | B43: 兑付赎回 | D43: 209.17 | E43: =+E42+C43-D43 -> 543.53824
E44: 545
E45: =+E44+C45-D45 -> 545
A46: 46111 | B46: 兑付赎回 | D46: 208.72 | E46: =+E45+C46-D46 -> 336.28
A47: 46111 | B47: 雪球申购 | C47: 333.112 | E47: =+E46+C47-D47 -> 669.392
E48: =+E47+C48-D48 -> 669.392
A49: 46111 | B49: 朗瑞1-5申购 | D49: 600 | E49: =+E48+C49-D49 -> 69.392
E50: =+E49+C50-D50 -> 69.392
E51: =+E50+C51-D51 -> 69.392
A52: 46115 | B52: 雪球申购 | C52: 718 | E52: =+E51+C52-D52 -> 787.392
A53: 46120 | B53: 外贸元康1赎回 | C53: 1298 | E53: =+E52+C53-D53 -> 2085.392
E54: =+E53+C54-D54 -> 2085.392
A55: 46121 | B55: 朗瑞1-5 | D55: 1000 | E55: =+E54+C55-D55 -> 1085.392
A56: 46122 | B56: 鹏雅119 | D56: 475 | E56: =+E55+C56-D56 -> 610.392
A57: 46122 | B57: 兑付赎回 | D57: =36.8*1.53 -> 56.304 | E57: =+E56+C57-D57 -> 554.088
A58: 46125 | B58: 雪球申购 | C58: 145 | E58: =+E57+C58-D58 -> 699.088
A59: 46125 | B59: 中正达广申购 | C59: 200 | E59: =+E58+C59-D59 -> 899.088
A60: 46127 | B60: 鹏雅119 | D60: 8 | E60: =+E59+C60-D60 -> 891.088
E61: =+E60+C61-D61 -> 891.088
E62: =+E61+C62-D62 -> 891.088
A63: 46129 | B63: 兑付赎回 | D63: 516.8691 | E63: =+E62+C63-D63 -> 374.2189
A64: 46132 | B64: 雪球申购 | C64: 210 | E64: =+E63+C64-D64 -> 584.2189
E65: =+E64+C65-D65 -> 584.2189
A66: 46133 | B66: 新增申购中正达广 | C66: 500 | E66: =+E65+C66-D66 -> 1084.2189
E67: =+E66+C67-D67 -> 1084.2189
E68: =+E67+C68-D68 -> 1084.2189
A69: 46136 | B69: 兑付赎回 | D69: 105.86611 | E69: =+E68+C69-D69 -> 978.35279
E70: =+E69+C70-D70 -> 978.35279
A71: 46136 | B71: 元康盛景28号 | D71: 700 | E71: =+E70+C71-D71 -> 278.35279 | F71: 已发
A72: 46136 | B72: 中正达广申购 | C72: 156 | E72: =+E71+C72-D72 -> 434.35279
A73: 46136 | B73: 雪球申购 | C73: 733 | E73: =+E72+C73-D73 -> 1167.3528
A74: 46140 | B74: 外贸-元康1号赎回 | C74: 800 | E74: =+E73+C74-D74 -> 1967.3528 | F74: 已发
A75: 46140 | B75: 鹏雅119 | D75: 700 | E75: =+E74+C75-D75 -> 1267.3528 | F75: 已发
A76: 46141 | B76: 元康盛景28号 | D76: 300 | E76: =+E75+C76-D76 -> 967.35279 | F76: 已发
E77: =+E76+C77-D77 -> 967.35279
A78: 46148 | B78: 兑付赎回 | D78: =233.180066+0.001585 -> 233.18165 | E78: =+E77+C78-D78 -> 734.17114
A79: 46149 | B79: 雪球申购 | C79: 1054.3 | E79: =+E78+C79-D79 -> 1788.4711
A80: 46150 | B80: 申购外贸-元康1号 | D80: 800 | E80: =+E79+C80-D80 -> 988.47114 | F80: 已发
A81: 46153 | B81: 雪球申购 | C81: 200 | E81: =+E80+C81-D81 -> 1188.4711
A82: 46153 | B82: 支付业绩报酬 | D82: 2.3 | E82: =+E81+C82-D82 -> 1186.1711
A83: 46155 | B83: 元康31号申购 | D83: 1150 | E83: =+E82+C83-D83 -> 36.17114 | F83: 已发
A84: 46157 | B84: 兑付赎回 | D84: 4.95236 | E84: =+E83+C84-D84 -> 31.21878
A85: 46157 | B85: 朗瑞1-7赎回 | C85: 800 | E85: =+E84+C85-D85 -> 831.21878
A86: 46160 | B86: 雪球申购 | C86: 935.7 | E86: =+E85+C86-D86 -> 1766.9188
A87: 46160 | B87: 工鑫34次 | D87: 1506 | E87: =+E86+C87-D87 -> 260.91878 | F87: 2、方向：西藏君集1号to【元康盛景17号】 交易日期：2026年5月18日 债券代码：263612.SH 债券简称：工鑫34次 交易全价：107.571元/百元面值 数量：1400万面值（14万张，14000手） 卖方：西藏信托君集1号集合资金信托计划 卖方询价QQ：2850981264钟振涛 卖方交易员代码：Z07119 买方：【元康盛景17号】 买方询价QQ：【刘靖涛qt3003993899】 买方交易员代码：【Z11825】 约定号：【222】
E88: =+E87+C88-D88 -> 260.91878
A89: 46162 | B89: 工鑫34次 | C89: 1506 | E89: =+E88+C89-D89 -> 1766.9188
A90: 46162 | B90: 24惠民4B | D90: 300 | E90: =+E89+C90-D90 -> 1466.9188 | F90: 5/20，24惠民4B，300W，100.5，国泰海通 樊文娟 to 元康盛景17号 刘靖涛
E91: =+E90+C91-D91 -> 1466.9188
B92: 盛业回购 | D92: 1400 | E92: =+E91+C92-D92 -> 66.91878
E93: =+E92+C93-D93 -> 66.91878
E94: =+E93+C94-D94 -> 66.91878
A95: 46164 | B95: 朗瑞1号5期赎回 | C95: 1200 | E95: =+E94+C95-D95 -> 1266.9188
A96: 46164 | B96: 鹏雅119 | D96: 1100 | E96: =+E95+C96-D96 -> 166.91878 | F96: 521发出
A97: 46164 | B97: 昆仑信托昆银1号 | D97: 100 | E97: =+E96+C97-D97 -> 66.91878
E98: =+E97+C98-D98 -> 66.91878
A99: 46169 | B99: 朗瑞1号5期赎回 | C99: 300 | E99: =+E98+C99-D99 -> 366.91878
A100: 46169 | B100: 元康28号 | D100: 200 | E100: =+E99+C100-D100 -> 166.91878 | F100: 526发出
A101: 46178 | B101: 兑付赎回 | D101: =68*1.6 -> 108.8 | E101: =+E100+C101-D101 -> 58.11878
...

Sheet 朗瑞1_5
A2: 日期 | B2: 现金流类型 | C2: 现金流入 | D2: 现金流出 | E2: 期末余额
A3: 46023 | E3: 234
E4: =+E3+C4-D4 -> 234
A5: 46031 | B5: 元康盛景1号申购 | C5: 600 | E5: =+E4+C5-D5 -> 834
A6: 46031 | B6: 元康17号申购 | C6: 350 | E6: =+E5+C6-D6 -> 1184
A7: 46035 | B7: 元康20赎回 | D7: 1100 | E7: 73
A8: 46036 | B8: 底层回款 | C8: 24 | E8: =+E7+C8-D8 -> 97
E9: =+E8+C9-D9 -> 97
A10: 46041 | B10: 元康20申购 | C10: 2600 | E10: =+E9+C10-D10 -> 2697
E11: =+E10+C11-D11 -> 2697
A12: 46041 | B12: 云信 | D12: =2000*1.074225 -> 2148.45 | E12: =+E11+C12-D12 -> 548.55 | F12: 24美团美玥ABN001次[082481199.IB]，2000w面值，107.4225,1月19日，中信证券 林秋益QT 3004157238 to 外贸信托朗瑞1号5期 孟亚琪
A13: 46042 | B13: 回款 | C13: 30.7 | E13: =+E12+C13-D13 -> 579.25
E14: =+E13+C14-D14 -> 579.25
A15: 46044 | B15: 元康29申购 | C15: 800 | E15: =+E14+C15-D15 -> 1379.25
A16: 46044 | B16: 回款 | C16: 9.1 | E16: =+E15+C16-D16 -> 1388.35
A17: 46044 | B17: 温兴 | D17: =800*1.003 -> 802.4 | E17: =+E16+C17-D17 -> 585.95 | F17: 25温兴1次级[2589143.IB] ，1月22日，800w，100.3，t+0，国泰海通 冉雅婷 to 外贸信托朗瑞1号5期 孟亚琪
E18: =+E17+C18-D18 -> 585.95
A19: 46048 | B19: 泸州 | C19: =1500*100.2683/100 -> 1504.0245 | E19: =+E18+C19-D19 -> 2089.9745
A20: 46048 | B20: 底层兑付 | C20: 87 | E20: =+E19+C20-D20 -> 2176.9745
A21: 46049 | B21: 底层兑付 | C21: 378 | E21: =+E20+C21-D21 -> 2554.9745
A22: 46051 | B22: 元康29号赎回 | D22: 507 | E22: =+E21+C22-D22 -> 2047.9745
A23: 46051 | B23: 元康20号赎回 | D23: 603 | E23: =+E22+C23-D23 -> 1444.9745
A24: 46055 | B24: 元康17号申购 | C24: 100 | E24: =+E23+C24-D24 -> 1544.9745
E25: =+E24+C25-D25 -> 1544.9745
A26: 46056 | B26: 元康20号赎回 | D26: 200 | E26: =+E25+C26-D26 -> 1344.9745
A27: 46059 | B27: 元康9号申购 | C27: 1100 | E27: =+E26+C27-D27 -> 2444.9745
A28: 46059 | B28: 元康22申购 | C28: 1650 | E28: =+E27+C28-D28 -> 4094.9745
A29: 46059 | B29: 元康17号申购 | C29: 200 | E29: =+E28+C29-D29 -> 4294.9745
A30: 46059 | B30: 元康1号赎回 | D30: 1201 | E30: =+E29+C30-D30 -> 3093.9745
A31: 46059 | B31: 25鼎柚3次级 | D31: =1200*1.018227 -> 1221.8724 | E31: =+E30+C31-D31 -> 1872.1021 | F31: 25鼎柚3次级，2589212.IB，2-6, 1200w，101.8227，国泰海通 夏雪 to 外贸信托朗瑞1号5期 孟亚琪
A32: 46059 | B32: 20飞驰建普2C | D32: =1975*0.2926/100 -> 5.77885 | E32: =+E31+C32-D32 -> 1866.3233 | F32: 1、20飞驰建普2C，2089421.IB，1975w，0.2826元/百元面值，2月6日，中诚信托固益人生18号集合资金信托计划殷锋 QT号：2885822426 to 天风证券 唐德婷qt2885078648
E33: 1869 | F33: 2、20飞驰建普2C，2089421.IB，1975w，0.2926元/百元面值，2月6日，外贸信托朗瑞1号5期 孟亚琪2881131472
E34: =+E33+C34-D34 -> 1869
A35: 46062 | B35: 元康1号申购 | C35: 200 | E35: =+E34+C35-D35 -> 2069
A36: 46062 | B36: 24和赢众鑫ABN002优先B | D36: =500*100.20089/100 -> 501.00445 | E36: =+E35+C36-D36 -> 1567.9956 | F36: 1、082480881.IB 24和赢众鑫ABN002优先B，500w 净价100.005 应计利息 0.19589，中信证券 to 外贸信托朗瑞1号5期（孟亚琪，2881131472），发中信证券（林秋益，3004157238）请求
A37: 46062 | B37: 24和赢众鑫ABN002次A | D37: =1350*1.08795 -> 1468.7325 | E37: =+E36+C37-D37 -> 99.26305 | F37: 2、082480882.IB 24和赢众鑫ABN002次A 1350w 净价=全价108.795 中信证券 to 外贸信托朗瑞1号5期（孟亚琪，2881131472），发中信证券（林秋益，3004157238）请求
E38: =+E37+C38-D38 -> 99.26305
A39: 46077 | B39: 回款 | C39: 4.25 | E39: =+E38+C39-D39 -> 103.51305
A40: 46078 | B40: 回款 | C40: 32.5 | E40: =+E39+C40-D40 -> 136.01305
E41: =+E40+C41-D41 -> 136.01305
E42: =+E41+C42-D42 -> 136.01305
A43: 46079 | B43: 回款 | C43: 2435 | E43: =+E42+C43-D43 -> 2571.0131
A44: 46080 | B44: 回款 | C44: 542 | E44: =+E43+C44-D44 -> 3113.0131
A45: 46080 | B45: 元康9号申购 | C45: 200 | E45: =+E44+C45-D45 -> 3313.0131
E46: =+E45+C46-D46 -> 3313.0131
A47: 46080 | B47: 元康盛景30号 | C47: 400 | E47: =+E46+C47-D47 -> 3713.0131
E48: =+E47+C48-D48 -> 3713.0131
E49: =+E48+C49-D49 -> 3713.0131
E50: =+E49+C50-D50 -> 3713.0131
A51: 46080 | B51: 元康盛景1号赎回 | D51: 201 | E51: =+E50+C51-D51 -> 3512.0131
A52: 46083 | B52: 16中盈1C | D52: =6000*21.9792% -> 1318.752 | E52: =+E51+C52-D52 -> 2193.2611 | F52: 2/27 16中盈1C 60万份（6000w面值） 21.9792元 天风to 外贸信托朗瑞1号5期（孟亚琪，2881131472）
B53: 16中盈2C | D53: =4500*27.6614% -> 1244.763 | E53: =+E52+C53-D53 -> 948.49805 | F53: 2/27 16中盈2C 45万份（4500万面值） 27.6614元 天风 to 外贸信托朗瑞1号5期（孟亚琪，2881131472）
A54: 46084 | B54: 元康盛景1号赎回 | D54: 952 | E54: =+E53+C54-D54 -> -3.50195
E55: =+E54+C55-D55 -> -3.50195
A56: 46085 | B56: 元康盛景29号申购 | C56: 5 | E56: =+E55+C56-D56 -> 1.49805
A57: 46091 | B57: 慧聚领航1号 | C57: =慧聚领航1号!D6 -> 300 | E57: =+E56+C57-D57 -> 301.49805 | I57: 25锦新小微ABN002次 | J57: =XIRR(J58:J59,I58:I59) -> 0.058415356
E58: =+E57+C58-D58 -> 301.49805 | I58: 45820 | J58: -100
A59: 46094 | B59: 元康20号追加 | C59: 750 | E59: =+E58+C59-D59 -> 1051.498 | I59: 46094 | J59: =-J58*(1+5.8%*(I59-I58)/365) -> 104.35397
A60: 46094 | B60: 25锦新小微ABN002次 | D60: 1044 | E60: =+E59+C60-D60 -> 7.49805
A61: 46099 | B61: 元康17号申购 | C61: 600 | E61: =+E60+C61-D61 -> 607.49805
A62: 46099 | B62: 20招银和家7C | D62: =400*141.9% -> 567.6 | E62: 59 | F62: 3-18 20招银和家7C（2089441.IB） 400万份（40000万面值） 141.9元 国泰海通 冉雅婷 2881971956 to 外贸信托朗瑞1号5期（孟亚琪，2881131472）
A63: 46100 | B63: 兑付 | C63: 28 | E63: 69.4
A64: 46101 | B64: 25锦新小微ABN002次兑付 | C64: =1000*104.4652% -> 1044.652 | E64: =+E63+C64-D64 -> 1114.052
A65: 46104 | B65: 元康盛景20号赎回 | D65: 1000 | E65: =+E64+C65-D65 -> 114.052
A66: 46104 | B66: 兑付回款 | C66: 3.8 | E66: =+E65+C66-D66 -> 117.852
A67: 46104 | B67: 元康20申购 | C67: 1300 | E67: =+E66+C67-D67 -> 1417.852
A68: 46104 | B68: 元康1申购 | C68: 700 | E68: =+E67+C68-D68 -> 2117.852
A69: 46104 | B69: 元康29号申购 | C69: 300 | E69: =+E68+C69-D69 -> 2417.852
A70: 46105 | B70: 26浩澜ABN001次[082680155.IB] | D70: 2021 | E70: =+E69+C70-D70 -> 396.852 | F70: 3/24， 26浩澜ABN001次[082680155.IB] 2000W 净价/全价 101.08 xx to 外贸信托朗瑞1号5期 孟亚琪qt 2881131472
A71: 46105 | B71: 24易鑫恒通ABN001优先B | D71: 305 | E71: 90.3 | F71: 3/24， 082481523.IB 24易鑫恒通ABN001优先B 300W 净价 101.36 国泰海通 to 外贸信托朗瑞1号5期 孟亚琪qt 2881131472
A72: 46107 | B72: 回款 | C72: 206 | E72: =+E71+C72-D72 -> 296.3
A73: 46107 | B73: 温州回款 | C73: 605 | E73: =+E72+C73-D73 -> 901.3
E74: =+E73+C74-D74 -> 901.3
A75: 46108 | B75: 24和赢众鑫ABN001优先B | C75: 450 | E75: 1386
A76: 46111 | B76: 24美团美玥ABN001次 | C76: 2173.5 | E76: =+E75+C76-D76 -> 3559.5
A77: 46111 | B77: 元康17追加 | C77: 600 | E77: =+E76+C77-D77 -> 4159.5
A78: 46111 | B78: 元康20号赎回 | D78: 3622.0022 | E78: =+E77+C78-D78 -> 537.4978 | I78: 25美团美好ABN002次 | J78: =XIRR(J79:J81,I79:I81) -> 0.040026757
E79: =+E78+C79-D79 -> 537.4978 | I79: 45994 | J79: -102.105
A80: 46121 | B80: 元康17 | C80: 1000 | E80: =+E79+C80-D80 -> 1537.4978 | I80: 46122 | J80: 103.52
A81: 46121 | B81: 滴滴启橙 | D81: 475 | E81: =+E80+C81-D81 -> 1062.4978 | F81: 4/9日缴款，26启橙2号ABN001次（082601458.IB）475w，6%单利，朗瑞1号5期缴款
A82: 46122 | B82: 鼎柚25-3 | D82: =400*101.827/100 -> 407.308 | E82: =+E81+C82-D82 -> 655.1898 | F82: 25鼎柚3次级[2589212.IB]，400w，101.827，4月10日，国泰海通 冉雅婷 2881971956 to 外贸信托朗瑞1号5期 孟亚琪qt 2881131472
A83: 46122 | B83: 25美团美好ABN002次 | D83: =580*103.52/100 -> 600.416 | E83: =+E82+C83-D83 -> 54.7738 | F83: 25美团美好ABN002次[082580682.IB]，580w，103.52，4月10日，国泰海通 冉雅婷 2881971956 to 外贸信托朗瑞1号5期 孟亚琪qt 2881131472
E84: =+E83+C84-D84 -> 54.7738
A85: 46125 | B85: 税费 | D85: 6.3 | E85: =+E84+C85-D85 -> 48.4738
A86: 46129 | B86: 深能源兑付 | C86: 65 | E86: =+E85+C86-D86 -> 113.4738
A87: 46132 | B87: 和赢蔚能兑付 | C87: 29.79 | E87: =+E86+C87-D87 -> 143.2638
A88: 46133 | B88: 元康22号申购 | C88: 2200 | E88: =+E87+C88-D88 -> 2343.2638
A89: 46133 | B89: 元康盛景1号赎回 | D89: 801 | E89: =+E88+C89-D89 -> 1542.2638 | F89: 已发
A90: 46133 | B90: 和赢蔚能ABN002、浩悦兑付 | C90: =14.8+4.25 -> 19.05 | E90: =+E89+C90-D90 -> 1561.3138
E91: =+E90+C91-D91 -> 1561.3138 | F91: 已发 | G91: =+D91/1.4039 -> 0
A92: 46139 | B92: 兑付回款 | C92: 815.6 | E92: =+E91+C92-D92 -> 2376.9138
A93: 46139 | B93: 慧聚领航1号赎回 | D93: 200 | E93: =+E92+C93-D93 -> 2176.9138
A94: 46139 | B94: 25弗迪租赁ABN001次级(绿色) | D94: =1900*1.005 -> 1909.5 | E94: =+E93+C94-D94 -> 267.4138 | F94: 4/27+0,25弗迪租赁ABN001次级(绿色)[082580900.IB],1900w,全价100.5035 中金 李欣月3007455122 to 外贸信托朗瑞1号5期 孟亚琪
E95: =+E94+C95-D95 -> 267.4138
E96: =+E95+C96-D96 -> 267.4138
E97: =+E96+C97-D97 -> 267.4138 | G97: 给鹏雅119 | H97: 4-24估值 | K97: 4/28估值 | L97: 起息日 | M97: 平价价格
A98: 46140 | B98: 24京东东裕3ABN002次 | C98: 741.0872 | E98: =+E97+C98-D98 -> 1008.501 | F98: 4/28，24京东东裕3ABN002次[082480853.IB]，700w，105.8696，外贸信托 孟亚琪 2881131472 to 中信证券 | G98: 70000 | H98: 105.811 | I98: 46140 | J98: 0.058 | K98: =ROUND(H98+J98/365*4*100,4) -> 105.8746 | L98: 45518 | M98: =100*(1+J98*(I98-L98)/365)-4 -> 105.88384 | N98: =+K98+0.005 -> 105.8796 | O98: =+N98-0.01 -> 105.8696
A99: 46140 | B99: 24东裕5仲裕ABN001次 | C99: 2093.132 | E99: =+E98+C99-D99 -> 3101.633 | F99: 4/28，24东裕5仲裕ABN001次[082481516.IB]，2000w，104.6566，外贸信托 孟亚琪 2881131472 to 中信证券 | G99: 200000 | H99: 104.5991 | I99: 46140 | J99: 0.057 | K99: =ROUND(H99+J99/365*4*100,4) -> 104.6616 | L99: 45596 | M99: =100*(1+J99*(I99-L99)/365)-4 -> 104.49534 | N99: =+K99+0.005 -> 104.6666 | O99: =+N99-0.01 -> 104.6566
E100: =+E99+C100-D100 -> 3101.633
A101: 46141 | B101: 蔚能ABN | D101: 2000 | E101: =+E100+C101-D101 -> 1101.633 | F101: 已发
...

Sheet 朗瑞1_7
A2: 日期 | B2: 现金流类型 | C2: 现金流入 | D2: 现金流出 | E2: 期末余额
A3: 46036 | E3: 73
E4: =+E3+C4-D4 -> 73
A5: 46090 | B5: 元康1号申购 | C5: 550 | E5: =+E4+C5-D5 -> 623
A6: 46090 | B6: 元康20号申购 | C6: 2200 | E6: =+E5+C6-D6 -> 2823 | F6: 等等一些二级交易谈判
A7: 46090 | B7: 元康17申购 | C7: 600 | E7: =+E6+C7-D7 -> 3423
A8: 46090 | B8: 元康9号申购 | C8: 850 | E8: =+E7+C8-D8 -> 4273
A9: 46090 | B9: 元康30号申购 | C9: 340 | E9: =+E8+C9-D9 -> 4613
A10: 46091 | B10: 26锦新小微ABN003次 | D10: 3000 | E10: =+E9+C10-D10 -> 1613 | F10: 1、26锦新小微ABN003次，082680149，3月10日缴款，1000w，中金分销，朗瑞1-7缴款，单利5.7%，期限10个月左右非现
E11: =+E10+C11-D11 -> 1613 | F11: 2、26锦新小微ABN003次，082680149，3月10日缴款，2000w，自持部分，朗瑞1-7缴款，单利5.7%，期限10个月左右非现
E12: =+E11+C12-D12 -> 1613
E13: =+E12+C13-D13 -> 1613
E14: =+E13+C14-D14 -> 1613 | F14: 从外贸元康盛景1号赎回的资金
A15: 46100 | B15: 元康17号 | C15: 1700 | E15: =+E14+C15-D15 -> 3313
A16: 46100 | B16: 元康9号申购 | C16: 300 | E16: =+E15+C16-D16 -> 3613
E17: =+E16+C17-D17 -> 3613
A18: 46104 | B18: 蔚能ABN次A | D18: 3500 | E18: =+E17+C18-D18 -> 113 | F18: 26蔚能电池ABN001BC次A(绿色)，082680178，3500w，3-23缴款，3-24起息，9%单利，朗瑞1号7期ideal孟亚琪
A19: 46104 | B19: 蔚能优先A1 | D19: 100 | E19: =+E18+C19-D19 -> 13
A20: 46107 | B20: 回款 | C20: 16.5 | E20: =+E19+C20-D20 -> 29.5
A21: 46119 | B21: 元康20号申购 | C21: 2100 | E21: =+E20+C21-D21 -> 2129.5
A22: 46120 | B22: 慧聚领航 | C22: 850 | E22: =+E21+C22-D22 -> 2979.5 | I22: 24京能3号ABN001次 | J22: =XIRR(J23:J29,I23:I29) -> 0.085686377
E23: =+E22+C23-D23 -> 2979.5 | I23: 45653 | J23: -100
A24: 46120 | B24: 京能 | D24: =2950*100.03% -> 2950.885 | E24: =+E23+C24-D24 -> 28.615 | F24: 2026-4-8，24京能3号ABN001次 (082482325.IB)，2950w，100.020元，【】 to 朗瑞1号7期 孟亚琪 2881131472 | I24: 45737 | J24: 1.956164
A25: 46142 | B25: 支付费用 | D25: 7.7 | E25: =+E24+C25-D25 -> 20.915 | I25: 45821 | J25: 1.9561644
A26: 46157 | B26: 元康20申购 | C26: 800 | E26: =+E25+C26-D26 -> 820.915 | F26: 已发 | I26: 45896 | J26: 1.7465753
A27: 46157 | B27: 元康17赎回 | D27: 800 | E27: =+E26+C27-D27 -> 20.915 | F27: 已发 | I27: 45996 | J27: 2.3287671
E28: =+E27+C28-D28 -> 20.915 | I28: 46108 | J28: 2.6082192 | L28: 票面 | M28: =-J23*(1+8.5%*(I29-I23)/365)-SUM(J24:J28) -> 100.27945
E29: =+E28+C29-D29 -> 20.915 | H29: 0.085 | I29: 46120 | J29: 100.02 | L29: 估值 | M29: 100.2231
E30: =+E29+C30-D30 -> 20.915
A31: 46168 | B31: 元康20号申购 | C31: 500 | E31: =+E30+C31-D31 -> 520.915
A32: 46168 | B32: 元康9号赎回 | D32: 500 | E32: =+E31+C32-D32 -> 20.915 | F32: 521发出，522申请
E33: =+E32+C33-D33 -> 20.915
E34: =+E33+C34-D34 -> 20.915
E35: =+E34+C35-D35 -> 20.915

Sheet 朗瑞1_8
A2: 日期 | B2: 现金流类型 | C2: 现金流入 | D2: 现金流出 | E2: 期末余额
A3: 46023 | E3: 2020
E4: =+E3+C4-D4 -> 2020
A5: 46031 | B5: 元康29申购 | C5: 1200 | E5: =E4+C5-D5 -> 3220
A6: 46031 | B6: 22臻金3C | D6: =71.245*3000/100 -> 2137.35 | E6: =E5+C6-D6 -> 1082.65 | F6: 1. 方向：百瑞君集1-3 to 中信证券 交易日期：2026年1月9日 债券代码：2289370.IB 债券简称：22臻金3C 交易净价：71.239元/百元面值 交易数量：3000万面值（30万张，3万手） 卖方：百瑞信托君集1号集合资金信托计划 卖方询价QQ：杨越 3004259924 买方：中信证券 买方询价留痕QQ：【3004413757 张正昊】 2. 方向：中信证券 to 外贸信托朗瑞1号8期 交易日期：2026年1月9日 债券代码：2289370.IB 债券简称：22臻金3C 交易净价：71.245元/百元面值 交易数量：3000万面值（30万张，3万手） 卖方：中信证券 卖方询价留痕QQ：【3004413757 张正昊】 买方：外贸信托朗瑞1号集合资金信托计划 买方询价QQ：孟亚琪 2881131472
E7: =E6+C7-D7 -> 1082.65
A8: 46034 | B8: 25臻金4C | D8: =1000*100.644/100 -> 1006.44 | E8: =E7+C8-D8 -> 76.21 | F8: 25臻金4C[2589445.IB] ,1000w,100.644, 1月12日，t+0, 中金 王东岳 to 外贸信托朗瑞1号8期，孟亚琪
A9: 46038 | B9: 元康29申购 | C9: 500 | E9: =+E8+C9-D9 -> 576.21
E10: =+E9+C10-D10 -> 576.21
A11: 46038 | B11: 代持买回 | D11: 147 | E11: =+E10+C11-D11 -> 429.21 | F11: 1、24臻粹3C[2489229.IB]，7w，全价57.1,1月16日，t+0，国泰海通 冉雅婷 to 外贸信托朗瑞1号8期 孟亚琪
E12: =+E11+C12-D12 -> 429.21 | F12: 2、24邮盈惠兴4C[2489188.IB]，400w，全价35.9,1月16日，t+0，国泰海通 冉雅婷 to 外贸信托朗瑞1号8期 孟亚琪
A13: 46041 | B13: 代持买回 | D13: 67 | E13: 357 | F13: 3、24邮盈惠兴5C[2489255.IB]，140w，全价47.9555, 1月19日，t+0，银河 赵恩聪 to 外贸信托朗瑞1号8期 孟亚琪
A14: 46044 | B14: 元康29申购追加 | C14: 2500 | E14: =+E13+C14-D14 -> 2857
A15: 46044 | B15: 代持买回 | D15: 2507 | E15: =+E14+C15-D15 -> 350 | F15: 23工元至诚8C[2389487.IB] ，1300w，126.90,1月22日，t+0，国泰海通 冉雅婷 to 外贸信托朗瑞1号8期 孟亚琪 | Q15: 23工元至诚8C 2026/1/26兑付后超集中度，2026/1/26（下周一）前至少要减持1300万
E16: =+E15+C16-D16 -> 350 | F16: 25橙益4C[2589087.IB] ，130w，108.12,1月22日，t+0，国泰海通 冉雅婷 to 外贸信托朗瑞1号8期 孟亚琪 | Q16: 25兴瑞1C 2026/1/26兑付后超集中度，2026/1/26（下周一）前至少要减持180万
E17: =+E16+C17-D17 -> 350 | F17: 25兴瑞1C[2589025.IB] ，180w，108.48,1月22日，t+0，国泰海通 冉雅婷 to 外贸信托朗瑞1号8期 孟亚琪 | Q17: 25橙益4C 需要减持130W
E18: =+E17+C18-D18 -> 350 | F18: 24浦鑫归航8C[2489436.IB]，500w，104.29,1月22日，t+0，国泰海通 冉雅婷 to 外贸信托朗瑞1号8期 孟亚琪 | Q18: 还有24浦鑫归航8C，超了350w
A19: 46045 | B19: 底层回款 | C19: 435 | E19: =+E18+C19-D19 -> 785
A20: 46045 | B20: 买券 | D20: =42*1.0289 -> 43.2138 | E20: =+E19+C20-D20 -> 741.7862 | F20: 25福鑫4C[2589218.IB],42w,102.8904,1月23日，国泰海通田飞凡 to 外贸信托朗瑞1号8期 孟亚琪2881131472
A21: 46048 | B21: 底层回款 | C21: 3701 | E21: =+E20+C21-D21 -> 4442.7862
A22: 46050 | B22: 底层回款 | C22: 11 | E22: =+E21+C22-D22 -> 4453.7862
A23: 46050 | B23: 24鸿富5C | C23: 270 | E23: =+E22+C23-D23 -> 4723.7862
A24: 46051 | B24: 24鸿富5C | C24: 260 | E24: =+E23+C24-D24 -> 4983.7862 | Q24: 交易日期 | R24: 交易价格 | S24: 交易金额 | T24: 补收益
A25: 46052 | B25: 25建欣8C | D25: =417*1.078479 -> 449.72574 | E25: =+E24+C25-D25 -> 4534.0605 | F25: 25建欣8C,2589233.IB，1-30, t+0，417w，107.8479，银河证券 刘成立 2853268300 to 外贸信托朗瑞1号 孟亚琪 | O25: 25建欣8C | P25: 417 | Q25: 46052 | R25: =P36 -> 107.84795 | S25: =+R25*P25*100 -> 4497259.3 | U25: 25建欣8C,2589233.IB，1-30, t+0，417w，107.8479，银河证券 刘成立 2853268300 to 外贸信托朗瑞1号 孟亚琪
E26: =+E25+C26-D26 -> 4534.0605 | O26: 25工元至诚普银3C | P26: 182 | Q26: 46056 | R26: =+S36 -> 113.41471 | S26: =+R26*P26*100 -> 2064147.8 | U26: 25工元至诚普银3C，2589168.IB，2-3，t+0，182w，113.4147，银河证券 刘成立 2853268300 to 粤财信托鹏雅10号120期 xxx
A27: 46052 | B27: 25建欣11C | D27: 731 | E27: =+E26+C27-D27 -> 3803.0605 | F27: 25建欣11C，2589247.IB，1-30，t+0,700w，104.5375，信达证券 3007461572 张诗玥 to 天风证券 唐德婷2885078648 | O27: 25建欣11C | P27: 700 | Q27: 46052 | R27: =+P40 -> 104.5375 | S27: =+R27*P27*100 -> 7317625 | U27: 25建欣11C，2589247.IB，1-30，t+0,700w，104.5375，信达证券 3007461572 张诗玥 to 天风证券 唐德婷2885078648 | AD27: 25建欣11C，2589247.IB，1-30，t+0,700w，104.5575，天风证券 唐德婷2885078648 to 外贸信托朗瑞1号 孟亚琪
E28: =+E27+C28-D28 -> 3803.0605 | F28: 25建欣11C，2589247.IB，1-30，t+0,700w，104.5575，天风证券 唐德婷2885078648 to 外贸信托朗瑞1号 孟亚琪 | O28: 24中誉至诚9C | P28: 68 | Q28: 46057 | R28: =S41 -> 25.57 | S28: =+R28*P28*100 -> 173876
A29: 46052 | B29: 24建欣6C | D29: 81.32 | E29: =+E28+C29-D29 -> 3721.7405 | F29: 24建欣6C，2489200.IB，1-30，t+0,76w，106.96，国泰海通 冉雅婷 to 外贸信托朗瑞1号 孟亚琪 | O29: 24建欣6C | P29: 76 | Q29: 46052 | R29: =+Q57 -> 106.96 | S29: =+R29*P29*100 -> 812896 | T29: =+(P57-Q57)*P29*100 -> 13224 | U29: 24建欣6C，2489200.IB，1-30，t+0,76w，106.96，国泰海通 冉雅婷 to 外贸信托朗瑞1号 孟亚琪
A30: 46052 | B30: 24橙益17C | D30: 176 | E30: =+E29+C30-D30 -> 3545.7405 | F30: 24橙益17C，2489414.IB，1-30，t+0，182w,97.22,国泰海通 冉雅婷 to 外贸信托朗瑞1号 孟亚琪 | O30: 24橙益17C | P30: 182 | Q30: 46052 | R30: =+U57 -> 97.22 | S30: =+R30*P30*100 -> 1769404 | T30: =+(T57-U57)*P30*100 -> 20020 | U30: 24橙益17C，2489414.IB，1-30，t+0，182w,97.22,国泰海通 冉雅婷 to 外贸信托朗瑞1号 孟亚琪
A31: 46055 | B31: 25浦鑫归航9C | D31: =200*1.00691 -> 201.382 | E31: =+E30+C31-D31 -> 3344.3585 | F31: 2/2 2589513.IB 25浦鑫归航9C 200W 100.691 天风证券 2850302347TO 外贸信托-朗瑞1号8期 孟亚琪
E32: =+E31+C32-D32 -> 3344.3585
E33: =+E32+C33-D33 -> 3344.3585
E34: =+E33+C34-D34 -> 3344.3585 | O34: 25建欣8C | P34: =XIRR(P35:P36,O35:O36) -> 0.050571117 | R34: 25工元至诚普银3C | S34: =XIRR(S35:S36,R35:R36) -> 0.050974563
A35: 46057 | B35: 24惠元8C | D35: =1500*1.121248 -> 1681.872 | E35: =+E34+C35-D35 -> 1662.4865 | F35: 1、24惠元8C，2489337.IB，1500w，112.0948，2月5日，T+0，银河证券 赵恩聪 to 天风 唐德婷2885078648 | O35: 45854 | P35: -105 | R35: 45973 | S35: -112.1397
A36: 46057 | B36: 24工元至诚4C | D36: =1000*1.171441 -> 1171.441 | E36: =+E35+C36-D36 -> 491.04546 | F36: 2、24惠元8C，2489337.IB，1500w，112.1248，2月5日，T+0，天风 唐德婷2885078648 to 外贸信托朗瑞1号8期 孟亚琪2881131472 | O36: =Q25 -> 46052 | P36: =-P35*(1+5%/365*(O36-O35)) -> 107.84795 | R36: =+Q26 -> 46056 | S36: =-S35*(1+5%/365*(R36-R35)) -> 113.41471
E37: =+E36+C37-D37 -> 491.04546 | F37: 3、24工元至诚4C，2489376.IB，1000w，117.1441, 2月5日，T+0，银河证券 赵恩聪 to 天风 唐德婷2885078648
E38: =+E37+C38-D38 -> 491.04546 | F38: 4、24工元至诚4C，2489376.IB，1000w，117.1441, 2月5日，T+0，天风 唐德婷2885078648 to 外贸信托朗瑞1号8期 孟亚琪2881131472 | O38: 25建欣11C | P38: =XIRR(P39:P40,O39:O40) -> 0.049953046 | R38: 24中誉至诚9C | S38: =XIRR(S39:S41,R39:R41) -> 0.049961779
E39: =+E38+C39-D39 -> 491.04546 | O39: 45868 | P39: -102 | R39: 45656 | S39: -101
A40: 46059 | B40: 22臻金1C | D40: =100*0.25 -> 25 | E40: =+E39+C40-D40 -> 466.04546 | F40: 22臻金1C，2289055.IB，100w，25元/百元面值，2月6日，天风证券 唐德婷qt2885078648 to 外贸信托朗瑞1号8期 孟亚琪2881131472 | O40: =+Q27 -> 46052 | P40: 104.5375 | R40: 46048 | S40: 80.89
A41: 46059 | B41: 25中誉至诚3C | D41: 249 | E41: =+E40+C41-D41 -> 217.04546 | F41: 25中誉至诚3C,2589127.IB,238w,104.458,2月6日，国泰海通 夏雪 to 外贸信托朗瑞1号8期 孟亚琪 | R41: =Q28 -> 46057 | S41: 25.57
A42: 46077 | B42: 回款 | C42: 121 | E42: =+E41+C42-D42 -> 338.04546
A43: 46079 | B43: 卖出25浦鑫归航9C | C43: 201 | E43: =+E42+C43-D43 -> 539.04546 | F43: 2/26 2589513.IB 25浦鑫归航9C 200W 全价100.9719 外贸信托-朗瑞1号8期 孟亚琪 T0 中金（黄兴）QT号：2850290224
A44: 46079 | B44: 回款 | C44: 1252 | E44: =+E43+C44-D44 -> 1791.0455
A45: 46079 | B45: 22兴瑞4优先 | D45: 201.9 | E45: =+E44+C45-D45 -> 1589.1455 | F45: 2289264.IB，22兴瑞4优先，1000w，净价20.23,2月26日，中信证券杨赟 to 外贸信托朗瑞1号8期 孟亚琪
E46: =+E45+C46-D46 -> 1589.1455
E47: 1599
A48: 46084 | B48: 元康29号提取赎回 | D48: 1205 | E48: =+E47+C48-D48 -> 394
A49: 46084 | B49: 25兴瑞1C | D49: =310*0.518511 -> 160.73841 | E49: =+E48+C49-D49 -> 233.26159 | F49: 2589025.IB 25兴瑞1C 310W 净价/全价 51.8511 天风证券 TO外贸信托朗瑞1号8期 孟亚琪qt 2881131472
E50: =+E49+C50-D50 -> 233.26159
A51: 46093 | B51: 25兴瑞1C | C51: =310*51.915% -> 160.9365 | E51: =+E50+C51-D51 -> 394.19809 | F51: 3/12 2589025.IB 25兴瑞1C 310W 净价/全价 51.9150 外贸信托朗瑞1号8期( 孟亚琪qt 2881131472） TO中金黄兴
A52: 46094 | B52: 24惠元8C | C52: 1737.8 | E52: =+E51+C52-D52 -> 2131.9981 | F52: 3/13+0, 24惠元8C[2489337.IB] ，1545w，112.48，外贸信托朗瑞1号8期 孟亚琪qt 2881131472 to 华林证券（信唐 郁正良 2885267029）
A53: 46094 | B53: 新增申购 | C53: 100 | E53: =+E52+C53-D53 -> 2231.9981
E54: =+E53+C54-D54 -> 2231.9981 | O54: 24建欣6C | P54: =XIRR(P55:P57,O55:O57) -> 0.049957374 | Q54: =XIRR(Q55:Q57,O55:O57) -> 0.03999975 | S54: 24橙益17C | T54: =XIRR(T55:T57,S55:S57) -> 0.049985895 | U54: =XIRR(U55:U57,S55:S57) -> 0.040009984
A55: 46094 | B55: 元康29号赎回 | D55: 2198.8 | E55: =+E54+C55-D55 -> 33.19809 | I55: 22臻金2C | K55: =510*0.37 -> 188.7 | O55: 45471 | P55: -107 | Q55: =+P55 -> -107 | S55: 45651 | T55: -100 | U55: =+T55 -> -100
E56: =+E55+C56-D56 -> 33.19809 | I56: 21工元至诚5C | K56: =6000*0.52 -> 3120 | O56: 46048 | P56: 6.93 | Q56: =+P56 -> 6.93 | S56: 46048 | T56: 7.1811 | U56: =+T56 -> 7.1811
A57: 46101 | B57: 回款 | C57: 33.7 | E57: =+E56+C57-D57 -> 66.89809 | I57: 20中誉2C | K57: =930*0.02 -> 18.6 | O57: =+Q29 -> 46052 | P57: 108.7 | Q57: 106.96 | S57: =+Q30 -> 46052 | T57: 98.32 | U57: 97.22
A58: 46104 | B58: 回款 | C58: 90 | E58: =+E57+C58-D58 -> 156.89809 | I58: 23中誉1C | K58: =1794*0.64 -> 1148.16
E59: =+E58+C59-D59 -> 156.89809
E60: =+E59+C60-D60 -> 156.89809
E61: =+E60+C61-D61 -> 156.89809
A62: 46107 | B62: 回款 | C62: 1648 | E62: =+E61+C62-D62 -> 1804.8981 | O62: 24惠元8C | P62: =XIRR(P63:P64,O63:O64) -> 0.051013604 | S62: 24工元至诚4C | T62: =XIRR(T63:T64,S63:S64) -> 0.051013604
A63: 46107 | B63: 苏誉缴款 | D63: =74+43 -> 117 | E63: =+E62+C63-D63 -> 1687.8981 | F63: 26苏誉1优先，代码2689037，74w，2.05%，3-26缴款，ideal分销外贸信托朗瑞1号8期，孟亚琪； | O63: 45986 | P63: -111 | S63: 45986 | T63: -116
A64: 46111 | B64: 元康29赎回 | D64: 1663 | E64: =+E63+C64-D64 -> 24.89809 | F64: 26苏誉1C，代码2689038，43w，100元，3-26缴款，ideal分销外贸信托朗瑞1号8期，孟亚琪； | O64: 46058 | P64: =-P63*(1+5%/365*(O64-O63)) -> 112.09479 | S64: 46058 | T64: =-T63*(1+5%/365*(S64-S63)) -> 117.14411
E65: =+E64+C65-D65 -> 24.89809
A66: 46122 | B66: 慧聚领航申购 | C66: =慧聚领航1号!D23 -> 30 | E66: 53.3 | O66: 日期 | P66: 0.06933268 | S66: 朗瑞1号8期
E67: =+E66+C67-D67 -> 53.3 | O67: 45618 | P67: -103 | S67: 日期 | T67: =XIRR(T68:T71,S68:S71) -> 0.13191703
A68: 46133 | B68: 慧聚领航 | C68: 600 | E68: =+E67+C68-D68 -> 653.3 | O68: 46086 | P68: =-P67*(1+7%*(O68-O67)/365) -> 112.2446 | Q68: 113.53 | S68: 45905 | T68: -16539225
A69: 46133 | B69: 25惠元6C | D69: 540 | E69: =+E68+C69-D69 -> 113.3 | F69: 4/21,+0, 25惠元6C[2589190.IB]，646w，83.6051，银河证券 xx to 外贸信托朗瑞1号8期 孟亚琪2881131472 | S69: 45986 | T69: 16650000
E70: =+E69+C70-D70 -> 113.3 | S70: 46058 | T70: -16818720 | U70: -112.1248
A71: 46134 | B71: 25福鑫4C | D71: =40*105.7726/100 -> 42.30904 | E71: =+E70+C71-D71 -> 70.99096 | F71: 4/22，t+0，25福鑫4C[2589218.IB]，40w，105.7726，国泰海通xx to 外贸信托朗瑞1号8期 孟亚琪2881131472 | S71: 46086 | T71: 17341791
E72: =+E71+C72-D72 -> 70.99096
A73: 46135 | B73: 回款 | C73: 384.7 | E73: =+E72+C73-D73 -> 455.69096
E74: =+E73+C74-D74 -> 455.69096 | N74: 补优先贴息
A75: 46135 | B75: 25橙益22C | D75: 20.557 | E75: =+E74+C75-D75 -> 435.13396 | F75: 4/23, 25橙益22C[2589366.IB]，20w，102.785，国泰海通 冉雅婷 to 外贸信托朗瑞1号8期 孟亚琪2881131472 | N75: =(100-99.85)*35/100+(100-99.813)*500/100 -> 0.9875
A76: 46135 | B76: 25橙益23C | D76: 217.87 | E76: =+E75+C76-D76 -> 217.26396 | F76: 4/23, 25橙益23C[2589368.IB]，200w，108.935，国泰海通 冉雅婷 to 外贸信托朗瑞1号8期 孟亚琪2881131472 | L76: 价格 | P76: 调整后价格 | Q76: 交易规模
A77: 46135 | B77: 25工元至诚惠银2C | D77: 110.575 | E77: =+E76+C77-D77 -> 106.68896 | F77: 4/23, 25工元至诚惠银2C[2589222.IB]，100w，110.575，国泰海通 冉雅婷 to 外贸信托朗瑞1号8期 孟亚琪2881131472 | I77: 2589366.IB | J77: 25橙益22C | K77: 20 | L77: =+K88 -> 102.55 | M77: =+L77*K77/100 -> 20.51 | N77: 0.04702381 | O77: =+M77+N77 -> 20.557024 | P77: =ROUND(+O77/K77*100,3) -> 102.785 | Q77: =+P77*K77/100 -> 20.557 | R77: ="4/23, "&J77&"["&I77&"]，"&K77&"w，"&P77&"，国泰海通 冉雅婷 to 外贸信托朗瑞1号8期 孟亚琪2881131472" -> 4/23, 25橙益22C[2589366.IB]，20w，102.785，国泰海通 冉雅婷 to 外贸信托朗瑞1号8期 孟亚琪2881131472
E78: =+E77+C78-D78 -> 106.68896 | I78: 2589368.IB | J78: 25橙益23C | K78: 200 | L78: =+M88 -> 108.7 | M78: =+L78*K78/100 -> 217.4 | N78: 0.4702381 | O78: =+M78+N78 -> 217.87024 | P78: =ROUND(+O78/K78*100,3) -> 108.935 | Q78: =+P78*K78/100 -> 217.87 | R78: ="4/23, "&J78&"["&I78&"]，"&K78&"w，"&P78&"，国泰海通 冉雅婷 to 外贸信托朗瑞1号8期 孟亚琪2881131472" -> 4/23, 25橙益23C[2589368.IB]，200w，108.935，国泰海通 冉雅婷 to 外贸信托朗瑞1号8期 孟亚琪2881131472
A79: 46135 | B79: 25浦鑫归航5优先 | D79: 96.1423 | E79: =+E78+C79-D79 -> 10.54666 | F79: 4/23, 25浦鑫归航5优先[2589301.IB]，80w，95.07，国泰海通 冉雅婷 to 外贸信托朗瑞1号8期 孟亚琪2881131472； 25浦鑫归航5优先，2589301，20w，20260423，净价95.07/全价96.1423；国泰海通 田飞凡 to 外贸信托朗瑞1号8期，孟亚琪 | I79: 2589222.IB | J79: 25工元至诚惠银2C | K79: 100 | L79: =O88 -> 110.34 | M79: =+L79*K79/100 -> 110.34 | N79: 0.23511905 | O79: =+M79+N79 -> 110.57512 | P79: =ROUND(+O79/K79*100,3) -> 110.575 | Q79: =+P79*K79/100 -> 110.575 | R79: ="4/23, "&J79&"["&I79&"]，"&K79&"w，"&P79&"，国泰海通 冉雅婷 to 外贸信托朗瑞1号8期 孟亚琪2881131472" -> 4/23, 25工元至诚惠银2C[2589222.IB]，100w，110.575，国泰海通 冉雅婷 to 外贸信托朗瑞1号8期 孟亚琪2881131472
E80: =+E79+C80-D80 -> 10.54666 | I80: 2589350.IB | J80: 25浦鑫归航7C | K80: 150 | L80: =+Q88 -> 102.59 | M80: =+L80*K80/100 -> 153.885 | N80: =(N75-SUM(N77:N79)) -> 0.23511905 | O80: =+M80+N80 -> 154.12012 | P80: =ROUND(+O80/K80*100,3) -> 102.747 | Q80: =+P80*K80/100 -> 154.1205 | R80: ="4/23, "&J80&"["&I80&"]，"&K80&"w，"&P80&"，国泰海通 冉雅婷 to 粤财鹏雅10号第120期 王同博 QT员工号：3004238546" -> 4/23, 25浦鑫归航7C[2589350.IB]，150w，102.747，国泰海通 冉雅婷 to 粤财鹏雅10号第120期 王同博 QT员工号：3004238546
E81: =+E80+C81-D81 -> 10.54666 | I81: 2589301.IB | J81: 25浦鑫归航5优先 | K81: 80 | L81: 95.07 | P81: =+L81 -> 95.07 | Q81: =+P81*K81/100 -> 76.056 | R81: ="4/23, "&J81&"["&I81&"]，"&K81&"w，"&P81&"，国泰海通 冉雅婷 to 外贸信托朗瑞1号8期 孟亚琪2881131472" -> 4/23, 25浦鑫归航5优先[2589301.IB]，80w，95.07，国泰海通 冉雅婷 to 外贸信托朗瑞1号8期 孟亚琪2881131472
A82: 46139 | B82: 回款 | C82: 2465.7 | E82: =+E81+C82-D82 -> 2476.2467 | K82: =SUM(K77:K81) -> 550 | M82: =SUM(M77:M80) -> 502.135 | Q82: =SUM(Q77:Q81) -> 579.1785
A83: 46140 | B83: 元康29号赎回 | D83: 2301.3 | E83: =+E82+C83-D83 -> 174.94666 | F83: 4/24发出 | I83: 2589218.IB | J83: 25福鑫4C | K83: 40 | M83: =+L83*K83/100 -> 0 | N83: 0 | O83: 0 | P83: =ROUND(+O83/K83*100,3) -> 0 | Q83: =+P83*K83/100 -> 0 | R83: ="4/23, "&J83&"["&I83&"]，"&K83&"w，"&P83&"，国泰海通 冉雅婷 to 外贸信托朗瑞1号8期 孟亚琪2881131472" -> 4/23, 25福鑫4C[2589218.IB]，40w，0，国泰海通 冉雅婷 to 外贸信托朗瑞1号8期 孟亚琪2881131472
A84: 46141 | B84: 元康29号申购 | C84: 30 | E84: =+E83+C84-D84 -> 204.94666 | F84: 已发
A85: 46142 | B85: 支付费用 | D85: 82 | E85: =+E84+C85-D85 -> 122.94666
E86: =+E85+C86-D86 -> 122.94666 | J86: 25橙益22C | K86: =XIRR(K87:K88,J87:J88) -> 0.044956401 | L86: 25橙益23C | M86: =XIRR(M87:M88,L87:L88) -> 0.044906035 | N86: 25工元至诚惠银2C | O86: =XIRR(O87:O88,N87:N88) -> 0.050033101 | P86: 25浦鑫归航7C | Q86: =XIRR(Q87:Q88,P87:P88) -> 0.045007744
E87: =+E86+C87-D87 -> 122.94666 | J87: 45926 | K87: -100 | L87: 45926 | M87: -106 | N87: 45835 | O87: -106 | P87: 45923 | Q87: -100
A88: 46162 | B88: 回款 | C88: 113.2 | E88: =+E87+C88-D88 -> 236.14666 | J88: 46135 | K88: 102.55 | L88: 46135 | M88: 108.7 | N88: 46135 | O88: 110.34 | P88: 46135 | Q88: 102.59
E89: =+E88+C89-D89 -> 236.14666
E90: =+E89+C90-D90 -> 236.14666
E91: =+E90+C91-D91 -> 236.14666
E92: =+E91+C92-D92 -> 236.14666
E93: =+E92+C93-D93 -> 236.14666
E94: =+E93+C94-D94 -> 236.14666
E95: =+E94+C95-D95 -> 236.14666
E96: =+E95+C96-D96 -> 236.14666
E97: =+E96+C97-D97 -> 236.14666
E98: =+E97+C98-D98 -> 236.14666
E99: =+E98+C99-D99 -> 236.14666
E100: =+E99+C100-D100 -> 236.14666
E101: =+E100+C101-D101 -> 236.14666

Sheet 鹏雅119
A2: 日期 | B2: 现金流类型 | C2: 现金流入 | D2: 现金流出 | E2: 期末余额
A3: 46052 | B3: 元康1申购 | C3: 50 | E3: 50
B4: 元康9申购 | C4: 150 | E4: =+E3+C4-D4 -> 200
E5: =+E4+C5-D5 -> 200
A6: 46056 | B6: 25东裕7叔裕ABN001次 | D6: =190*1.032454 -> 196.16626 | E6: 3.8 | F6: 1、25东裕7叔裕ABN001次,082501056.IB,190w,103.2454,2-3，t+0，国泰海通 夏雪 QT号：3007305611to 粤财信托鹏雅10号119期 王同博 QT员工号：3004238546
A7: 46080 | B7: 元康盛景30号申购 | C7: 380 | E7: =+E6+C7-D7 -> 383.8
A8: 46083 | B8: 25美团美好ABN002次 | D8: 381 | E8: 2.3 | F8: 25美团美好ABN002次，082580682.IB，370w，103.101, 3-2，国泰海通 冉雅婷 QT号：2881971956 to 粤财信托鹏雅10号集合资金信托计划119期 王同博 QT员工号：3004238546
E9: =+E8+C9-D9 -> 2.3
E10: =+E9+C10-D10 -> 2.3
A11: 46104 | B11: 元康9追加 | C11: 1000 | E11: =+E10+C11-D11 -> 1002.3
A12: 46105 | B12: 26锦新小微ABN002次 | D12: 1000 | E12: =+E11+C12-D12 -> 2.3 | F12: 3/24，26锦新小微ABN002次，082680162,1000w，5.7%，一级缴款，鹏雅10期119号；ideal麻烦发粤财信托刘硕 13650996026
E13: =+E12+C13-D13 -> 2.3
A14: 46122 | B14: 元康17追加 | C14: 475 | E14: =+E13+C14-D14 -> 477.3
A15: 46122 | B15: 25美团美好ABN002次 | D15: =450*103.52/100 -> 465.84 | E15: =+E14+C15-D15 -> 11.46 | F15: 25美团美好ABN002次[082580682.IB]，450w，103.52，4月10日，国泰海通 冉雅婷 2881971956 to 粤财信托鹏雅10号119期 王同博 QT员工号：3004238546
E16: =+E15+C16-D16 -> 11.46
A17: 46127 | B17: 元康17号 | C17: 8 | E17: =+E16+C17-D17 -> 19.46
E18: =+E17+C18-D18 -> 19.46
B19: 信保基金 | D19: 16 | E19: =+E18+C19-D19 -> 3.46
E20: =+E19+C20-D20 -> 3.46
E21: =+E20+C21-D21 -> 3.46
A22: 46140 | B22: 元康17号 | C22: 700 | E22: =+E21+C22-D22 -> 703.46
A23: 46140 | B23: 元康1号申购 | C23: 3000 | E23: =+E22+C23-D23 -> 3703.46
E24: =+E23+C24-D24 -> 3703.46
A25: 46140 | B25: 24京东东裕3ABN002次 | D25: 741.1572 | E25: =+E24+C25-D25 -> 2962.3028 | F25: 4/28，24京东东裕3ABN002次[082480853.IB]，700w，105.8796，中信证券 to 粤财信托 王同博 3004238546
A26: 46140 | B26: 24东裕5仲裕ABN001次 | D26: 2093.332 | E26: =+E25+C26-D26 -> 868.9708 | F26: 4/28，24东裕5仲裕ABN001次[082481516.IB]，2000w，104.6666，中信证券 to 粤财信托 王同博 3004238546
A27: 46141 | B27: 次级（26美团美好ABN001次，082680129） | D27: 804 | E27: =+E26+C27-D27 -> 64.9708 | F27: 4/29，26美团美好ABN001次，082680129.IB，800w，100.463，国泰海通 冉雅婷 to 粤财信托鹏雅10号119期 王同博 QT员工号：3004238546
E28: =+E27+C28-D28 -> 64.9708
A29: 46164 | B29: 元康17号申购 | C29: 1100 | E29: =+E28+C29-D29 -> 1164.9708
E30: =+E29+C30-D30 -> 1164.9708
A31: 46170 | B31: 25东裕7叔裕ABN001次 | C31: 200 | E31: =+E30+C31-D31 -> 1364.9708
E32: =+E31+C32-D32 -> 1364.9708
B33: 浩澜 | D33: 1000 | E33: =+E32+C33-D33 -> 364.9708
E34: =+E33+C34-D34 -> 364.9708
E35: =+E34+C35-D35 -> 364.9708
E36: =+E35+C36-D36 -> 364.9708
E37: =+E36+C37-D37 -> 364.9708
E38: =+E37+C38-D38 -> 364.9708
E39: =+E38+C39-D39 -> 364.9708
E40: =+E39+C40-D40 -> 364.9708
E41: =+E40+C41-D41 -> 364.9708

Sheet 鹏雅120
A2: 日期 | B2: 现金流类型 | C2: 现金流入 | D2: 现金流出 | E2: 期末余额
A3: 46052 | B3: 元康29申购 | C3: 300 | E3: 300
A4: 46052 | B4: 磐宙自有申购 | C4: 30 | E4: =+E3+C4-D4 -> 330
E5: =+E4+C5-D5 -> 330
A6: 46056 | B6: 25工元至诚普银3C | D6: =182*1.134147 -> 206.41475 | E6: =+E5+C6-D6 -> 123.58525 | F6: 25工元至诚普银3C，2589168.IB，2-3，t+0，182w，113.4147，银河证券 赵恩聪 3007251238 to 粤财信托鹏雅10号120期 王同博 QT员工号：3004238546
E7: =+E6+C7-D7 -> 123.58525
E8: =+E7+C8-D8 -> 123.58525
A9: 46062 | B9: 元康29追加 | C9: 1850 | E9: =+E8+C9-D9 -> 1973.5852 | F9: 待定。先不打款
E10: =+E9+C10-D10 -> 1973.5852
E11: =+E10+C11-D11 -> 1973.5852
E12: =+E11+C12-D12 -> 1973.5852
E13: =+E12+C13-D13 -> 1973.5852 | H13: 证券名称 | I13: 交易份额 | J13: 交易日期 | K13: 交易价格 | L13: 交易金额 | M13: 补收益
A14: 46063 | B14: 23工元至诚1C | D14: =L14/10000 -> 117.8 | E14: =+E13+C14-D14 -> 1855.7852 | F14: 23工元至诚1C,2389064.IB,200w,58.9,2月10日，t+0，国泰海通 夏雪 to 粤财信托鹏雅10号120期 王同博 QT员工号：3004238546 | H14: 23工元至诚1C | I14: 200 | J14: 46063 | K14: =M25 -> 58.9 | L14: =K14*I14*100 -> 1178000 | N14: 2389064.IB | O14: =H14&","&N14&","&I14&"w"&","&K14&","&J14 -> 23工元至诚1C,2389064.IB,200w,58.9,46063
A15: 46063 | B15: 25兴瑞1C | D15: =L15/10000 -> 556.128 | E15: =+E14+C15-D15 -> 1299.6572 | F15: 25兴瑞1C,2589025.IB,720w,77.24,,2月10日，t+0，国泰海通 夏雪 to 粤财信托鹏雅10号120期 王同博 QT员工号：3004238546 | H15: 25兴瑞1C | I15: 720 | J15: 46063 | K15: =P24 -> 77.24 | L15: =K15*I15*100 -> 5561280 | N15: 2589025.IB | O15: =H15&","&N15&","&I15&"w"&","&K15&","&J15 -> 25兴瑞1C,2589025.IB,720w,77.24,46063
A16: 46063 | B16: 25浦鑫归航1C | D16: =L16/10000 -> 1243.6716 | E16: =+E15+C16-D16 -> 55.985646 | F16: 25浦鑫归航1C,2589031.IB,1200w,103.6393,,2月10日，t+0，国泰海通 夏雪 to 粤财信托鹏雅10号120期 王同博 QT员工号：3004238546 | H16: 25浦鑫归航1C | I16: 1200 | J16: 46063 | K16: =J29 -> 103.6393 | L16: =K16*I16*100 -> 12436716 | M16: =(I29-J29)*I16*100 -> 88884 | N16: 2589031.IB | O16: =H16&","&N16&","&I16&"w"&","&K16&","&J16 -> 25浦鑫归航1C,2589031.IB,1200w,103.6393,46063
E17: =+E16+C17-D17 -> 55.985646
E18: =+E17+C18-D18 -> 55.985646 | H18: 25中誉至诚3C | I18: 238 | J18: 46059 | K18: =M29 -> 104.458 | L18: =K18*I18*100 -> 2486100.4 | N18: 2589127.IB | O18: =H18&","&N18&","&I18&"w"&","&K18&","&J18 -> 25中誉至诚3C,2589127.IB,238w,104.458,46059
A19: 46079 | B19: 回款 | C19: 624 | E19: =+E18+C19-D19 -> 679.98565 | L19: =SUM(L10:L18) -> 21662096 | O19: 25中誉至诚3C,2589127.IB,238w,104.445,46058
E20: =+E19+C20-D20 -> 679.98565
A21: 46084 | B21: 提取至元康29号 | D21: 660 | E21: 17 | H21: 25中誉至诚1C | I21: =XIRR(I22:I24,$H$22:$H$24) -> 0.050038108 | L21: 23工元至诚1C | M21: =XIRR(M22:M25,$L$22:$L$25) -> 0.049973705 | O21: 25兴瑞1C | P21: =XIRR(P22:P24,$O$22:$O$24) -> 0.049964055
A22: 46094 | B22: 慧聚领航 | C22: 300 | E22: =+E21+C22-D22 -> 317 | H22: 45744 | I22: -103 | L22: 45008 | M22: -105 | O22: 45741 | P22: -105
E23: =+E22+C23-D23 -> 317 | H23: 46048 | I23: 100.9018 | L23: 45866 | M23: 26.8418 | O23: 46048 | P23: 32.31
A24: 46099 | B24: 磐宙提起 | D24: =30*1.045 -> 31.35 | E24: =+E23+C24-D24 -> 285.65 | H24: 46056 | I24: 6.38 | L24: 46048 | M24: 34.3671 | O24: =J15 -> 46063 | P24: 77.24
A25: 46099 | B25: 元康29号提取 | D25: 276.64 | E25: =+E24+C25-D25 -> 9.01 | L25: =J14 -> 46063 | M25: 58.9
E26: =+E25+C26-D26 -> 9.01
A27: 46105 | B27: 元康29追加 | C27: 1030 | E27: =+E26+C27-D27 -> 1039.01 | G27: 2800000 | H27: 25浦鑫归航1C | I27: =XIRR(I28:I29,$H$28:$H$29) -> 0.049951395 | J27: =XIRR(J28:J29,$H$28:$H$29) -> 0.041483602 | L27: 25中誉至诚3C | M27: =XIRR(M28:M29,$L$28:$L$29) -> 0.049968514
E28: =+E27+C28-D28 -> 1039.01 | G28: 1.0432 | H28: 45742 | I28: -100 | J28: =I28 -> -100 | L28: 45807 | M28: -101
A29: 46105 | B29: 25邮盈惠泽5C | D29: =490*1.069 -> 523.81 | E29: =+E28+C29-D29 -> 515.2 | F29: 3/24，2589249.IB 25邮盈惠泽5C 490W 净价/全价 106.9 国泰海通 to 粤财信托鹏雅10号120期 王同博 QT员工号：3004238546 | G29: =G27/G28 -> 2684049.1 | H29: =J16 -> 46063 | I29: 104.38 | J29: 103.6393 | L29: 46059 | M29: 104.458
E30: =+E29+C30-D30 -> 515.2 | G30: 2660000
A31: 46106 | B31: 26福鑫1C | D31: 200 | E31: =+E30+C31-D31 -> 315.2 | G31: =G30*G28 -> 2774912 | R31: =R37-T37 -> -9.09984
A32: 46106 | B32: 26福鑫2C | D32: 300 | E32: =+E31+C32-D32 -> 15.2 | H32: 4月初交易计划 | I32: 证券代码 | J32: 持仓规模 | K32: DC成本 | L32: 买入日期 | M32: 买入价格 | N32: 剩余本金（万元） | O32: 当前面值 | P32: 交易日期 | Q32: 交易价格 | R32: 交易金额（万元） | U32: 23中誉2C | V32: =XIRR(V33:V37,U33:U37) -> 0.04995046 | W32: 24浦鑫归航8C | X32: =XIRR(X33:X35,W33:W35) -> 0.049955294 | Y32: 25建欣1C | Z32: =XIRR(Z33:Z35,Y33:Y35) -> 0.049953172 | AA32: 25橙益4C | AB32: =XIRR(AB33:AB35,AA33:AA35) -> 0.050011542 | AC32: 25橙益8C | AD32: =XIRR(AD33:AD35,AC33:AC35) -> 0.049952939 | AE32: 25建欣1C | AF32: =XIRR(AF33:AF35,AE33:AE35) -> 0.049971989 | AH32: =XIRR(AH33:AH35,AG33:AG35) -> 0.050817969
E33: =+E32+C33-D33 -> 15.2 | G33: gtht | H33: 25建欣1C | I33: 2589057.IB | J33: 55800 | K33: 0.05 | L33: 45743 | M33: 105 | N33: 579.0366 | O33: 98.77 | P33: 46113 | Q33: 109.078 | R33: =+Q33*J33/10000 -> 608.65524 | S33: 25建欣1C[2589057.IB]，558w，109.078，4月1日，国泰海通 冉雅婷 2881971956 to 粤财鹏雅10号第120期 王同博 QT员工号：3004238546 | U33: 45027 | V33: =-M37 -> -107 | W33: =+L41 -> 45653 | X33: =-M41 -> -100 | Y33: =L33 -> 45743 | Z33: =-M33 -> -105 | AA33: =L34 -> 45772 | AB33: =-M34 -> -105 | AC33: =L35 -> 45805 | AD33: =-M35 -> -108 | AE33: =L36 -> 45743 | AF33: =-M36 -> -105 | AG33: 45986 | AH33: -112
A34: 46107 | B34: 回款 | C34: 258 | E34: =+E33+C34-D34 -> 273.2 | G34: gtht | H34: 25橙益4C | I34: 2589087.IB | J34: 42000 | K34: 0.05 | L34: 45772 | M34: 105 | N34: 436.944 | O34: 100 | P34: 46113 | Q34: 109.898 | R34: =+Q34*J34/10000 -> 461.5716 | S34: 25橙益4C[2589087.IB]，420w，109.898，4月1日，国泰海通 冉雅婷 2881971956 to 粤财鹏雅10号第120期 王同博 QT员工号：3004238546 | U34: 45714 | V34: 5.44 | W34: 46107 | X34: 33.58 | Y34: 46048 | Z34: 1.23 | AA34: =+P34 -> 46113 | AB34: 109.898 | AC34: =+P35 -> 46113 | AD34: 112.535 | AE34: 46048 | AF34: 1.23 | AG34: =AE34 -> 46048 | AH34: 1.23
A35: 46107 | B35: 26惠元3C（2689044） | D35: 169.6 | E35: =+E34+C35-D35 -> 103.6 | G35: gtht | H35: 25橙益8C | I35: 2589115.IB | J35: 28500 | K35: 0.05 | L35: 45805 | M35: 108 | N35: 307.8 | O35: 100 | P35: 46113 | Q35: 112.535 | R35: =+Q35*J35/10000 -> 320.72475 | S35: 25橙益8C[2589115.IB]，285w，112.535，4月1日，国泰海通 冉雅婷 2881971956 to 粤财鹏雅10号第120期 王同博 QT员工号：3004238546 | U35: 45895 | V35: 24.19 | W35: =+P41 -> 46121 | X35: 72.807 | Y35: =P33 -> 46113 | Z35: 109.078 | AE35: =+P36 -> 46113 | AF35: 109.08 | AG35: =AE35 -> 46113 | AH35: =-AH33*5%/365*(AG34-AG33)+(-AH33-AH34)*5%/365*(AG35-AG34)+-AH33-AH34 -> 112.70754
A36: 46112 | B36: 元康29号申购 | C36: 2150 | E36: =+E35+C36-D36 -> 2253.6 | G36: yh | H36: 25建欣1C | I36: 2589057.IB | J36: 71600 | K36: 0.05 | L36: 45743 | M36: 105 | N36: 793.1132 | O36: 98.77 | P36: 46113 | Q36: 112.70754 | R36: =+Q36*J36/10000 -> 806.98599 | S36: 25建欣1C[2589057.IB]，716w，112.70754109589，4月1日，银河证券 to 粤财鹏雅10号第120期 王同博 QT员工号：3004238546期 | U36: 46079 | V36: 22.18
A37: 46113 | B37: DC买回 | D37: 2198 | E37: =+E36+C37-D37 -> 55.6 | F37: 25建欣1C[2589057.IB]，558w，109.078，4月1日，国泰海通 冉雅婷 2881971956 to 粤财鹏雅10号第120期 王同博 QT员工号：3004238546；25橙益4C[2589087.IB]，420w，109.898，4月1日，国泰海通 冉雅婷 2881971956 to 粤财鹏雅10号第120期 王同博 QT员工号：3004238546；25橙益8C[2589115.IB]，285w，112.535，4月1日，国泰海通 冉雅婷 2881971956 to 粤财鹏雅10号第120期 王同博 QT员工号：3004238546；25建欣1C[2589057.IB]，716w，112.7075，4月1日，银河证券 to 粤财鹏雅10号第120期 王同博 QT员工号：3004238546 | G37: gtht | H37: 23中誉2C | I37: 2389095.IB | J37: 107100 | K37: 0.05 | L37: 45027 | M37: 107 | N37: 516.1149 | O37: 48.19 | P37: 46121 | Q37: 70.002342 | R37: =+Q37*J37/10000 -> 749.72508 | S37: 23中誉2C[2389095.IB]，1071w，70.0023417366947，4月9日，国泰海通 冉雅婷 2881971956 to 粤财鹏雅10号第120期 王同博 QT员工号：3004238546 | T37: =V37*J37/10000 -> 758.82492 | U37: =P37 -> 46121 | V37: 70.852
A38: 46119 | B38: 元康29追加 | C38: 750 | E38: =+E37+C38-D38 -> 805.6 | G38: gtht | H38: 25工元至诚普银3C | I38: 2589168.IB | J38: 35100 | K38: 0.05 | L38: 45832 | M38: 110 | N38: 381.8958 | O38: 100 | P38: 46121 | Q38: 114.33 | R38: =+Q38*J38/10000 -> 401.2983 | S38: 25工元至诚普银3C[2589168.IB]，351w，114.33，4月9日，国泰海通 冉雅婷 2881971956 to 粤财鹏雅10号第120期 王同博 QT员工号：3004238546
A39: 46119 | B39: 缴款 | D39: 140.4 | E39: =+E38+C39-D39 -> 665.2 | G39: 信达 | H39: 25建欣16C | I39: 2589486.IB | J39: 76800 | K39: 0.05 | L39: 46008 | M39: 104 | N39: 797.68576 | O39: 100 | P39: 46121 | Q39: 105.582 | R39: =+Q39*J39/10000 -> 810.86976 | S39: 25建欣16C[2589486.IB]，768w，105.58，4月9日，信达证券 to 粤财鹏雅10号第120期 王同博 QT员工号：3004238546 | U39: 25建欣16C | V39: =XIRR(V40:V41,U40:U41) -> 0.049973217 | W39: 25工元至诚普银3C | X39: =XIRR(X40:X41,W40:W41) -> 0.049970189 | Y39: 25建欣7C | Z39: =XIRR(Z40:Z41,Y40:Y41) -> 0.050021914 | AA39: 25橙益21C | AB39: =XIRR(AB40:AB41,AA40:AA41) -> 0.044965753 | AC39: 25建欣11C | AD39: =XIRR(AD40:AD41,AC40:AC41) -> 0.04996241
A40: 46120 | B40: 慧聚领航 | C40: =慧聚领航1号!D16 -> 2364 | E40: =+E39+C40-D40 -> 3029.2 | G40: 信达 | H40: 25建欣11C | I40: 2589247.IB | J40: 3000 | K40: 0.05 | L40: 45867 | M40: 102 | N40: 12.7 | O40: 100 | P40: 46121 | Q40: =AD41 -> 105.52 | R40: =+Q40*J40/10000 -> 31.656 | S40: 25建欣11C[2589247.IB]，30w，105.52，4月9日，信达证券 to 粤财鹏雅10号第120期 王同博 QT员工号：3004238546 | U40: =L39 -> 46008 | V40: =-M39 -> -104 | W40: =+L38 -> 45832 | X40: =-M38 -> -110 | Y40: =+L42 -> 45834 | Z40: =-M42 -> -103 | AA40: =L43 -> 45925 | AB40: =-M43 -> -100 | AC40: =L40 -> 45867 | AD40: =-M40 -> -102
E41: =+E40+C41-D41 -> 3029.2 | G41: gtht | H41: 24浦鑫归航8C | I41: 2489436.IB | J41: 50000 | K41: 0.05 | L41: 45653 | M41: 100 | N41: 478.55 | O41: 66.42 | P41: 46121 | Q41: 72.807 | R41: =+Q41*J41/10000 -> 364.035 | S41: 24浦鑫归航8C[2489436.IB]，500w，72.807，4月9日，国泰海通 冉雅婷 2881971956 to 粤财鹏雅10号第120期 王同博 QT员工号：3004238546 | T41: 暂不交易 | U41: =+P39 -> 46121 | V41: 105.582 | W41: =+P38 -> 46121 | X41: 114.33 | Y41: =P42 -> 46121 | Z41: 107.03 | AA41: =+P43 -> 46121 | AB41: 102.39 | AC41: =+P40 -> 46121 | AD41: 105.52
A42: 46121 | B42: 23中誉2C | D42: 750 | E42: =+E41+C42-D42 -> 2279.2 | F42: 23中誉2C[2389095.IB]，1071w，70.002，4月9日，国泰海通 冉雅婷 2881971956 to 粤财鹏雅10号第120期 王同博 QT员工号：3004238546； | G42: gtht | H42: 25建欣7C | I42: 2589216.IB | J42: 41300 | K42: 0.05 | L42: 45834 | M42: 103 | N42: 425.39 | O42: 100 | P42: 46121 | Q42: 107.03 | R42: =+Q42*J42/10000 -> 442.0339 | S42: 25建欣7C[2589216.IB]，413w，107.03，4月9日，国泰海通 冉雅婷 2881971956 to 粤财鹏雅10号第120期 王同博 QT员工号：3004238546 | T42: 暂不交易
A43: 46121 | B43: 25建欣16C-信达 | D43: 810.86976 | E43: =+E42+C43-D43 -> 1468.3302 | F43: 25建欣16C[2589486.IB]，768w，105.582，4月9日，信达证券 to 粤财鹏雅10号第120期 王同博 QT员工号：3004238546 | G43: gtht | H43: 25橙益21C | I43: 2589364.IB | J43: 9000 | K43: 0.045 | L43: 45925 | M43: 100 | N43: 90 | O43: 100 | P43: 46121 | Q43: 102.39 | R43: =+Q43*J43/10000 -> 92.151 | S43: 25橙益21C[2589364.IB]，90w，102.39，4月9日，国泰海通 冉雅婷 2881971956 to 粤财鹏雅10号第120期 王同博 QT员工号：3004238546 | T43: 暂不交易
A44: 46121 | B44: 25建欣11C | D44: 31.656 | E44: =+E43+C44-D44 -> 1436.6742 | F44: 25建欣11C[2589247.IB]，30w，105.52，4月9日，信达证券 to 粤财鹏雅10号第120期 王同博 QT员工号：3004238546 | R44: =SUM(R37:R43) -> 2891.769
A45: 46121 | B45: 25工元至诚普银3C | D45: 401.2983 | E45: =+E44+C45-D45 -> 1035.3759 | F45: 25工元至诚普银3C[2589168.IB]，351w，114.33，4月9日，国泰海通 冉雅婷 2881971956 to 粤财鹏雅10号第120期 王同博 QT员工号：3004238546
E46: =+E45+C46-D46 -> 1035.3759 | J46: 25建欣7C[2589216.IB]，413w，107.03，4月9日，国泰海通 冉雅婷 2881971956 to 粤财鹏雅10号第120期 王同博 QT员工号：3004238546
A47: 46121 | B47: 元康29号追加 | C47: 150 | E47: =+E46+C47-D47 -> 1185.3759 | J47: 25橙益21C[2589364.IB]，90w，102.39，4月9日，国泰海通 冉雅婷 2881971956 to 粤财鹏雅10号第120期 王同博 QT员工号：3004238546
A48: 46122 | B48: 25臻金2C | D48: 1120 | E48: =+E47+C48-D48 -> 65.37594 | F48: 2026/4/10+0 25臻金2C (2589159.IB) 交易面额1000w 价格112.0143 中信证券 出给粤财信托 王同博
E49: =+E48+C49-D49 -> 65.37594
E50: =+E49+C50-D50 -> 65.37594
E51: =+E50+C51-D51 -> 65.37594
E52: =+E51+C52-D52 -> 65.37594
A53: 46134 | B53: 元康29号追加 | C53: 210 | E53: =+E52+C53-D53 -> 275.37594
A54: 46135 | B54: 25浦鑫归航7C | D54: 154.1205 | E54: =+E53+C54-D54 -> 121.25544 | F54: 4/23, 25浦鑫归航7C[2589350.IB]，150w，102.747，国泰海通 冉雅婷 to 粤财鹏雅10号第120期 王同博 QT员工号：3004238546
E55: =+E54+C55-D55 -> 121.25544
A56: 46135 | B56: 25招元和萃5优先 | D56: 7.712965 | E56: =+E55+C56-D56 -> 113.54247 | F56: 25招元和萃5优先，2589181，65w，20260423，净价11.8477/全价11.8661；国泰海通 田飞凡 to 粤财信托鹏雅10号120期，王同博 | L56: 净价 | M56: 全价
A57: 46135 | B57: 25招元和萃5C | D57: 56.27 | E57: =+E56+C57-D57 -> 57.272475 | F57: 25招元和萃5C，2589182，50w，20260423，报价112.54；国泰海通 田飞凡 to 粤财信托鹏雅10号120期，王同博 | I57: 25浦鑫归航5优先，20w，票面2.3% | J57: 20 | K57: =20*L57/100 -> 19.014 | L57: =100-4.93 -> 95.07 | M57: 96.1423 | N57: =+M57*J57/100 -> 19.22846 | Q57: 23臻金2C
E58: =+E57+C58-D58 -> 57.272475 | I58: 25招元和萃5优先，65w，票面2.03% | J58: 65 | K58: =J58*L58/100 -> 7.701005 | L58: =2381.3877/201 -> 11.8477 | M58: 11.8661 | N58: =+M58*J58/100 -> 7.712965
A59: 46136 | B59: 25建欣1C | C59: 857.46825 | E59: =+E58+C59-D59 -> 914.74072 | F59: 4/24, 25建欣1C[2589057.IB]，750w，114.4557，粤财鹏雅10号第120期 王同博 QT员工号：3004238546 to 国泰海通 冉雅婷 | I59: 25招元和萃5C，50w | J59: 50 | K59: 55 | L59: 112.54 | M59: =+L59 -> 112.54 | N59: =+M59*J59/100 -> 56.27
A60: 46136 | B60: 25臻金3C | D60: 821.4 | E60: =+E59+C60-D60 -> 93.340725 | F60: 4/24, 25臻金3C[2589318.IB]，800w，102.675，国泰海通 冉雅婷 to 粤财鹏雅10号第120期 王同博 QT员工号：3004238546 | N60: =SUM(N57:N59) -> 83.211425
A61: 46136 | B61: 信保基金 | D61: 25.2 | E61: =+E60+C61-D61 -> 68.140725 | K61: =SUM(K57:K59) -> 81.715005
A62: 46139 | B62: 回款 | C62: 1298.8 | E62: =+E61+C62-D62 -> 1366.9407
A63: 46140 | B63: 元康29 | C63: 1500 | E63: =+E62+C63-D63 -> 2866.9407 | H63: 毛旸 | I63: 25浦鑫归航5优先 | J63: 80 | K63: =J63*L63/100 -> 76.056 | L63: =100-4.93 -> 95.07 | M63: 96.1423 | N63: =+M63*J63/100 -> 76.91384
A64: 46141 | B64: 23中誉至诚5C | D64: =841*119.02% -> 1000.9582 | E64: =+E63+C64-D64 -> 1865.9825 | F64: 4/29，23中誉至诚5C，2389446.IB，841w，119.02，国泰海通 冉雅婷 to 粤财鹏雅10号第120期 王同博 QT员工号：3004238546
A65: 46141 | B65: 23工元至诚8C | D65: =1400*131.12% -> 1835.68 | E65: =+E64+C65-D65 -> 30.302525 | F65: 4/29，23工元至诚8C，2389487.IB，1400w，131.12，国泰海通 冉雅婷 to 粤财鹏雅10号第120期 王同博 QT员工号：3004238546 | K65: 价格 | L65: 金额 | N65: 估值
E66: =+E65+C66-D66 -> 30.302525 | I66: 25建欣1C | J66: 750 | K66: =+N66 -> 114.4557 | L66: =+K66*J66/100 -> 858.41775 | N66: 114.4557
